Workbook

Sheet Для клиента
B5: Оценка проекта | D5: ='Sales (Итоги оценки)'!C4 -> P2P платформа
B6: В стоимость входит тестирование, работа менеджера
B7: В течение 3 месяцев мы бесплатно устраняем технические ошибки (техподдержка)
B8: Актуально на: 06.04.2026
B9: Команда проекта, человек | C9: Длительность проекта, часы | D9: Стоимость, $
B10: 8 | C10: 2182 | D10: 92367
B12: Специалисты | C12: Занятость на проекте, недели | D12: Занятость на проекте, часы
B13: Smart contract | C13: 3 | D13: 119
B14: Backend | C14: 10.2 | D14: 407
B15: Backend | C15: 10.9 | D15: 436
B16: Frontend | C16: 12.7 | D16: 509
B17: Project manager | C17: 3.8 | D17: 153
B18: DevOps | C18: 4.4 | D18: 176
B19: Аналитик | C19: 4.8 | D19: 193
B20: QA | C20: 4.8 | D20: 193
B23: DevOps
B24: Вид работ | C24: Задача | D24: Комментарий | E24: Длительность, часы
B25: DevOps | C25: Создание и настройка репозиториев | D25: Backend, Frontend, Contracts — структура, README, права доступа | E25: 10
B26: DevOps | C26: Настройка CI/CD pipelines | D26: Сборка, линтинг, тесты, деплой для всех репозиториев | E26: 20
B27: DevOps | C27: Настройка PostgreSQL | D27: Установка, конфигурация, резервное копирование | E27: 20
B28: DevOps | C28: Настройка Redis | D28: Кэш, очереди, сессии | E28: 20
B29: DevOps | C29: Настройка HashiCorp Vault | D29: Хранение секретов, ключей шифрования | E29: 20
B30: DevOps | C30: Настройка Nginx и доменов | D30: Reverse proxy, SSL, rate limiting, DNS | E30: 32
B31: DevOps | C31: Настройка мониторинга и алертинга | D31: Prometheus, Grafana, PagerDuty/Slack интеграция | E31: 32
B32: DevOps | C32: Настройка централизованного логирования | E32: 26
B34: Smart contract
B35: Вид работ | C35: Задача | D35: Комментарий | E35: Длительность, часы
B36: Smart contract | C36: Разработка EscrowFactory | D36: Создание прокси-контрактов, события, access control | E36: 16
B37: Smart contract | C37: Разработка Escrow Implementation | D37: Логика депозита, релиза, refund, referral link, resolveDispute, интеграция USDT | E37: 32
B38: Smart contract | C38: Написание unit и integration тестов | D38: Покрытие всех функций, happy path, edge cases, gas optimization | E38: 26
B39: Smart contract | C39: Деплой в testnet (Sepolia) | D39: Factory + Implementation, верификация в Etherscan | E39: 7
B40: Smart contract | C40: Деплой в mainnet | D40: Factory + Implementation, настройка мультисиг/Fireblocks | E40: 26
B41: Smart contract | C41: Аудит безопасности | D41: Внешний аудит, исправление найденных проблем | E41: 13
B43: Backend
B44: Вид работ | C44: Задача | D44: Комментарий | E44: Длительность, часы
B45: Backend | C45: Настройка инфраструктуры | D45: TypeORM (PostgreSQL), Redis, Bull Queue, валидация | E45: 32
B46: Backend | C46: Разработка Shared Layer | D46: Database Service, Cache Service, Queue Service, Auth Service | E46: 32
B47: Backend | C47: Разработка Blockchain Service | D47: Ethers.js интеграция, RPC, индексатор событий | E47: 32
B48: Backend | C48: Разработка Encryption Service | D48: AES-256 для шифрования реквизитов | E48: 20
B49: Backend | C49: Создание сущностей | D49: User (с полями реферальной программы: referrer_id, referrer_wallet, referral_code), Wallet, KycStatus, UserLevel — таблицы, связи, индексы | E49: 26
B50: Backend | C50: Разработка API | D50: Регистрация, авторизация (Web3 + JWT), профиль, привязка кошелька | E50: 39
B51: Backend | C51: Реализация уровней доступа | D51: Проверка прав, лимиты | E51: 32
B52: Backend | C52: Создание сущностей | D52: Order, Deal, EscrowContract — таблицы, связи | E52: 20
B53: Backend | C53: Разработка Order API | D53: CRUD ордеров, стакан, фильтрация, WebSocket для real-time | E53: 49
B54: Backend | C54: Разработка Deal API | D54: Инициация, деплой эскроу, обработка депозита, подтверждения | E54: 49
B55: Backend | C55: Реализация жизненного цикла сделки | D55: Таймауты, авто-отмена, релиз, комиссия | E55: 52
B56: Backend | C56: Реализация режима "Яма" | D56: Переговорные сделки, фиксация курса | E56: 52
C57: Backend (Monolith): Payment Module | E57: 0
B58: Backend | C58: Создание сущности PaymentDetails | D58: Таблица, шифрование | E58: 10
B59: Backend | C59: Разработка API | D59: CRUD реквизитов, передача в сделке после депозита | E59: 13
C60: Backend (Monolith): Dispute Module | E60: 0
B61: Backend | C61: Создание сущностей | D61: Dispute — таблицы, статусы | E61: 13
B62: Backend | C62: Разработка API | D62: Создание диспута, добавление доказательств, продление блокировки | E62: 32
B63: Backend | C63: Разработка Admin API | D63: Список диспутов, просмотр, принятие решения, вызов resolveDispute | E63: 32
C64: Backend (Monolith): rating Module | E64: 0
B65: Backend | C65: Создание сущностей | D65: Rating, RatingHistory | E65: 13
B66: Backend | C66: Разработка Rating Service | D66: Расчет рейтинга (сделки, отмены, диспуты, объем) | E66: 20
C67: Backend (Monolith): Analytics Module | E67: 0
B68: Backend | C68: Подключение стороннего сервиса аналитики | D68: Redash или др | E68: 10
B69: Backend | C69: API генерации реферальной ссылки | D69: Уникальный код, URL | E69: 10
B70: Backend | C70: API установки кошелька комиссий | D70: Валидация адреса | E70: 10
B71: Backend | C71: Привязка при регистрации | D71: Парсинг ?ref=, сохранение referrer_id/wallet | E71: 7
B72: Backend | C72: Интеграция со сделками | D72: Получение referrer_wallet при создании сделки, передача в контракт | E72: 20
B73: Backend | C73: Создание сущности ReferralReward | D73: Хранение истории выплат | E73: 10
B74: Backend | C74: API реферальной статистики | D74: Кол-во рефералов, сделок, сумма выплат, список | E74: 20
B75: Backend | C75: Обработка событий выплат | D75: Обновление статистики при выплате из контракта | E75: 13
B76: Backend | C76: Создание миграций | D76: Все таблицы с учетом реферальной программы: users (с полями referrer_id, referrer_wallet, referral_code), wallets, orders, deals, disputes, rating, referral_rewards и др. | E76: 32
B77: Backend | C77: Настройка Swagger/OpenAPI | D77: Автогенерация документации для всех endpoints | E77: 20
B78: Backend | C78: KYC Интеграция | D78: Регистрация в провайдере (SumSub/Onfido), вебхуки, SDK на frontend, обработка статусов | E78: 32
B79: Backend | C79: Чат Интеграция | D79: Регистрация в провайдере (Stream/PubNub), создание каналов, добавление участников, история | E79: 42
... B82: Backend | C82: уведомление о статусе сделки в телеграм бота | D82: при получении сообщений, при других сменах статуса, в бота куда подключится тейкер/мейкер придут сообщения. подключение опционально. авторизация через телегу тоже | E82: 20
B84: Frontend
B85: Вид работ | C85: Задача | D85: Комментарий | E85: Длительность, часы
B86: Frontend | C86: инициализация проекта | D86: верстка | E86: 52
C87: Rewards Module(Frontend): Referral Module | E87: 0
B88: Frontend | C88: Раздел в ЛК | D88: правки верстки | E88: 13
B89: Frontend | C89: Таблица сделок | D89: Таблица сделок рефералов, пагинация/фильтры | E89: 13
B90: Frontend | C90: Интеграция API | D90: Интеграция получения ссылки, интеграция сохранения кошелька, Интеграция статистики | E90: 20
C91: Frontend: Страницы | E91: 0
B92: Frontend | C92: Страница Авторизации | D92: Подключение кошелька, подпись сообщения, JWT | E92: 20
B93: Frontend | C93: Страница Профиля | D93: Информация, KYC статус, кошельки, реквизиты, рейтинг, рефералы | E93: 32
B94: Frontend | C94: Страница Стакана (Order Book) | D94: Три колонки (Sell/Pit/Buy), фильтры, WebSocket, карточки ордеров | E94: 58
B95: Frontend | C95: Страница Создания Ордера и управление объявлениями | D95: Тип (FIXED/PIT), направление, валюта, сумма, цена, банки, реквизиты | E95: 32
B96: Frontend | C96: Страница Сделки | D96: Информационная панель, шаги, депозит, подтверждения, чат, диспут | E96: 97
B97: Frontend | C97: Страница "Яма" (Pit) | D97: Чат, предложение курса, принятие, фиксация | E97: 13
B98: Frontend | C98: Страница Истории Сделок | D98: Список, фильтры, детальная информация | E98: 10
C99: Frontend: Админ-панель | E99: 0
B100: Frontend | C100: Layout и Dashboard | D100: Сайдбар, навигация, статистика, метрики | E100: 64
B101: Frontend | C101: Управление пользователями | D101: Список, фильтры, детали профиля, KYC, действия | E101: 0
B102: Frontend | C102: Управление ордерами и сделками | D102: Просмотр всех ордеров и сделок | E102: 0
B103: Frontend | C103: Управление диспутами | D103: Список, детали, доказательства, форма решения | E103: 0
C104: Frontend: Интеграция с API | E104: 0
B105: Frontend | C105: Интеграция WebSocket | D105: Стакан, уведомления, обработка ошибок | E105: 20
B106: Frontend | C106: KYC Интеграция | D106: Изучение документации КУС | E106: 13
B107: Frontend | C107: Чат Интеграция | D107: Изучение документации чата | E107: 13
D108: Адаптив | E108: 0
B109: Frontend | C109: Доработка интерфейсов под мобильные устройства | E109: 45
B111: QA
B112: Вид работ | C112: Задача | D112: Комментарий | E112: Длительность, часы
B113: QA | C113: Интеграционное тестирование | D113: E2E: регистрация, создание ордера, сделка happy path, отмена, диспут, Pit на testnet | E113: 193
...

Sheet Sales (Итоги оценки)
B1: ⭠ Инструкция к заполнению (нажми "+")
B2: Sales 1. Заполняется Sales менеджером, после оценки проекта и настройки коэфицентов (делает PM). 2. Заполняются только ячейки закрашеные зеленым цветом. 3. Вноситься % реферальный по проекту, если такой есть. (% sales manager заложен в маржу проекта) 4. Вноситься маржа по каждому разработчику в столбце L. | F2: PM 1. Заполняет продолжительность проекта в ячейке С21 в соответсвии с предпологаемой продолжительностью работ на проекте. (Сколько проект будет длиться в фактических неделях) 2. Заполняет название проекта, ячейка С6. И прикладывает ссылки на маеты и тз (ячейки С7 и С8). 3. Схематично, на таймлайне, отрисовывает ход проекта в недельном выражении. Какие работы удит паралельно или последовательно. Учитывая прзаднечные, выходные, и отпуска.
B4: Проект: | C4: P2P платформа | E4: Проектная команда/тип работ: | F4: Продолжительность работ в неделях | G4: Продолжительность работ в днях | H4: Продолжительность работ в часах | I4: Себестоимость | J4: Стоимость работ | K4: Ставка на клиенте | L4: Ставка на руки | M4: Закладываемая маржа на разработчика (%)
B5: Ссылка на макеты | E5: Итого: | F5: =SUM(F6:F19) -> 54.536 | G5: =F5*5 -> 272.68 | H5: =G5*8 -> 2181.44 | I5: =SUM(I6:I19) -> 48875.2 | J5: =SUM(J6:J19) -> 92366.933 | M5: =((C9/(C14/100+1))-SUM(I6:I19))/(C9/(C14/100+1)) -> 0.47085826
B6: Ссылка на ТЗ
E7: ='PM (Расчеты)'!B6 -> Project manager | F7: ='PM (Расчеты)'!I6 -> 3.816 | G7: =F7*5 -> 19.08 | H7: =G7*8 -> 152.64 | I7: ='PM (Расчеты)'!J6 -> 2289.6 | J7: =('PM (Расчеты)'!J6/(1-M7)) -> 4579.2 | K7: ='PM (Расчеты)'!D6/(100%-M7) -> 30 | L7: ='PM (Расчеты)'!D6 -> 15 | M7: 0.5
B8: Стоимость проекта | E8: ='PM (Расчеты)'!B7 -> DevOps | F8: ='PM (Расчеты)'!I7 -> 4.4 | G8: =F8*5 -> 22 | H8: =G8*8 -> 176 | I8: ='PM (Расчеты)'!J7 -> 4400 | J8: =('PM (Расчеты)'!J7/(1-M8)) -> 8800 | K8: ='PM (Расчеты)'!D7/(100%-M8) -> 50 | L8: ='PM (Расчеты)'!D7 -> 25 | M8: 0.5
B9: Стоимость проекта: | C9: =SUM(J6:J19)*(C14/100+1) -> 92366.933 | E9: ='PM (Расчеты)'!B8 -> Smart contract | F9: ='PM (Расчеты)'!I8 -> 2.96 | G9: =F9*5 -> 14.8 | H9: =G9*8 -> 118.4 | I9: ='PM (Расчеты)'!J8 -> 3552 | J9: =('PM (Расчеты)'!J8/(1-M9)) -> 5920 | K9: ='PM (Расчеты)'!D8/(100%-M9) -> 50 | L9: ='PM (Расчеты)'!D8 -> 30 | M9: 0.4
B10: Маржинальность проекта: | C10: =M5 -> 0.47085826 | E10: ='PM (Расчеты)'!B9 -> Backend | F10: ='PM (Расчеты)'!I9 -> 10.16 | G10: =F10*5 -> 50.8 | H10: =G10*8 -> 406.4 | I10: ='PM (Расчеты)'!J9 -> 12598.4 | J10: =('PM (Расчеты)'!J9/(1-M10)) -> 20997.333 | K10: ='PM (Расчеты)'!D9/(100%-M10) -> 51.666667 | L10: ='PM (Расчеты)'!D9 -> 31 | M10: 0.4
E11: ='PM (Расчеты)'!B10 -> Backend | F11: ='PM (Расчеты)'!I10 -> 10.88 | G11: =F11*5 -> 54.4 | H11: =G11*8 -> 435.2 | I11: ='PM (Расчеты)'!J10 -> 9139.2 | J11: =('PM (Расчеты)'!J10/(1-M11)) -> 18278.4 | K11: ='PM (Расчеты)'!D10/(100%-M11) -> 42 | L11: ='PM (Расчеты)'!D10 -> 21 | M11: 0.5
E12: ='PM (Расчеты)'!B11 -> Frontend | F12: ='PM (Расчеты)'!I11 -> 12.72 | G12: =F12*5 -> 63.6 | H12: =G12*8 -> 508.8 | I12: ='PM (Расчеты)'!J11 -> 10176 | J12: =('PM (Расчеты)'!J11/(1-M12)) -> 20352 | K12: ='PM (Расчеты)'!D11/(100%-M12) -> 40 | L12: ='PM (Расчеты)'!D11 -> 20 | M12: 0.5
B13: % Sales | C13: Включен в маржу | E13: ='PM (Расчеты)'!B12 -> QA | F13: ='PM (Расчеты)'!I12 -> 4.8 | G13: =F13*5 -> 24 | H13: =G13*8 -> 192 | I13: ='PM (Расчеты)'!J12 -> 2880 | J13: =('PM (Расчеты)'!J12/(1-M13)) -> 5760 | K13: ='PM (Расчеты)'!D12/(100%-M13) -> 30 | L13: ='PM (Расчеты)'!D12 -> 15 | M13: 0.5
B14: % другое | C14: 0 | E14: Аналитик | F14: ='PM (Расчеты)'!I13 -> 4.8 | G14: =F14*5 -> 24 | H14: =G14*8 -> 192 | I14: ='PM (Расчеты)'!J13 -> 3840 | J14: =('PM (Расчеты)'!J13/(1-M14)) -> 7680 | K14: ='PM (Расчеты)'!D13/(100%-M14) -> 40 | L14: ='PM (Расчеты)'!D13 -> 20 | M14: 0.5
B16: Продолжительность раб. часов/дней/недель:
B17: Часов | C17: =H5 -> 2181.44
B18: Дней | C18: =C19*5 -> 5
B19: Недель | C19: 1
E21: Хронология проекта (необходимо учесть выходные, праздничные и отпуск) | F21: 1 неделя | G21: 5 недель | H21: 6 недель | I21: 7 недель | J21: 8 недель | M21: 9 недель
E22: Работы по дизайну:
E23: Работы по фронтенду:
E24: Работы по бекенду:
E25: Работы по смарт контрактам
E26: Работы менеджера:
E27: Работы тестировщика:

Sheet Оценка
B2: Инструкция к заполнению: 1. Задачи оцениваются в днях/полу днях. 2. Для каждого типа работ указывает этот тип работ в столбце B. 3. Для каждого типа работ на проекте проставляем кто будет выполнять эту работу в столбце А (специалист 1,2 и т.д.) 4. Если задача занимает больше 5 дней. Ее необходимо разделить на более мелкие подзадачи 5. Задачи по фронтенду должны сразу включать в себя работы по интеграции с бэкендом 6. При нажатии на "+" - раскрывается разбивка по выбранным специалистам. Сколько на каждого выделено время на проекте. Можно использовать для разбивки работ для команды. 7. Во вкладке "Чек лист Задач" - можно ознакомиться с типовыми задачами. О которых можно было забыть. Оценка производится в полу днях, а не в часах, в связи с тем, что между задачами происходит переключение. Меняется фокус и скорость работы. Человек не робот, не работает максимально эффективно над каждой задачей. Такой подход снижает нагрузку на команду и повышает точность планирования, так как легче учитывать погрешности в рамках дня, а не точного количества часов, которые могут варьироваться из-за перерывов или непредвиденных факторов.
A3: ⭠ Инструкция к заполнению (нажми "+")
B4: Дни минимум | C4: Дни максимум | D4: Недель с коф. | F4: Дни минимум | G4: Дни максимум | H4: Недель с коф.
A5: 1 | B5: =SUMPRODUCT(($A12:$A1002 = 1) * (F12:F1002) * IF(LEN('Оценка'!$E$12:$E1002) = 0, 1, IF('Оценка'!$E$12:$E1002 = 0, 1, 'Оценка'!$E$12:$E1002))) -> 10.5 | C5: =SUMPRODUCT(($A12:$A1002 = 1) * (G12:G1002) * IF(LEN('Оценка'!$E$12:$E1002) = 0, 1, IF('Оценка'!$E$12:$E1002 = 0, 1, 'Оценка'!$E$12:$E1002))) -> 17 | D5: ='PM (Расчеты)'!I7 -> 4.4 | E5: 7 | F5: =SUMPRODUCT(($A12:$A1002 = 7) * ('Оценка'!F12:F1002) * IF(LEN('Оценка'!$E$12:$E1002) = 0, 1, IF('Оценка'!$E$12:$E1002 = 0, 1, 'Оценка'!$E$12:$E1002))) -> 15 | G5: =SUMPRODUCT(($A12:$A1002 = 7) * ('Оценка'!G12:G1002) * IF(LEN('Оценка'!$E$12:$E1002) = 0, 1, IF('Оценка'!$E$12:$E1002 = 0, 1, 'Оценка'!$E$12:$E1002))) -> 15 | H5: ='PM (Расчеты)'!I13 -> 4.8
A6: 2 | B6: =SUMPRODUCT(($A12:$A1002 = 2) * ('Оценка'!F12:F1002) * IF(LEN('Оценка'!$E$12:$E1002) = 0, 1, IF('Оценка'!$E$12:$E1002 = 0, 1, 'Оценка'!$E$12:$E1002))) -> 8 | C6: =SUMPRODUCT(($A12:$A1002 = 2) * ('Оценка'!G12:G1002) * IF(LEN('Оценка'!$E$12:$E1002) = 0, 1, IF('Оценка'!$E$12:$E1002 = 0, 1, 'Оценка'!$E$12:$E1002))) -> 10.5 | D6: ='PM (Расчеты)'!I8 -> 2.96 | E6: 8 | F6: =SUMPRODUCT(($A12:$A1002 = 8) * ('Оценка'!F12:F1002) * IF(LEN('Оценка'!$E$12:$E1002) = 0, 1, IF('Оценка'!$E$12:$E1002 = 0, 1, 'Оценка'!$E$12:$E1002))) -> 0 | G6: =SUMPRODUCT(($A12:$A1002 = 8) * ('Оценка'!G12:G1002) * IF(LEN('Оценка'!$E$12:$E1002) = 0, 1, IF('Оценка'!$E$12:$E1002 = 0, 1, 'Оценка'!$E$12:$E1002))) -> 0 | H6: ='PM (Расчеты)'!I14 -> 0
A7: 3 | B7: =SUMPRODUCT(($A12:$A1002 = 3) * ('Оценка'!F12:F1002) * IF(LEN('Оценка'!$E$12:$E1002) = 0, 1, IF('Оценка'!$E$12:$E1002 = 0, 1, 'Оценка'!$E$12:$E1002))) -> 24.5 | C7: =SUMPRODUCT(($A12:$A1002 = 3) * ('Оценка'!G12:G1002) * IF(LEN('Оценка'!$E$12:$E1002) = 0, 1, IF('Оценка'!$E$12:$E1002 = 0, 1, 'Оценка'!$E$12:$E1002))) -> 39 | D7: ='PM (Расчеты)'!I9 -> 10.16 | E7: 9 | F7: =SUMPRODUCT(($A12:$A1002 = 9) * ('Оценка'!F12:F1002) * IF(LEN('Оценка'!$E$12:$E1002) = 0, 1, IF('Оценка'!$E$12:$E1002 = 0, 1, 'Оценка'!$E$12:$E1002))) -> 0 | G7: =SUMPRODUCT(($A12:$A1002 = 9) * ('Оценка'!G12:G1002) * IF(LEN('Оценка'!$E$12:$E1002) = 0, 1, IF('Оценка'!$E$12:$E1002 = 0, 1, 'Оценка'!$E$12:$E1002))) -> 0 | H7: ='PM (Расчеты)'!I15 -> 0
A8: 4 | B8: =SUMPRODUCT(($A12:$A1002 = 4) * ('Оценка'!F12:F1002) * IF(LEN('Оценка'!$E$12:$E1002) = 0, 1, IF('Оценка'!$E$12:$E1002 = 0, 1, 'Оценка'!$E$12:$E1002))) -> 26.5 | C8: =SUMPRODUCT(($A12:$A1002 = 4) * ('Оценка'!G12:G1002) * IF(LEN('Оценка'!$E$12:$E1002) = 0, 1, IF('Оценка'!$E$12:$E1002 = 0, 1, 'Оценка'!$E$12:$E1002))) -> 41.5 | D8: па | E8: 10 | F8: =SUMPRODUCT(($A12:$A1002 = 10) * ('Оценка'!F12:F1002) * IF(LEN('Оценка'!$E$12:$E1002) = 0, 1, IF('Оценка'!$E$12:$E1002 = 0, 1, 'Оценка'!$E$12:$E1002))) -> 0 | G8: =SUMPRODUCT(($A12:$A1002 = 10) * ('Оценка'!G12:G1002) * IF(LEN('Оценка'!$E$12:$E1002) = 0, 1, IF('Оценка'!$E$12:$E1002 = 0, 1, 'Оценка'!$E$12:$E1002))) -> 0 | H8: ='PM (Расчеты)'!I16 -> 0
A9: 5 | B9: =SUMPRODUCT(($A12:$A1002 = 5) * ('Оценка'!F12:F1002) * IF(LEN('Оценка'!$E$12:$E1002) = 0, 1, IF('Оценка'!$E$12:$E1002 = 0, 1, 'Оценка'!$E$12:$E1002))) -> 35 | C9: =SUMPRODUCT(($A12:$A1002 = 5) * ('Оценка'!G12:G1002) * IF(LEN('Оценка'!$E$12:$E1002) = 0, 1, IF('Оценка'!$E$12:$E1002 = 0, 1, 'Оценка'!$E$12:$E1002))) -> 44.5 | D9: ='PM (Расчеты)'!I11 -> 12.72 | E9: 11 | F9: =SUMPRODUCT(($A12:$A1002 = 11) * ('Оценка'!F12:F1002) * IF(LEN('Оценка'!$E$12:$E1002) = 0, 1, IF('Оценка'!$E$12:$E1002 = 0, 1, 'Оценка'!$E$12:$E1002))) -> 0 | G9: =SUMPRODUCT(($A12:$A1002 = 11) * ('Оценка'!G12:G1002) * IF(LEN('Оценка'!$E$12:$E1002) = 0, 1, IF('Оценка'!$E$12:$E1002 = 0, 1, 'Оценка'!$E$12:$E1002))) -> 0 | H9: ='PM (Расчеты)'!I17 -> 0
A10: 6 | B10: =SUMPRODUCT(($A12:$A1002 = 6) * ('Оценка'!F12:F1002) * IF(LEN('Оценка'!$E$12:$E1002) = 0, 1, IF('Оценка'!$E$12:$E1002 = 0, 1, 'Оценка'!$E$12:$E1002))) -> 15 | C10: =SUMPRODUCT(($A12:$A1002 = 6) * ('Оценка'!G12:G1002) * IF(LEN('Оценка'!$E$12:$E1002) = 0, 1, IF('Оценка'!$E$12:$E1002 = 0, 1, 'Оценка'!$E$12:$E1002))) -> 15 | D10: ='PM (Расчеты)'!I12 -> 4.8 | E10: 12 | F10: =SUMPRODUCT(($A12:$A1002 = 12) * ('Оценка'!F12:F1002) * IF(LEN('Оценка'!$E$12:$E1002) = 0, 1, IF('Оценка'!$E$12:$E1002 = 0, 1, 'Оценка'!$E$12:$E1002))) -> 0 | G10: =SUMPRODUCT(($A12:$A1002 = 12) * ('Оценка'!G12:G1002) * IF(LEN('Оценка'!$E$12:$E1002) = 0, 1, IF('Оценка'!$E$12:$E1002 = 0, 1, 'Оценка'!$E$12:$E1002))) -> 0 | H10: ='PM (Расчеты)'!I18 -> 0
A11: Распределение работ | B11: Вид работ | C11: Задача | D11: Комментарий | F11: Минимальная оценка дни (первичные данные) | G11: Максимальная оценка дни (первичные данные) | H11: Итоговые значения с учетом коэффициентов
C12: DevOps: Инфраструктура | H12: =IF(OR(ISBLANK('Оценка'!F12), ISBLANK('Оценка'!G12)), "", (AVERAGE( ( ('Оценка'!F12 + 4*AVERAGE('Оценка'!F12:G12) + 'Оценка'!G12)/6 - 2*(('Оценка'!G12 - 'Оценка'!F12)/6) )/5 , ( ('Оценка'!F12 + 4*AVERAGE('Оценка'!F12:G12) + 'Оценка'!G12)/6 + 2*(('Оценка'!G12 - 'Оценка'!F12)/6) )/5 ) * ( ( ('PM (Расчеты)'!$C$22/8 + 'PM (Расчеты)'!$C$23/40) + 'PM (Расчеты)'!$C$21/100 + 'PM (Расчеты)'!$C$25/100 + 'PM (Расчеты)'!$C$26/100 ) + 1 ))*5)
A13: 1 | B13: DevOps | C13: Создание и настройка репозиториев | D13: Backend, Frontend, Contracts — структура, README, права доступа | F13: 0.5 | G13: 1 | H13: =IF(OR(ISBLANK('Оценка'!F13), ISBLANK('Оценка'!G13)), "", (AVERAGE( ( ('Оценка'!F13 + 4*AVERAGE('Оценка'!F13:G13) + 'Оценка'!G13)/6 - 2*(('Оценка'!G13 - 'Оценка'!F13)/6) )/5 , ( ('Оценка'!F13 + 4*AVERAGE('Оценка'!F13:G13) + 'Оценка'!G13)/6 + 2*(('Оценка'!G13 - 'Оценка'!F13)/6) )/5 ) * ( ( ('PM (Расчеты)'!$C$22/8 + 'PM (Расчеты)'!$C$23/40) + 'PM (Расчеты)'!$C$21/100 + 'PM (Расчеты)'!$C$25/100 + 'PM (Расчеты)'!$C$26/100 ) + 1 ))*5) -> 1.2
A14: 1 | B14: DevOps | C14: Настройка CI/CD pipelines | D14: Сборка, линтинг, тесты, деплой для всех репозиториев | F14: 1 | G14: 2 | H14: =IF(OR(ISBLANK('Оценка'!F14), ISBLANK('Оценка'!G14)), "", (AVERAGE( ( ('Оценка'!F14 + 4*AVERAGE('Оценка'!F14:G14) + 'Оценка'!G14)/6 - 2*(('Оценка'!G14 - 'Оценка'!F14)/6) )/5 , ( ('Оценка'!F14 + 4*AVERAGE('Оценка'!F14:G14) + 'Оценка'!G14)/6 + 2*(('Оценка'!G14 - 'Оценка'!F14)/6) )/5 ) * ( ( ('PM (Расчеты)'!$C$22/8 + 'PM (Расчеты)'!$C$23/40) + 'PM (Расчеты)'!$C$21/100 + 'PM (Расчеты)'!$C$25/100 + 'PM (Расчеты)'!$C$26/100 ) + 1 ))*5) -> 2.4
A15: 1 | B15: DevOps | C15: Настройка PostgreSQL | D15: Установка, конфигурация, резервное копирование | F15: 1 | G15: 2 | H15: =IF(OR(ISBLANK('Оценка'!F15), ISBLANK('Оценка'!G15)), "", (AVERAGE( ( ('Оценка'!F15 + 4*AVERAGE('Оценка'!F15:G15) + 'Оценка'!G15)/6 - 2*(('Оценка'!G15 - 'Оценка'!F15)/6) )/5 , ( ('Оценка'!F15 + 4*AVERAGE('Оценка'!F15:G15) + 'Оценка'!G15)/6 + 2*(('Оценка'!G15 - 'Оценка'!F15)/6) )/5 ) * ( ( ('PM (Расчеты)'!$C$22/8 + 'PM (Расчеты)'!$C$23/40) + 'PM (Расчеты)'!$C$21/100 + 'PM (Расчеты)'!$C$25/100 + 'PM (Расчеты)'!$C$26/100 ) + 1 ))*5) -> 2.4
A16: 1 | B16: DevOps | C16: Настройка Redis | D16: Кэш, очереди, сессии | F16: 1 | G16: 2 | H16: =IF(OR(ISBLANK('Оценка'!F16), ISBLANK('Оценка'!G16)), "", (AVERAGE( ( ('Оценка'!F16 + 4*AVERAGE('Оценка'!F16:G16) + 'Оценка'!G16)/6 - 2*(('Оценка'!G16 - 'Оценка'!F16)/6) )/5 , ( ('Оценка'!F16 + 4*AVERAGE('Оценка'!F16:G16) + 'Оценка'!G16)/6 + 2*(('Оценка'!G16 - 'Оценка'!F16)/6) )/5 ) * ( ( ('PM (Расчеты)'!$C$22/8 + 'PM (Расчеты)'!$C$23/40) + 'PM (Расчеты)'!$C$21/100 + 'PM (Расчеты)'!$C$25/100 + 'PM (Расчеты)'!$C$26/100 ) + 1 ))*5) -> 2.4
A17: 1 | B17: DevOps | C17: Настройка HashiCorp Vault | D17: Хранение секретов, ключей шифрования | F17: 1 | G17: 2 | H17: =IF(OR(ISBLANK('Оценка'!F17), ISBLANK('Оценка'!G17)), "", (AVERAGE( ( ('Оценка'!F17 + 4*AVERAGE('Оценка'!F17:G17) + 'Оценка'!G17)/6 - 2*(('Оценка'!G17 - 'Оценка'!F17)/6) )/5 , ( ('Оценка'!F17 + 4*AVERAGE('Оценка'!F17:G17) + 'Оценка'!G17)/6 + 2*(('Оценка'!G17 - 'Оценка'!F17)/6) )/5 ) * ( ( ('PM (Расчеты)'!$C$22/8 + 'PM (Расчеты)'!$C$23/40) + 'PM (Расчеты)'!$C$21/100 + 'PM (Расчеты)'!$C$25/100 + 'PM (Расчеты)'!$C$26/100 ) + 1 ))*5) -> 2.4
A18: 1 | B18: DevOps | C18: Настройка Nginx и доменов | D18: Reverse proxy, SSL, rate limiting, DNS | F18: 2 | G18: 3 | H18: =IF(OR(ISBLANK('Оценка'!F18), ISBLANK('Оценка'!G18)), "", (AVERAGE( ( ('Оценка'!F18 + 4*AVERAGE('Оценка'!F18:G18) + 'Оценка'!G18)/6 - 2*(('Оценка'!G18 - 'Оценка'!F18)/6) )/5 , ( ('Оценка'!F18 + 4*AVERAGE('Оценка'!F18:G18) + 'Оценка'!G18)/6 + 2*(('Оценка'!G18 - 'Оценка'!F18)/6) )/5 ) * ( ( ('PM (Расчеты)'!$C$22/8 + 'PM (Расчеты)'!$C$23/40) + 'PM (Расчеты)'!$C$21/100 + 'PM (Расчеты)'!$C$25/100 + 'PM (Расчеты)'!$C$26/100 ) + 1 ))*5) -> 4
A19: 1 | B19: DevOps | C19: Настройка мониторинга и алертинга | D19: Prometheus, Grafana, PagerDuty/Slack интеграция | F19: 2 | G19: 3 | H19: =IF(OR(ISBLANK('Оценка'!F19), ISBLANK('Оценка'!G19)), "", (AVERAGE( ( ('Оценка'!F19 + 4*AVERAGE('Оценка'!F19:G19) + 'Оценка'!G19)/6 - 2*(('Оценка'!G19 - 'Оценка'!F19)/6) )/5 , ( ('Оценка'!F19 + 4*AVERAGE('Оценка'!F19:G19) + 'Оценка'!G19)/6 + 2*(('Оценка'!G19 - 'Оценка'!F19)/6) )/5 ) * ( ( ('PM (Расчеты)'!$C$22/8 + 'PM (Расчеты)'!$C$23/40) + 'PM (Расчеты)'!$C$21/100 + 'PM (Расчеты)'!$C$25/100 + 'PM (Расчеты)'!$C$26/100 ) + 1 ))*5) -> 4
A20: 1 | B20: DevOps | C20: Настройка централизованного логирования | F20: 2 | G20: 2 | H20: =IF(OR(ISBLANK('Оценка'!F20), ISBLANK('Оценка'!G20)), "", (AVERAGE( ( ('Оценка'!F20 + 4*AVERAGE('Оценка'!F20:G20) + 'Оценка'!G20)/6 - 2*(('Оценка'!G20 - 'Оценка'!F20)/6) )/5 , ( ('Оценка'!F20 + 4*AVERAGE('Оценка'!F20:G20) + 'Оценка'!G20)/6 + 2*(('Оценка'!G20 - 'Оценка'!F20)/6) )/5 ) * ( ( ('PM (Расчеты)'!$C$22/8 + 'PM (Расчеты)'!$C$23/40) + 'PM (Расчеты)'!$C$21/100 + 'PM (Расчеты)'!$C$25/100 + 'PM (Расчеты)'!$C$26/100 ) + 1 ))*5) -> 3.2
C21: Смарт-контракты | H21: =IF(OR(ISBLANK('Оценка'!F21), ISBLANK('Оценка'!G21)), "", (AVERAGE( ( ('Оценка'!F21 + 4*AVERAGE('Оценка'!F21:G21) + 'Оценка'!G21)/6 - 2*(('Оценка'!G21 - 'Оценка'!F21)/6) )/5 , ( ('Оценка'!F21 + 4*AVERAGE('Оценка'!F21:G21) + 'Оценка'!G21)/6 + 2*(('Оценка'!G21 - 'Оценка'!F21)/6) )/5 ) * ( ( ('PM (Расчеты)'!$C$22/8 + 'PM (Расчеты)'!$C$23/40) + 'PM (Расчеты)'!$C$21/100 + 'PM (Расчеты)'!$C$25/100 + 'PM (Расчеты)'!$C$26/100 ) + 1 ))*5)
A22: 2 | B22: Smart contract | C22: Разработка EscrowFactory | D22: Создание прокси-контрактов, события, access control | F22: 1 | G22: 1.5 | H22: =IF(OR(ISBLANK('Оценка'!F22), ISBLANK('Оценка'!G22)), "", (AVERAGE( ( ('Оценка'!F22 + 4*AVERAGE('Оценка'!F22:G22) + 'Оценка'!G22)/6 - 2*(('Оценка'!G22 - 'Оценка'!F22)/6) )/5 , ( ('Оценка'!F22 + 4*AVERAGE('Оценка'!F22:G22) + 'Оценка'!G22)/6 + 2*(('Оценка'!G22 - 'Оценка'!F22)/6) )/5 ) * ( ( ('PM (Расчеты)'!$C$22/8 + 'PM (Расчеты)'!$C$23/40) + 'PM (Расчеты)'!$C$21/100 + 'PM (Расчеты)'!$C$25/100 + 'PM (Расчеты)'!$C$26/100 ) + 1 ))*5) -> 2
A23: 2 | B23: Smart contract | C23: Разработка Escrow Implementation | D23: Логика депозита, релиза, refund, referral link, resolveDispute, интеграция USDT | F23: 2 | G23: 3 | H23: =IF(OR(ISBLANK('Оценка'!F23), ISBLANK('Оценка'!G23)), "", (AVERAGE( ( ('Оценка'!F23 + 4*AVERAGE('Оценка'!F23:G23) + 'Оценка'!G23)/6 - 2*(('Оценка'!G23 - 'Оценка'!F23)/6) )/5 , ( ('Оценка'!F23 + 4*AVERAGE('Оценка'!F23:G23) + 'Оценка'!G23)/6 + 2*(('Оценка'!G23 - 'Оценка'!F23)/6) )/5 ) * ( ( ('PM (Расчеты)'!$C$22/8 + 'PM (Расчеты)'!$C$23/40) + 'PM (Расчеты)'!$C$21/100 + 'PM (Расчеты)'!$C$25/100 + 'PM (Расчеты)'!$C$26/100 ) + 1 ))*5) -> 4
A24: 2 | B24: Smart contract | C24: Написание unit и integration тестов | D24: Покрытие всех функций, happy path, edge cases, gas optimization | F24: 1.5 | G24: 2.5 | H24: =IF(OR(ISBLANK('Оценка'!F24), ISBLANK('Оценка'!G24)), "", (AVERAGE( ( ('Оценка'!F24 + 4*AVERAGE('Оценка'!F24:G24) + 'Оценка'!G24)/6 - 2*(('Оценка'!G24 - 'Оценка'!F24)/6) )/5 , ( ('Оценка'!F24 + 4*AVERAGE('Оценка'!F24:G24) + 'Оценка'!G24)/6 + 2*(('Оценка'!G24 - 'Оценка'!F24)/6) )/5 ) * ( ( ('PM (Расчеты)'!$C$22/8 + 'PM (Расчеты)'!$C$23/40) + 'PM (Расчеты)'!$C$21/100 + 'PM (Расчеты)'!$C$25/100 + 'PM (Расчеты)'!$C$26/100 ) + 1 ))*5) -> 3.2
A25: 2 | B25: Smart contract | C25: Деплой в testnet (Sepolia) | D25: Factory + Implementation, верификация в Etherscan | F25: 0.5 | G25: 0.5 | H25: =IF(OR(ISBLANK('Оценка'!F25), ISBLANK('Оценка'!G25)), "", (AVERAGE( ( ('Оценка'!F25 + 4*AVERAGE('Оценка'!F25:G25) + 'Оценка'!G25)/6 - 2*(('Оценка'!G25 - 'Оценка'!F25)/6) )/5 , ( ('Оценка'!F25 + 4*AVERAGE('Оценка'!F25:G25) + 'Оценка'!G25)/6 + 2*(('Оценка'!G25 - 'Оценка'!F25)/6) )/5 ) * ( ( ('PM (Расчеты)'!$C$22/8 + 'PM (Расчеты)'!$C$23/40) + 'PM (Расчеты)'!$C$21/100 + 'PM (Расчеты)'!$C$25/100 + 'PM (Расчеты)'!$C$26/100 ) + 1 ))*5) -> 0.8
A26: 2 | B26: Smart contract | C26: Деплой в mainnet | D26: Factory + Implementation, настройка мультисиг/Fireblocks | F26: 2 | G26: 2 | H26: =IF(OR(ISBLANK('Оценка'!F26), ISBLANK('Оценка'!G26)), "", (AVERAGE( ( ('Оценка'!F26 + 4*AVERAGE('Оценка'!F26:G26) + 'Оценка'!G26)/6 - 2*(('Оценка'!G26 - 'Оценка'!F26)/6) )/5 , ( ('Оценка'!F26 + 4*AVERAGE('Оценка'!F26:G26) + 'Оценка'!G26)/6 + 2*(('Оценка'!G26 - 'Оценка'!F26)/6) )/5 ) * ( ( ('PM (Расчеты)'!$C$22/8 + 'PM (Расчеты)'!$C$23/40) + 'PM (Расчеты)'!$C$21/100 + 'PM (Расчеты)'!$C$25/100 + 'PM (Расчеты)'!$C$26/100 ) + 1 ))*5) -> 3.2
A27: 2 | B27: Smart contract | C27: Аудит безопасности | D27: Внешний аудит, исправление найденных проблем | F27: 1 | G27: 1 | H27: =IF(OR(ISBLANK('Оценка'!F27), ISBLANK('Оценка'!G27)), "", (AVERAGE( ( ('Оценка'!F27 + 4*AVERAGE('Оценка'!F27:G27) + 'Оценка'!G27)/6 - 2*(('Оценка'!G27 - 'Оценка'!F27)/6) )/5 , ( ('Оценка'!F27 + 4*AVERAGE('Оценка'!F27:G27) + 'Оценка'!G27)/6 + 2*(('Оценка'!G27 - 'Оценка'!F27)/6) )/5 ) * ( ( ('PM (Расчеты)'!$C$22/8 + 'PM (Расчеты)'!$C$23/40) + 'PM (Расчеты)'!$C$21/100 + 'PM (Расчеты)'!$C$25/100 + 'PM (Расчеты)'!$C$26/100 ) + 1 ))*5) -> 1.6
C28: Backend (Monolith): Инициализация NestJS проекта | H28: =IF(OR(ISBLANK('Оценка'!F28), ISBLANK('Оценка'!G28)), "", (AVERAGE( ( ('Оценка'!F28 + 4*AVERAGE('Оценка'!F28:G28) + 'Оценка'!G28)/6 - 2*(('Оценка'!G28 - 'Оценка'!F28)/6) )/5 , ( ('Оценка'!F28 + 4*AVERAGE('Оценка'!F28:G28) + 'Оценка'!G28)/6 + 2*(('Оценка'!G28 - 'Оценка'!F28)/6) )/5 ) * ( ( ('PM (Расчеты)'!$C$22/8 + 'PM (Расчеты)'!$C$23/40) + 'PM (Расчеты)'!$C$21/100 + 'PM (Расчеты)'!$C$25/100 + 'PM (Расчеты)'!$C$26/100 ) + 1 ))*5)
A29: 3 | B29: Backend | C29: Настройка инфраструктуры | D29: TypeORM (PostgreSQL), Redis, Bull Queue, валидация | F29: 2 | G29: 3 | H29: =IF(OR(ISBLANK('Оценка'!F29), ISBLANK('Оценка'!G29)), "", (AVERAGE( ( ('Оценка'!F29 + 4*AVERAGE('Оценка'!F29:G29) + 'Оценка'!G29)/6 - 2*(('Оценка'!G29 - 'Оценка'!F29)/6) )/5 , ( ('Оценка'!F29 + 4*AVERAGE('Оценка'!F29:G29) + 'Оценка'!G29)/6 + 2*(('Оценка'!G29 - 'Оценка'!F29)/6) )/5 ) * ( ( ('PM (Расчеты)'!$C$22/8 + 'PM (Расчеты)'!$C$23/40) + 'PM (Расчеты)'!$C$21/100 + 'PM (Расчеты)'!$C$25/100 + 'PM (Расчеты)'!$C$26/100 ) + 1 ))*5) -> 4
A30: 3 | B30: Backend | C30: Разработка Shared Layer | D30: Database Service, Cache Service, Queue Service, Auth Service | F30: 2 | G30: 3 | H30: =IF(OR(ISBLANK('Оценка'!F30), ISBLANK('Оценка'!G30)), "", (AVERAGE( ( ('Оценка'!F30 + 4*AVERAGE('Оценка'!F30:G30) + 'Оценка'!G30)/6 - 2*(('Оценка'!G30 - 'Оценка'!F30)/6) )/5 , ( ('Оценка'!F30 + 4*AVERAGE('Оценка'!F30:G30) + 'Оценка'!G30)/6 + 2*(('Оценка'!G30 - 'Оценка'!F30)/6) )/5 ) * ( ( ('PM (Расчеты)'!$C$22/8 + 'PM (Расчеты)'!$C$23/40) + 'PM (Расчеты)'!$C$21/100 + 'PM (Расчеты)'!$C$25/100 + 'PM (Расчеты)'!$C$26/100 ) + 1 ))*5) -> 4
A31: 4 | B31: Backend | C31: Разработка Blockchain Service | D31: Ethers.js интеграция, RPC, индексатор событий | F31: 2 | G31: 3 | H31: =IF(OR(ISBLANK('Оценка'!F31), ISBLANK('Оценка'!G31)), "", (AVERAGE( ( ('Оценка'!F31 + 4*AVERAGE('Оценка'!F31:G31) + 'Оценка'!G31)/6 - 2*(('Оценка'!G31 - 'Оценка'!F31)/6) )/5 , ( ('Оценка'!F31 + 4*AVERAGE('Оценка'!F31:G31) + 'Оценка'!G31)/6 + 2*(('Оценка'!G31 - 'Оценка'!F31)/6) )/5 ) * ( ( ('PM (Расчеты)'!$C$22/8 + 'PM (Расчеты)'!$C$23/40) + 'PM (Расчеты)'!$C$21/100 + 'PM (Расчеты)'!$C$25/100 + 'PM (Расчеты)'!$C$26/100 ) + 1 ))*5) -> 4
A32: 3 | B32: Backend | C32: Разработка Encryption Service | D32: AES-256 для шифрования реквизитов | F32: 1 | G32: 2 | H32: =IF(OR(ISBLANK('Оценка'!F32), ISBLANK('Оценка'!G32)), "", (AVERAGE( ( ('Оценка'!F32 + 4*AVERAGE('Оценка'!F32:G32) + 'Оценка'!G32)/6 - 2*(('Оценка'!G32 - 'Оценка'!F32)/6) )/5 , ( ('Оценка'!F32 + 4*AVERAGE('Оценка'!F32:G32) + 'Оценка'!G32)/6 + 2*(('Оценка'!G32 - 'Оценка'!F32)/6) )/5 ) * ( ( ('PM (Расчеты)'!$C$22/8 + 'PM (Расчеты)'!$C$23/40) + 'PM (Расчеты)'!$C$21/100 + 'PM (Расчеты)'!$C$25/100 + 'PM (Расчеты)'!$C$26/100 ) + 1 ))*5) -> 2.4
C33: Backend (Monolith): User Module | H33: =IF(OR(ISBLANK('Оценка'!F33), ISBLANK('Оценка'!G33)), "", (AVERAGE( ( ('Оценка'!F33 + 4*AVERAGE('Оценка'!F33:G33) + 'Оценка'!G33)/6 - 2*(('Оценка'!G33 - 'Оценка'!F33)/6) )/5 , ( ('Оценка'!F33 + 4*AVERAGE('Оценка'!F33:G33) + 'Оценка'!G33)/6 + 2*(('Оценка'!G33 - 'Оценка'!F33)/6) )/5 ) * ( ( ('PM (Расчеты)'!$C$22/8 + 'PM (Расчеты)'!$C$23/40) + 'PM (Расчеты)'!$C$21/100 + 'PM (Расчеты)'!$C$25/100 + 'PM (Расчеты)'!$C$26/100 ) + 1 ))*5)
A34: 4 | B34: Backend | C34: Создание сущностей | D34: User (с полями реферальной программы: referrer_id, referrer_wallet, referral_code), Wallet, KycStatus, UserLevel — таблицы, связи, индексы | F34: 1.5 | G34: 2.5 | H34: =IF(OR(ISBLANK('Оценка'!F34), ISBLANK('Оценка'!G34)), "", (AVERAGE( ( ('Оценка'!F34 + 4*AVERAGE('Оценка'!F34:G34) + 'Оценка'!G34)/6 - 2*(('Оценка'!G34 - 'Оценка'!F34)/6) )/5 , ( ('Оценка'!F34 + 4*AVERAGE('Оценка'!F34:G34) + 'Оценка'!G34)/6 + 2*(('Оценка'!G34 - 'Оценка'!F34)/6) )/5 ) * ( ( ('PM (Расчеты)'!$C$22/8 + 'PM (Расчеты)'!$C$23/40) + 'PM (Расчеты)'!$C$21/100 + 'PM (Расчеты)'!$C$25/100 + 'PM (Расчеты)'!$C$26/100 ) + 1 ))*5) -> 3.2
A35: 4 | B35: Backend | C35: Разработка API | D35: Регистрация, авторизация (Web3 + JWT), профиль, привязка кошелька | F35: 2.5 | G35: 3.5 | H35: =IF(OR(ISBLANK('Оценка'!F35), ISBLANK('Оценка'!G35)), "", (AVERAGE( ( ('Оценка'!F35 + 4*AVERAGE('Оценка'!F35:G35) + 'Оценка'!G35)/6 - 2*(('Оценка'!G35 - 'Оценка'!F35)/6) )/5 , ( ('Оценка'!F35 + 4*AVERAGE('Оценка'!F35:G35) + 'Оценка'!G35)/6 + 2*(('Оценка'!G35 - 'Оценка'!F35)/6) )/5 ) * ( ( ('PM (Расчеты)'!$C$22/8 + 'PM (Расчеты)'!$C$23/40) + 'PM (Расчеты)'!$C$21/100 + 'PM (Расчеты)'!$C$25/100 + 'PM (Расчеты)'!$C$26/100 ) + 1 ))*5) -> 4.8
A36: 4 | B36: Backend | C36: Реализация уровней доступа | D36: Проверка прав, лимиты | F36: 2 | G36: 3 | H36: =IF(OR(ISBLANK('Оценка'!F36), ISBLANK('Оценка'!G36)), "", (AVERAGE( ( ('Оценка'!F36 + 4*AVERAGE('Оценка'!F36:G36) + 'Оценка'!G36)/6 - 2*(('Оценка'!G36 - 'Оценка'!F36)/6) )/5 , ( ('Оценка'!F36 + 4*AVERAGE('Оценка'!F36:G36) + 'Оценка'!G36)/6 + 2*(('Оценка'!G36 - 'Оценка'!F36)/6) )/5 ) * ( ( ('PM (Расчеты)'!$C$22/8 + 'PM (Расчеты)'!$C$23/40) + 'PM (Расчеты)'!$C$21/100 + 'PM (Расчеты)'!$C$25/100 + 'PM (Расчеты)'!$C$26/100 ) + 1 ))*5) -> 4
C37: Backend (Monolith): Trading Module | H37: =IF(OR(ISBLANK('Оценка'!F37), ISBLANK('Оценка'!G37)), "", (AVERAGE( ( ('Оценка'!F37 + 4*AVERAGE('Оценка'!F37:G37) + 'Оценка'!G37)/6 - 2*(('Оценка'!G37 - 'Оценка'!F37)/6) )/5 , ( ('Оценка'!F37 + 4*AVERAGE('Оценка'!F37:G37) + 'Оценка'!G37)/6 + 2*(('Оценка'!G37 - 'Оценка'!F37)/6) )/5 ) * ( ( ('PM (Расчеты)'!$C$22/8 + 'PM (Расчеты)'!$C$23/40) + 'PM (Расчеты)'!$C$21/100 + 'PM (Расчеты)'!$C$25/100 + 'PM (Расчеты)'!$C$26/100 ) + 1 ))*5)
A38: 3 | B38: Backend | C38: Создание сущностей | D38: Order, Deal, EscrowContract — таблицы, связи | F38: 1 | G38: 2 | H38: =IF(OR(ISBLANK('Оценка'!F38), ISBLANK('Оценка'!G38)), "", (AVERAGE( ( ('Оценка'!F38 + 4*AVERAGE('Оценка'!F38:G38) + 'Оценка'!G38)/6 - 2*(('Оценка'!G38 - 'Оценка'!F38)/6) )/5 , ( ('Оценка'!F38 + 4*AVERAGE('Оценка'!F38:G38) + 'Оценка'!G38)/6 + 2*(('Оценка'!G38 - 'Оценка'!F38)/6) )/5 ) * ( ( ('PM (Расчеты)'!$C$22/8 + 'PM (Расчеты)'!$C$23/40) + 'PM (Расчеты)'!$C$21/100 + 'PM (Расчеты)'!$C$25/100 + 'PM (Расчеты)'!$C$26/100 ) + 1 ))*5) -> 2.4
A39: 3 | B39: Backend | C39: Разработка Order API | D39: CRUD ордеров, стакан, фильтрация, WebSocket для real-time | F39: 3 | G39: 4.5 | H39: =IF(OR(ISBLANK('Оценка'!F39), ISBLANK('Оценка'!G39)), "", (AVERAGE( ( ('Оценка'!F39 + 4*AVERAGE('Оценка'!F39:G39) + 'Оценка'!G39)/6 - 2*(('Оценка'!G39 - 'Оценка'!F39)/6) )/5 , ( ('Оценка'!F39 + 4*AVERAGE('Оценка'!F39:G39) + 'Оценка'!G39)/6 + 2*(('Оценка'!G39 - 'Оценка'!F39)/6) )/5 ) * ( ( ('PM (Расчеты)'!$C$22/8 + 'PM (Расчеты)'!$C$23/40) + 'PM (Расчеты)'!$C$21/100 + 'PM (Расчеты)'!$C$25/100 + 'PM (Расчеты)'!$C$26/100 ) + 1 ))*5) -> 6
A40: 3 | B40: Backend | C40: Разработка Deal API | D40: Инициация, деплой эскроу, обработка депозита, подтверждения | F40: 3 | G40: 4.5 | H40: =IF(OR(ISBLANK('Оценка'!F40), ISBLANK('Оценка'!G40)), "", (AVERAGE( ( ('Оценка'!F40 + 4*AVERAGE('Оценка'!F40:G40) + 'Оценка'!G40)/6 - 2*(('Оценка'!G40 - 'Оценка'!F40)/6) )/5 , ( ('Оценка'!F40 + 4*AVERAGE('Оценка'!F40:G40) + 'Оценка'!G40)/6 + 2*(('Оценка'!G40 - 'Оценка'!F40)/6) )/5 ) * ( ( ('PM (Расчеты)'!$C$22/8 + 'PM (Расчеты)'!$C$23/40) + 'PM (Расчеты)'!$C$21/100 + 'PM (Расчеты)'!$C$25/100 + 'PM (Расчеты)'!$C$26/100 ) + 1 ))*5) -> 6
A41: 3 | B41: Backend | C41: Реализация жизненного цикла сделки | D41: Таймауты, авто-отмена, релиз, комиссия | F41: 3 | G41: 5 | H41: =IF(OR(ISBLANK('Оценка'!F41), ISBLANK('Оценка'!G41)), "", (AVERAGE( ( ('Оценка'!F41 + 4*AVERAGE('Оценка'!F41:G41) + 'Оценка'!G41)/6 - 2*(('Оценка'!G41 - 'Оценка'!F41)/6) )/5 , ( ('Оценка'!F41 + 4*AVERAGE('Оценка'!F41:G41) + 'Оценка'!G41)/6 + 2*(('Оценка'!G41 - 'Оценка'!F41)/6) )/5 ) * ( ( ('PM (Расчеты)'!$C$22/8 + 'PM (Расчеты)'!$C$23/40) + 'PM (Расчеты)'!$C$21/100 + 'PM (Расчеты)'!$C$25/100 + 'PM (Расчеты)'!$C$26/100 ) + 1 ))*5) -> 6.4
A42: 3 | B42: Backend | C42: Реализация режима "Яма" | D42: Переговорные сделки, фиксация курса | F42: 3 | G42: 5 | H42: =IF(OR(ISBLANK('Оценка'!F42), ISBLANK('Оценка'!G42)), "", (AVERAGE( ( ('Оценка'!F42 + 4*AVERAGE('Оценка'!F42:G42) + 'Оценка'!G42)/6 - 2*(('Оценка'!G42 - 'Оценка'!F42)/6) )/5 , ( ('Оценка'!F42 + 4*AVERAGE('Оценка'!F42:G42) + 'Оценка'!G42)/6 + 2*(('Оценка'!G42 - 'Оценка'!F42)/6) )/5 ) * ( ( ('PM (Расчеты)'!$C$22/8 + 'PM (Расчеты)'!$C$23/40) + 'PM (Расчеты)'!$C$21/100 + 'PM (Расчеты)'!$C$25/100 + 'PM (Расчеты)'!$C$26/100 ) + 1 ))*5) -> 6.4
A43: 3 | C43: Backend (Monolith): Payment Module | H43: =IF(OR(ISBLANK('Оценка'!F43), ISBLANK('Оценка'!G43)), "", (AVERAGE( ( ('Оценка'!F43 + 4*AVERAGE('Оценка'!F43:G43) + 'Оценка'!G43)/6 - 2*(('Оценка'!G43 - 'Оценка'!F43)/6) )/5 , ( ('Оценка'!F43 + 4*AVERAGE('Оценка'!F43:G43) + 'Оценка'!G43)/6 + 2*(('Оценка'!G43 - 'Оценка'!F43)/6) )/5 ) * ( ( ('PM (Расчеты)'!$C$22/8 + 'PM (Расчеты)'!$C$23/40) + 'PM (Расчеты)'!$C$21/100 + 'PM (Расчеты)'!$C$25/100 + 'PM (Расчеты)'!$C$26/100 ) + 1 ))*5)
A44: 3 | B44: Backend | C44: Создание сущности PaymentDetails | D44: Таблица, шифрование | F44: 0.5 | G44: 1 | H44: =IF(OR(ISBLANK('Оценка'!F44), ISBLANK('Оценка'!G44)), "", (AVERAGE( ( ('Оценка'!F44 + 4*AVERAGE('Оценка'!F44:G44) + 'Оценка'!G44)/6 - 2*(('Оценка'!G44 - 'Оценка'!F44)/6) )/5 , ( ('Оценка'!F44 + 4*AVERAGE('Оценка'!F44:G44) + 'Оценка'!G44)/6 + 2*(('Оценка'!G44 - 'Оценка'!F44)/6) )/5 ) * ( ( ('PM (Расчеты)'!$C$22/8 + 'PM (Расчеты)'!$C$23/40) + 'PM (Расчеты)'!$C$21/100 + 'PM (Расчеты)'!$C$25/100 + 'PM (Расчеты)'!$C$26/100 ) + 1 ))*5) -> 1.2
A45: 3 | B45: Backend | C45: Разработка API | D45: CRUD реквизитов, передача в сделке после депозита | F45: 1 | G45: 1 | H45: =IF(OR(ISBLANK('Оценка'!F45), ISBLANK('Оценка'!G45)), "", (AVERAGE( ( ('Оценка'!F45 + 4*AVERAGE('Оценка'!F45:G45) + 'Оценка'!G45)/6 - 2*(('Оценка'!G45 - 'Оценка'!F45)/6) )/5 , ( ('Оценка'!F45 + 4*AVERAGE('Оценка'!F45:G45) + 'Оценка'!G45)/6 + 2*(('Оценка'!G45 - 'Оценка'!F45)/6) )/5 ) * ( ( ('PM (Расчеты)'!$C$22/8 + 'PM (Расчеты)'!$C$23/40) + 'PM (Расчеты)'!$C$21/100 + 'PM (Расчеты)'!$C$25/100 + 'PM (Расчеты)'!$C$26/100 ) + 1 ))*5) -> 1.6
A46: 4 | C46: Backend (Monolith): Dispute Module | H46: =IF(OR(ISBLANK('Оценка'!F46), ISBLANK('Оценка'!G46)), "", (AVERAGE( ( ('Оценка'!F46 + 4*AVERAGE('Оценка'!F46:G46) + 'Оценка'!G46)/6 - 2*(('Оценка'!G46 - 'Оценка'!F46)/6) )/5 , ( ('Оценка'!F46 + 4*AVERAGE('Оценка'!F46:G46) + 'Оценка'!G46)/6 + 2*(('Оценка'!G46 - 'Оценка'!F46)/6) )/5 ) * ( ( ('PM (Расчеты)'!$C$22/8 + 'PM (Расчеты)'!$C$23/40) + 'PM (Расчеты)'!$C$21/100 + 'PM (Расчеты)'!$C$25/100 + 'PM (Расчеты)'!$C$26/100 ) + 1 ))*5)
A47: 4 | B47: Backend | C47: Создание сущностей | D47: Dispute — таблицы, статусы | F47: 1 | G47: 1 | H47: =IF(OR(ISBLANK('Оценка'!F47), ISBLANK('Оценка'!G47)), "", (AVERAGE( ( ('Оценка'!F47 + 4*AVERAGE('Оценка'!F47:G47) + 'Оценка'!G47)/6 - 2*(('Оценка'!G47 - 'Оценка'!F47)/6) )/5 , ( ('Оценка'!F47 + 4*AVERAGE('Оценка'!F47:G47) + 'Оценка'!G47)/6 + 2*(('Оценка'!G47 - 'Оценка'!F47)/6) )/5 ) * ( ( ('PM (Расчеты)'!$C$22/8 + 'PM (Расчеты)'!$C$23/40) + 'PM (Расчеты)'!$C$21/100 + 'PM (Расчеты)'!$C$25/100 + 'PM (Расчеты)'!$C$26/100 ) + 1 ))*5) -> 1.6
A48: 4 | B48: Backend | C48: Разработка API | D48: Создание диспута, добавление доказательств, продление блокировки | F48: 2 | G48: 3 | H48: =IF(OR(ISBLANK('Оценка'!F48), ISBLANK('Оценка'!G48)), "", (AVERAGE( ( ('Оценка'!F48 + 4*AVERAGE('Оценка'!F48:G48) + 'Оценка'!G48)/6 - 2*(('Оценка'!G48 - 'Оценка'!F48)/6) )/5 , ( ('Оценка'!F48 + 4*AVERAGE('Оценка'!F48:G48) + 'Оценка'!G48)/6 + 2*(('Оценка'!G48 - 'Оценка'!F48)/6) )/5 ) * ( ( ('PM (Расчеты)'!$C$22/8 + 'PM (Расчеты)'!$C$23/40) + 'PM (Расчеты)'!$C$21/100 + 'PM (Расчеты)'!$C$25/100 + 'PM (Расчеты)'!$C$26/100 ) + 1 ))*5) -> 4
A49: 4 | B49: Backend | C49: Разработка Admin API | D49: Список диспутов, просмотр, принятие решения, вызов resolveDispute | F49: 2 | G49: 3 | H49: =IF(OR(ISBLANK('Оценка'!F49), ISBLANK('Оценка'!G49)), "", (AVERAGE( ( ('Оценка'!F49 + 4*AVERAGE('Оценка'!F49:G49) + 'Оценка'!G49)/6 - 2*(('Оценка'!G49 - 'Оценка'!F49)/6) )/5 , ( ('Оценка'!F49 + 4*AVERAGE('Оценка'!F49:G49) + 'Оценка'!G49)/6 + 2*(('Оценка'!G49 - 'Оценка'!F49)/6) )/5 ) * ( ( ('PM (Расчеты)'!$C$22/8 + 'PM (Расчеты)'!$C$23/40) + 'PM (Расчеты)'!$C$21/100 + 'PM (Расчеты)'!$C$25/100 + 'PM (Расчеты)'!$C$26/100 ) + 1 ))*5) -> 4
A50: 4 | C50: Backend (Monolith): rating Module | H50: =IF(OR(ISBLANK('Оценка'!F50), ISBLANK('Оценка'!G50)), "", (AVERAGE( ( ('Оценка'!F50 + 4*AVERAGE('Оценка'!F50:G50) + 'Оценка'!G50)/6 - 2*(('Оценка'!G50 - 'Оценка'!F50)/6) )/5 , ( ('Оценка'!F50 + 4*AVERAGE('Оценка'!F50:G50) + 'Оценка'!G50)/6 + 2*(('Оценка'!G50 - 'Оценка'!F50)/6) )/5 ) * ( ( ('PM (Расчеты)'!$C$22/8 + 'PM (Расчеты)'!$C$23/40) + 'PM (Расчеты)'!$C$21/100 + 'PM (Расчеты)'!$C$25/100 + 'PM (Расчеты)'!$C$26/100 ) + 1 ))*5)
A51: 4 | B51: Backend | C51: Создание сущностей | D51: Rating, RatingHistory | F51: 1 | G51: 1 | H51: =IF(OR(ISBLANK('Оценка'!F51), ISBLANK('Оценка'!G51)), "", (AVERAGE( ( ('Оценка'!F51 + 4*AVERAGE('Оценка'!F51:G51) + 'Оценка'!G51)/6 - 2*(('Оценка'!G51 - 'Оценка'!F51)/6) )/5 , ( ('Оценка'!F51 + 4*AVERAGE('Оценка'!F51:G51) + 'Оценка'!G51)/6 + 2*(('Оценка'!G51 - 'Оценка'!F51)/6) )/5 ) * ( ( ('PM (Расчеты)'!$C$22/8 + 'PM (Расчеты)'!$C$23/40) + 'PM (Расчеты)'!$C$21/100 + 'PM (Расчеты)'!$C$25/100 + 'PM (Расчеты)'!$C$26/100 ) + 1 ))*5) -> 1.6
A52: 4 | B52: Backend | C52: Разработка Rating Service | D52: Расчет рейтинга (сделки, отмены, диспуты, объем) | F52: 1.5 | G52: 1.5 | H52: =IF(OR(ISBLANK('Оценка'!F52), ISBLANK('Оценка'!G52)), "", (AVERAGE( ( ('Оценка'!F52 + 4*AVERAGE('Оценка'!F52:G52) + 'Оценка'!G52)/6 - 2*(('Оценка'!G52 - 'Оценка'!F52)/6) )/5 , ( ('Оценка'!F52 + 4*AVERAGE('Оценка'!F52:G52) + 'Оценка'!G52)/6 + 2*(('Оценка'!G52 - 'Оценка'!F52)/6) )/5 ) * ( ( ('PM (Расчеты)'!$C$22/8 + 'PM (Расчеты)'!$C$23/40) + 'PM (Расчеты)'!$C$21/100 + 'PM (Расчеты)'!$C$25/100 + 'PM (Расчеты)'!$C$26/100 ) + 1 ))*5) -> 2.4
A53: 3 | C53: Backend (Monolith): Analytics Module | H53: =IF(OR(ISBLANK('Оценка'!F53), ISBLANK('Оценка'!G53)), "", (AVERAGE( ( ('Оценка'!F53 + 4*AVERAGE('Оценка'!F53:G53) + 'Оценка'!G53)/6 - 2*(('Оценка'!G53 - 'Оценка'!F53)/6) )/5 , ( ('Оценка'!F53 + 4*AVERAGE('Оценка'!F53:G53) + 'Оценка'!G53)/6 + 2*(('Оценка'!G53 - 'Оценка'!F53)/6) )/5 ) * ( ( ('PM (Расчеты)'!$C$22/8 + 'PM (Расчеты)'!$C$23/40) + 'PM (Расчеты)'!$C$21/100 + 'PM (Расчеты)'!$C$25/100 + 'PM (Расчеты)'!$C$26/100 ) + 1 ))*5)
A54: 4 | B54: Backend | C54: Подключение стороннего сервиса аналитики | D54: Redash или др | F54: 0.5 | G54: 1 | H54: =IF(OR(ISBLANK('Оценка'!F54), ISBLANK('Оценка'!G54)), "", (AVERAGE( ( ('Оценка'!F54 + 4*AVERAGE('Оценка'!F54:G54) + 'Оценка'!G54)/6 - 2*(('Оценка'!G54 - 'Оценка'!F54)/6) )/5 , ( ('Оценка'!F54 + 4*AVERAGE('Оценка'!F54:G54) + 'Оценка'!G54)/6 + 2*(('Оценка'!G54 - 'Оценка'!F54)/6) )/5 ) * ( ( ('PM (Расчеты)'!$C$22/8 + 'PM (Расчеты)'!$C$23/40) + 'PM (Расчеты)'!$C$21/100 + 'PM (Расчеты)'!$C$25/100 + 'PM (Расчеты)'!$C$26/100 ) + 1 ))*5) -> 1.2
C55: Backend (Monolith): Referral Module | H55: =IF(OR(ISBLANK('Оценка'!F55), ISBLANK('Оценка'!G55)), "", (AVERAGE( ( ('Оценка'!F55 + 4*AVERAGE('Оценка'!F55:G55) + 'Оценка'!G55)/6 - 2*(('Оценка'!G55 - 'Оценка'!F55)/6) )/5 , ( ('Оценка'!F55 + 4*AVERAGE('Оценка'!F55:G55) + 'Оценка'!G55)/6 + 2*(('Оценка'!G55 - 'Оценка'!F55)/6) )/5 ) * ( ( ('PM (Расчеты)'!$C$22/8 + 'PM (Расчеты)'!$C$23/40) + 'PM (Расчеты)'!$C$21/100 + 'PM (Расчеты)'!$C$25/100 + 'PM (Расчеты)'!$C$26/100 ) + 1 ))*5)
A56: 4 | B56: Backend | C56: API генерации реферальной ссылки | D56: Уникальный код, URL | F56: 0.5 | G56: 1 | H56: =IF(OR(ISBLANK('Оценка'!F56), ISBLANK('Оценка'!G56)), "", (AVERAGE( ( ('Оценка'!F56 + 4*AVERAGE('Оценка'!F56:G56) + 'Оценка'!G56)/6 - 2*(('Оценка'!G56 - 'Оценка'!F56)/6) )/5 , ( ('Оценка'!F56 + 4*AVERAGE('Оценка'!F56:G56) + 'Оценка'!G56)/6 + 2*(('Оценка'!G56 - 'Оценка'!F56)/6) )/5 ) * ( ( ('PM (Расчеты)'!$C$22/8 + 'PM (Расчеты)'!$C$23/40) + 'PM (Расчеты)'!$C$21/100 + 'PM (Расчеты)'!$C$25/100 + 'PM (Расчеты)'!$C$26/100 ) + 1 ))*5) -> 1.2
A57: 4 | B57: Backend | C57: API установки кошелька комиссий | D57: Валидация адреса | F57: 0.5 | G57: 1 | H57: =IF(OR(ISBLANK('Оценка'!F57), ISBLANK('Оценка'!G57)), "", (AVERAGE( ( ('Оценка'!F57 + 4*AVERAGE('Оценка'!F57:G57) + 'Оценка'!G57)/6 - 2*(('Оценка'!G57 - 'Оценка'!F57)/6) )/5 , ( ('Оценка'!F57 + 4*AVERAGE('Оценка'!F57:G57) + 'Оценка'!G57)/6 + 2*(('Оценка'!G57 - 'Оценка'!F57)/6) )/5 ) * ( ( ('PM (Расчеты)'!$C$22/8 + 'PM (Расчеты)'!$C$23/40) + 'PM (Расчеты)'!$C$21/100 + 'PM (Расчеты)'!$C$25/100 + 'PM (Расчеты)'!$C$26/100 ) + 1 ))*5) -> 1.2
A58: 4 | B58: Backend | C58: Привязка при регистрации | D58: Парсинг ?ref=, сохранение referrer_id/wallet | F58: 0.5 | G58: 0.5 | H58: =IF(OR(ISBLANK('Оценка'!F58), ISBLANK('Оценка'!G58)), "", (AVERAGE( ( ('Оценка'!F58 + 4*AVERAGE('Оценка'!F58:G58) + 'Оценка'!G58)/6 - 2*(('Оценка'!G58 - 'Оценка'!F58)/6) )/5 , ( ('Оценка'!F58 + 4*AVERAGE('Оценка'!F58:G58) + 'Оценка'!G58)/6 + 2*(('Оценка'!G58 - 'Оценка'!F58)/6) )/5 ) * ( ( ('PM (Расчеты)'!$C$22/8 + 'PM (Расчеты)'!$C$23/40) + 'PM (Расчеты)'!$C$21/100 + 'PM (Расчеты)'!$C$25/100 + 'PM (Расчеты)'!$C$26/100 ) + 1 ))*5) -> 0.8
A59: 4 | B59: Backend | C59: Интеграция со сделками | D59: Получение referrer_wallet при создании сделки, передача в контракт | F59: 1 | G59: 2 | H59: =IF(OR(ISBLANK('Оценка'!F59), ISBLANK('Оценка'!G59)), "", (AVERAGE( ( ('Оценка'!F59 + 4*AVERAGE('Оценка'!F59:G59) + 'Оценка'!G59)/6 - 2*(('Оценка'!G59 - 'Оценка'!F59)/6) )/5 , ( ('Оценка'!F59 + 4*AVERAGE('Оценка'!F59:G59) + 'Оценка'!G59)/6 + 2*(('Оценка'!G59 - 'Оценка'!F59)/6) )/5 ) * ( ( ('PM (Расчеты)'!$C$22/8 + 'PM (Расчеты)'!$C$23/40) + 'PM (Расчеты)'!$C$21/100 + 'PM (Расчеты)'!$C$25/100 + 'PM (Расчеты)'!$C$26/100 ) + 1 ))*5) -> 2.4
A60: 4 | B60: Backend | C60: Создание сущности ReferralReward | D60: Хранение истории выплат | F60: 0.5 | G60: 1 | H60: =IF(OR(ISBLANK('Оценка'!F60), ISBLANK('Оценка'!G60)), "", (AVERAGE( ( ('Оценка'!F60 + 4*AVERAGE('Оценка'!F60:G60) + 'Оценка'!G60)/6 - 2*(('Оценка'!G60 - 'Оценка'!F60)/6) )/5 , ( ('Оценка'!F60 + 4*AVERAGE('Оценка'!F60:G60) + 'Оценка'!G60)/6 + 2*(('Оценка'!G60 - 'Оценка'!F60)/6) )/5 ) * ( ( ('PM (Расчеты)'!$C$22/8 + 'PM (Расчеты)'!$C$23/40) + 'PM (Расчеты)'!$C$21/100 + 'PM (Расчеты)'!$C$25/100 + 'PM (Расчеты)'!$C$26/100 ) + 1 ))*5) -> 1.2
A61: 4 | B61: Backend | C61: API реферальной статистики | D61: Кол-во рефералов, сделок, сумма выплат, список | F61: 1 | G61: 2 | H61: =IF(OR(ISBLANK('Оценка'!F61), ISBLANK('Оценка'!G61)), "", (AVERAGE( ( ('Оценка'!F61 + 4*AVERAGE('Оценка'!F61:G61) + 'Оценка'!G61)/6 - 2*(('Оценка'!G61 - 'Оценка'!F61)/6) )/5 , ( ('Оценка'!F61 + 4*AVERAGE('Оценка'!F61:G61) + 'Оценка'!G61)/6 + 2*(('Оценка'!G61 - 'Оценка'!F61)/6) )/5 ) * ( ( ('PM (Расчеты)'!$C$22/8 + 'PM (Расчеты)'!$C$23/40) + 'PM (Расчеты)'!$C$21/100 + 'PM (Расчеты)'!$C$25/100 + 'PM (Расчеты)'!$C$26/100 ) + 1 ))*5) -> 2.4
A62: 4 | B62: Backend | C62: Обработка событий выплат | D62: Обновление статистики при выплате из контракта | F62: 0.5 | G62: 1.5 | H62: =IF(OR(ISBLANK('Оценка'!F62), ISBLANK('Оценка'!G62)), "", (AVERAGE( ( ('Оценка'!F62 + 4*AVERAGE('Оценка'!F62:G62) + 'Оценка'!G62)/6 - 2*(('Оценка'!G62 - 'Оценка'!F62)/6) )/5 , ( ('Оценка'!F62 + 4*AVERAGE('Оценка'!F62:G62) + 'Оценка'!G62)/6 + 2*(('Оценка'!G62 - 'Оценка'!F62)/6) )/5 ) * ( ( ('PM (Расчеты)'!$C$22/8 + 'PM (Расчеты)'!$C$23/40) + 'PM (Расчеты)'!$C$21/100 + 'PM (Расчеты)'!$C$25/100 + 'PM (Расчеты)'!$C$26/100 ) + 1 ))*5) -> 1.6
C65: Backend (Monolith): Миграции БД и документация | H65: =IF(OR(ISBLANK('Оценка'!F65), ISBLANK('Оценка'!G65)), "", (AVERAGE( ( ('Оценка'!F65 + 4*AVERAGE('Оценка'!F65:G65) + 'Оценка'!G65)/6 - 2*(('Оценка'!G65 - 'Оценка'!F65)/6) )/5 , ( ('Оценка'!F65 + 4*AVERAGE('Оценка'!F65:G65) + 'Оценка'!G65)/6 + 2*(('Оценка'!G65 - 'Оценка'!F65)/6) )/5 ) * ( ( ('PM (Расчеты)'!$C$22/8 + 'PM (Расчеты)'!$C$23/40) + 'PM (Расчеты)'!$C$21/100 + 'PM (Расчеты)'!$C$25/100 + 'PM (Расчеты)'!$C$26/100 ) + 1 ))*5)
A66: 3 | B66: Backend | C66: Создание миграций | D66: Все таблицы с учетом реферальной программы: users (с полями referrer_id, referrer_wallet, referral_code), wallets, orders, deals, disputes, rating, referral_rewards и др. | F66: 2 | G66: 3 | H66: =IF(OR(ISBLANK('Оценка'!F66), ISBLANK('Оценка'!G66)), "", (AVERAGE( ( ('Оценка'!F66 + 4*AVERAGE('Оценка'!F66:G66) + 'Оценка'!G66)/6 - 2*(('Оценка'!G66 - 'Оценка'!F66)/6) )/5 , ( ('Оценка'!F66 + 4*AVERAGE('Оценка'!F66:G66) + 'Оценка'!G66)/6 + 2*(('Оценка'!G66 - 'Оценка'!F66)/6) )/5 ) * ( ( ('PM (Расчеты)'!$C$22/8 + 'PM (Расчеты)'!$C$23/40) + 'PM (Расчеты)'!$C$21/100 + 'PM (Расчеты)'!$C$25/100 + 'PM (Расчеты)'!$C$26/100 ) + 1 ))*5) -> 4
A67: 3 | B67: Backend | C67: Настройка Swagger/OpenAPI | D67: Автогенерация документации для всех endpoints | F67: 1 | G67: 2 | H67: =IF(OR(ISBLANK('Оценка'!F67), ISBLANK('Оценка'!G67)), "", (AVERAGE( ( ('Оценка'!F67 + 4*AVERAGE('Оценка'!F67:G67) + 'Оценка'!G67)/6 - 2*(('Оценка'!G67 - 'Оценка'!F67)/6) )/5 , ( ('Оценка'!F67 + 4*AVERAGE('Оценка'!F67:G67) + 'Оценка'!G67)/6 + 2*(('Оценка'!G67 - 'Оценка'!F67)/6) )/5 ) * ( ( ('PM (Расчеты)'!$C$22/8 + 'PM (Расчеты)'!$C$23/40) + 'PM (Расчеты)'!$C$21/100 + 'PM (Расчеты)'!$C$25/100 + 'PM (Расчеты)'!$C$26/100 ) + 1 ))*5) -> 2.4
H68: =IF(OR(ISBLANK('Оценка'!F68), ISBLANK('Оценка'!G68)), "", (AVERAGE( ( ('Оценка'!F68 + 4*AVERAGE('Оценка'!F68:G68) + 'Оценка'!G68)/6 - 2*(('Оценка'!G68 - 'Оценка'!F68)/6) )/5 , ( ('Оценка'!F68 + 4*AVERAGE('Оценка'!F68:G68) + 'Оценка'!G68)/6 + 2*(('Оценка'!G68 - 'Оценка'!F68)/6) )/5 ) * ( ( ('PM (Расчеты)'!$C$22/8 + 'PM (Расчеты)'!$C$23/40) + 'PM (Расчеты)'!$C$21/100 + 'PM (Расчеты)'!$C$25/100 + 'PM (Расчеты)'!$C$26/100 ) + 1 ))*5)
C69: Интеграции | H69: =IF(OR(ISBLANK('Оценка'!F69), ISBLANK('Оценка'!G69)), "", (AVERAGE( ( ('Оценка'!F69 + 4*AVERAGE('Оценка'!F69:G69) + 'Оценка'!G69)/6 - 2*(('Оценка'!G69 - 'Оценка'!F69)/6) )/5 , ( ('Оценка'!F69 + 4*AVERAGE('Оценка'!F69:G69) + 'Оценка'!G69)/6 + 2*(('Оценка'!G69 - 'Оценка'!F69)/6) )/5 ) * ( ( ('PM (Расчеты)'!$C$22/8 + 'PM (Расчеты)'!$C$23/40) + 'PM (Расчеты)'!$C$21/100 + 'PM (Расчеты)'!$C$25/100 + 'PM (Расчеты)'!$C$26/100 ) + 1 ))*5)
A70: 4 | B70: Backend | C70: KYC Интеграция | D70: Регистрация в провайдере (SumSub/Onfido), вебхуки, SDK на frontend, обработка статусов | F70: 2 | G70: 3 | H70: =IF(OR(ISBLANK('Оценка'!F70), ISBLANK('Оценка'!G70)), "", (AVERAGE( ( ('Оценка'!F70 + 4*AVERAGE('Оценка'!F70:G70) + 'Оценка'!G70)/6 - 2*(('Оценка'!G70 - 'Оценка'!F70)/6) )/5 , ( ('Оценка'!F70 + 4*AVERAGE('Оценка'!F70:G70) + 'Оценка'!G70)/6 + 2*(('Оценка'!G70 - 'Оценка'!F70)/6) )/5 ) * ( ( ('PM (Расчеты)'!$C$22/8 + 'PM (Расчеты)'!$C$23/40) + 'PM (Расчеты)'!$C$21/100 + 'PM (Расчеты)'!$C$25/100 + 'PM (Расчеты)'!$C$26/100 ) + 1 ))*5) -> 4
A71: 4 | B71: Backend | C71: Чат Интеграция | D71: Регистрация в провайдере (Stream/PubNub), создание каналов, добавление участников, история | F71: 2.5 | G71: 4 | H71: =IF(OR(ISBLANK('Оценка'!F71), ISBLANK('Оценка'!G71)), "", (AVERAGE( ( ('Оценка'!F71 + 4*AVERAGE('Оценка'!F71:G71) + 'Оценка'!G71)/6 - 2*(('Оценка'!G71 - 'Оценка'!F71)/6) )/5 , ( ('Оценка'!F71 + 4*AVERAGE('Оценка'!F71:G71) + 'Оценка'!G71)/6 + 2*(('Оценка'!G71 - 'Оценка'!F71)/6) )/5 ) * ( ( ('PM (Расчеты)'!$C$22/8 + 'PM (Расчеты)'!$C$23/40) + 'PM (Расчеты)'!$C$21/100 + 'PM (Расчеты)'!$C$25/100 + 'PM (Расчеты)'!$C$26/100 ) + 1 ))*5) -> 5.2
H72: =IF(OR(ISBLANK('Оценка'!F72), ISBLANK('Оценка'!G72)), "", (AVERAGE( ( ('Оценка'!F72 + 4*AVERAGE('Оценка'!F72:G72) + 'Оценка'!G72)/6 - 2*(('Оценка'!G72 - 'Оценка'!F72)/6) )/5 , ( ('Оценка'!F72 + 4*AVERAGE('Оценка'!F72:G72) + 'Оценка'!G72)/6 + 2*(('Оценка'!G72 - 'Оценка'!F72)/6) )/5 ) * ( ( ('PM (Расчеты)'!$C$22/8 + 'PM (Расчеты)'!$C$23/40) + 'PM (Расчеты)'!$C$21/100 + 'PM (Расчеты)'!$C$25/100 + 'PM (Расчеты)'!$C$26/100 ) + 1 ))*5)
C73: Старт проекта | H73: =IF(OR(ISBLANK('Оценка'!F73), ISBLANK('Оценка'!G73)), "", (AVERAGE( ( ('Оценка'!F73 + 4*AVERAGE('Оценка'!F73:G73) + 'Оценка'!G73)/6 - 2*(('Оценка'!G73 - 'Оценка'!F73)/6) )/5 , ( ('Оценка'!F73 + 4*AVERAGE('Оценка'!F73:G73) + 'Оценка'!G73)/6 + 2*(('Оценка'!G73 - 'Оценка'!F73)/6) )/5 ) * ( ( ('PM (Расчеты)'!$C$22/8 + 'PM (Расчеты)'!$C$23/40) + 'PM (Расчеты)'!$C$21/100 + 'PM (Расчеты)'!$C$25/100 + 'PM (Расчеты)'!$C$26/100 ) + 1 ))*5)
A74: 5 | B74: Frontend | C74: инициализация проекта | D74: верстка | F74: 3.5 | G74: 4.5 | H74: =IF(OR(ISBLANK('Оценка'!F74), ISBLANK('Оценка'!G74)), "", (AVERAGE( ( ('Оценка'!F74 + 4*AVERAGE('Оценка'!F74:G74) + 'Оценка'!G74)/6 - 2*(('Оценка'!G74 - 'Оценка'!F74)/6) )/5 , ( ('Оценка'!F74 + 4*AVERAGE('Оценка'!F74:G74) + 'Оценка'!G74)/6 + 2*(('Оценка'!G74 - 'Оценка'!F74)/6) )/5 ) * ( ( ('PM (Расчеты)'!$C$22/8 + 'PM (Расчеты)'!$C$23/40) + 'PM (Расчеты)'!$C$21/100 + 'PM (Расчеты)'!$C$25/100 + 'PM (Расчеты)'!$C$26/100 ) + 1 ))*5) -> 6.4
A75: 5 | H75: =IF(OR(ISBLANK('Оценка'!F75), ISBLANK('Оценка'!G75)), "", (AVERAGE( ( ('Оценка'!F75 + 4*AVERAGE('Оценка'!F75:G75) + 'Оценка'!G75)/6 - 2*(('Оценка'!G75 - 'Оценка'!F75)/6) )/5 , ( ('Оценка'!F75 + 4*AVERAGE('Оценка'!F75:G75) + 'Оценка'!G75)/6 + 2*(('Оценка'!G75 - 'Оценка'!F75)/6) )/5 ) * ( ( ('PM (Расчеты)'!$C$22/8 + 'PM (Расчеты)'!$C$23/40) + 'PM (Расчеты)'!$C$21/100 + 'PM (Расчеты)'!$C$25/100 + 'PM (Расчеты)'!$C$26/100 ) + 1 ))*5)
A76: 5 | C76: Rewards Module(Frontend): Referral Module | H76: =IF(OR(ISBLANK('Оценка'!F76), ISBLANK('Оценка'!G76)), "", (AVERAGE( ( ('Оценка'!F76 + 4*AVERAGE('Оценка'!F76:G76) + 'Оценка'!G76)/6 - 2*(('Оценка'!G76 - 'Оценка'!F76)/6) )/5 , ( ('Оценка'!F76 + 4*AVERAGE('Оценка'!F76:G76) + 'Оценка'!G76)/6 + 2*(('Оценка'!G76 - 'Оценка'!F76)/6) )/5 ) * ( ( ('PM (Расчеты)'!$C$22/8 + 'PM (Расчеты)'!$C$23/40) + 'PM (Расчеты)'!$C$21/100 + 'PM (Расчеты)'!$C$25/100 + 'PM (Расчеты)'!$C$26/100 ) + 1 ))*5)
A77: 5 | B77: Frontend | C77: Раздел в ЛК | D77: правки верстки | F77: 1 | G77: 1 | H77: =IF(OR(ISBLANK('Оценка'!F77), ISBLANK('Оценка'!G77)), "", (AVERAGE( ( ('Оценка'!F77 + 4*AVERAGE('Оценка'!F77:G77) + 'Оценка'!G77)/6 - 2*(('Оценка'!G77 - 'Оценка'!F77)/6) )/5 , ( ('Оценка'!F77 + 4*AVERAGE('Оценка'!F77:G77) + 'Оценка'!G77)/6 + 2*(('Оценка'!G77 - 'Оценка'!F77)/6) )/5 ) * ( ( ('PM (Расчеты)'!$C$22/8 + 'PM (Расчеты)'!$C$23/40) + 'PM (Расчеты)'!$C$21/100 + 'PM (Расчеты)'!$C$25/100 + 'PM (Расчеты)'!$C$26/100 ) + 1 ))*5) -> 1.6
A78: 5 | B78: Frontend | C78: Таблица сделок | D78: Таблица сделок рефералов, пагинация/фильтры | F78: 1 | G78: 1 | H78: =IF(OR(ISBLANK('Оценка'!F78), ISBLANK('Оценка'!G78)), "", (AVERAGE( ( ('Оценка'!F78 + 4*AVERAGE('Оценка'!F78:G78) + 'Оценка'!G78)/6 - 2*(('Оценка'!G78 - 'Оценка'!F78)/6) )/5 , ( ('Оценка'!F78 + 4*AVERAGE('Оценка'!F78:G78) + 'Оценка'!G78)/6 + 2*(('Оценка'!G78 - 'Оценка'!F78)/6) )/5 ) * ( ( ('PM (Расчеты)'!$C$22/8 + 'PM (Расчеты)'!$C$23/40) + 'PM (Расчеты)'!$C$21/100 + 'PM (Расчеты)'!$C$25/100 + 'PM (Расчеты)'!$C$26/100 ) + 1 ))*5) -> 1.6
A79: 5 | B79: Frontend | C79: Интеграция API | D79: Интеграция получения ссылки, интеграция сохранения кошелька, Интеграция статистики | F79: 1 | G79: 2 | H79: =IF(OR(ISBLANK('Оценка'!F79), ISBLANK('Оценка'!G79)), "", (AVERAGE( ( ('Оценка'!F79 + 4*AVERAGE('Оценка'!F79:G79) + 'Оценка'!G79)/6 - 2*(('Оценка'!G79 - 'Оценка'!F79)/6) )/5 , ( ('Оценка'!F79 + 4*AVERAGE('Оценка'!F79:G79) + 'Оценка'!G79)/6 + 2*(('Оценка'!G79 - 'Оценка'!F79)/6) )/5 ) * ( ( ('PM (Расчеты)'!$C$22/8 + 'PM (Расчеты)'!$C$23/40) + 'PM (Расчеты)'!$C$21/100 + 'PM (Расчеты)'!$C$25/100 + 'PM (Расчеты)'!$C$26/100 ) + 1 ))*5) -> 2.4
A80: 5 | H80: =IF(OR(ISBLANK('Оценка'!F80), ISBLANK('Оценка'!G80)), "", (AVERAGE( ( ('Оценка'!F80 + 4*AVERAGE('Оценка'!F80:G80) + 'Оценка'!G80)/6 - 2*(('Оценка'!G80 - 'Оценка'!F80)/6) )/5 , ( ('Оценка'!F80 + 4*AVERAGE('Оценка'!F80:G80) + 'Оценка'!G80)/6 + 2*(('Оценка'!G80 - 'Оценка'!F80)/6) )/5 ) * ( ( ('PM (Расчеты)'!$C$22/8 + 'PM (Расчеты)'!$C$23/40) + 'PM (Расчеты)'!$C$21/100 + 'PM (Расчеты)'!$C$25/100 + 'PM (Расчеты)'!$C$26/100 ) + 1 ))*5)
A81: 5 | H81: =IF(OR(ISBLANK('Оценка'!F81), ISBLANK('Оценка'!G81)), "", (AVERAGE( ( ('Оценка'!F81 + 4*AVERAGE('Оценка'!F81:G81) + 'Оценка'!G81)/6 - 2*(('Оценка'!G81 - 'Оценка'!F81)/6) )/5 , ( ('Оценка'!F81 + 4*AVERAGE('Оценка'!F81:G81) + 'Оценка'!G81)/6 + 2*(('Оценка'!G81 - 'Оценка'!F81)/6) )/5 ) * ( ( ('PM (Расчеты)'!$C$22/8 + 'PM (Расчеты)'!$C$23/40) + 'PM (Расчеты)'!$C$21/100 + 'PM (Расчеты)'!$C$25/100 + 'PM (Расчеты)'!$C$26/100 ) + 1 ))*5)
A82: 5 | C82: Frontend: Страницы | H82: =IF(OR(ISBLANK('Оценка'!F82), ISBLANK('Оценка'!G82)), "", (AVERAGE( ( ('Оценка'!F82 + 4*AVERAGE('Оценка'!F82:G82) + 'Оценка'!G82)/6 - 2*(('Оценка'!G82 - 'Оценка'!F82)/6) )/5 , ( ('Оценка'!F82 + 4*AVERAGE('Оценка'!F82:G82) + 'Оценка'!G82)/6 + 2*(('Оценка'!G82 - 'Оценка'!F82)/6) )/5 ) * ( ( ('PM (Расчеты)'!$C$22/8 + 'PM (Расчеты)'!$C$23/40) + 'PM (Расчеты)'!$C$21/100 + 'PM (Расчеты)'!$C$25/100 + 'PM (Расчеты)'!$C$26/100 ) + 1 ))*5)
A83: 5 | B83: Frontend | C83: Страница Авторизации | D83: Подключение кошелька, подпись сообщения, JWT | F83: 1 | G83: 2 | H83: =IF(OR(ISBLANK('Оценка'!F83), ISBLANK('Оценка'!G83)), "", (AVERAGE( ( ('Оценка'!F83 + 4*AVERAGE('Оценка'!F83:G83) + 'Оценка'!G83)/6 - 2*(('Оценка'!G83 - 'Оценка'!F83)/6) )/5 , ( ('Оценка'!F83 + 4*AVERAGE('Оценка'!F83:G83) + 'Оценка'!G83)/6 + 2*(('Оценка'!G83 - 'Оценка'!F83)/6) )/5 ) * ( ( ('PM (Расчеты)'!$C$22/8 + 'PM (Расчеты)'!$C$23/40) + 'PM (Расчеты)'!$C$21/100 + 'PM (Расчеты)'!$C$25/100 + 'PM (Расчеты)'!$C$26/100 ) + 1 ))*5) -> 2.4
A84: 5 | B84: Frontend | C84: Страница Профиля | D84: Информация, KYC статус, кошельки, реквизиты, рейтинг, рефералы | F84: 2 | G84: 3 | H84: =IF(OR(ISBLANK('Оценка'!F84), ISBLANK('Оценка'!G84)), "", (AVERAGE( ( ('Оценка'!F84 + 4*AVERAGE('Оценка'!F84:G84) + 'Оценка'!G84)/6 - 2*(('Оценка'!G84 - 'Оценка'!F84)/6) )/5 , ( ('Оценка'!F84 + 4*AVERAGE('Оценка'!F84:G84) + 'Оценка'!G84)/6 + 2*(('Оценка'!G84 - 'Оценка'!F84)/6) )/5 ) * ( ( ('PM (Расчеты)'!$C$22/8 + 'PM (Расчеты)'!$C$23/40) + 'PM (Расчеты)'!$C$21/100 + 'PM (Расчеты)'!$C$25/100 + 'PM (Расчеты)'!$C$26/100 ) + 1 ))*5) -> 4
A85: 5 | B85: Frontend | C85: Страница Стакана (Order Book) | D85: Три колонки (Sell/Pit/Buy), фильтры, WebSocket, карточки ордеров | F85: 4 | G85: 5 | H85: =IF(OR(ISBLANK('Оценка'!F85), ISBLANK('Оценка'!G85)), "", (AVERAGE( ( ('Оценка'!F85 + 4*AVERAGE('Оценка'!F85:G85) + 'Оценка'!G85)/6 - 2*(('Оценка'!G85 - 'Оценка'!F85)/6) )/5 , ( ('Оценка'!F85 + 4*AVERAGE('Оценка'!F85:G85) + 'Оценка'!G85)/6 + 2*(('Оценка'!G85 - 'Оценка'!F85)/6) )/5 ) * ( ( ('PM (Расчеты)'!$C$22/8 + 'PM (Расчеты)'!$C$23/40) + 'PM (Расчеты)'!$C$21/100 + 'PM (Расчеты)'!$C$25/100 + 'PM (Расчеты)'!$C$26/100 ) + 1 ))*5) -> 7.2
A86: 5 | B86: Frontend | C86: Страница Создания Ордера и управление объявлениями | D86: Тип (FIXED/PIT), направление, валюта, сумма, цена, банки, реквизиты | F86: 2 | G86: 3 | H86: =IF(OR(ISBLANK('Оценка'!F86), ISBLANK('Оценка'!G86)), "", (AVERAGE( ( ('Оценка'!F86 + 4*AVERAGE('Оценка'!F86:G86) + 'Оценка'!G86)/6 - 2*(('Оценка'!G86 - 'Оценка'!F86)/6) )/5 , ( ('Оценка'!F86 + 4*AVERAGE('Оценка'!F86:G86) + 'Оценка'!G86)/6 + 2*(('Оценка'!G86 - 'Оценка'!F86)/6) )/5 ) * ( ( ('PM (Расчеты)'!$C$22/8 + 'PM (Расчеты)'!$C$23/40) + 'PM (Расчеты)'!$C$21/100 + 'PM (Расчеты)'!$C$25/100 + 'PM (Расчеты)'!$C$26/100 ) + 1 ))*5) -> 4
A87: 5 | B87: Frontend | C87: Страница Сделки | D87: Информационная панель, шаги, депозит, подтверждения, чат, диспут | F87: 7 | G87: 8 | H87: =IF(OR(ISBLANK('Оценка'!F87), ISBLANK('Оценка'!G87)), "", (AVERAGE( ( ('Оценка'!F87 + 4*AVERAGE('Оценка'!F87:G87) + 'Оценка'!G87)/6 - 2*(('Оценка'!G87 - 'Оценка'!F87)/6) )/5 , ( ('Оценка'!F87 + 4*AVERAGE('Оценка'!F87:G87) + 'Оценка'!G87)/6 + 2*(('Оценка'!G87 - 'Оценка'!F87)/6) )/5 ) * ( ( ('PM (Расчеты)'!$C$22/8 + 'PM (Расчеты)'!$C$23/40) + 'PM (Расчеты)'!$C$21/100 + 'PM (Расчеты)'!$C$25/100 + 'PM (Расчеты)'!$C$26/100 ) + 1 ))*5) -> 12
A88: 5 | B88: Frontend | C88: Страница "Яма" (Pit) | D88: Чат, предложение курса, принятие, фиксация | F88: 1 | G88: 1 | H88: =IF(OR(ISBLANK('Оценка'!F88), ISBLANK('Оценка'!G88)), "", (AVERAGE( ( ('Оценка'!F88 + 4*AVERAGE('Оценка'!F88:G88) + 'Оценка'!G88)/6 - 2*(('Оценка'!G88 - 'Оценка'!F88)/6) )/5 , ( ('Оценка'!F88 + 4*AVERAGE('Оценка'!F88:G88) + 'Оценка'!G88)/6 + 2*(('Оценка'!G88 - 'Оценка'!F88)/6) )/5 ) * ( ( ('PM (Расчеты)'!$C$22/8 + 'PM (Расчеты)'!$C$23/40) + 'PM (Расчеты)'!$C$21/100 + 'PM (Расчеты)'!$C$25/100 + 'PM (Расчеты)'!$C$26/100 ) + 1 ))*5) -> 1.6
A89: 5 | B89: Frontend | C89: Страница Истории Сделок | D89: Список, фильтры, детальная информация | F89: 0.5 | G89: 1 | H89: =IF(OR(ISBLANK('Оценка'!F89), ISBLANK('Оценка'!G89)), "", (AVERAGE( ( ('Оценка'!F89 + 4*AVERAGE('Оценка'!F89:G89) + 'Оценка'!G89)/6 - 2*(('Оценка'!G89 - 'Оценка'!F89)/6) )/5 , ( ('Оценка'!F89 + 4*AVERAGE('Оценка'!F89:G89) + 'Оценка'!G89)/6 + 2*(('Оценка'!G89 - 'Оценка'!F89)/6) )/5 ) * ( ( ('PM (Расчеты)'!$C$22/8 + 'PM (Расчеты)'!$C$23/40) + 'PM (Расчеты)'!$C$21/100 + 'PM (Расчеты)'!$C$25/100 + 'PM (Расчеты)'!$C$26/100 ) + 1 ))*5) -> 1.2
A90: 5 | C90: Frontend: Админ-панель | H90: =IF(OR(ISBLANK('Оценка'!F90), ISBLANK('Оценка'!G90)), "", (AVERAGE( ( ('Оценка'!F90 + 4*AVERAGE('Оценка'!F90:G90) + 'Оценка'!G90)/6 - 2*(('Оценка'!G90 - 'Оценка'!F90)/6) )/5 , ( ('Оценка'!F90 + 4*AVERAGE('Оценка'!F90:G90) + 'Оценка'!G90)/6 + 2*(('Оценка'!G90 - 'Оценка'!F90)/6) )/5 ) * ( ( ('PM (Расчеты)'!$C$22/8 + 'PM (Расчеты)'!$C$23/40) + 'PM (Расчеты)'!$C$21/100 + 'PM (Расчеты)'!$C$25/100 + 'PM (Расчеты)'!$C$26/100 ) + 1 ))*5)
A91: 5 | B91: Frontend | C91: Layout и Dashboard | D91: Сайдбар, навигация, статистика, метрики | F91: 5 | G91: 5 | H91: =IF(OR(ISBLANK('Оценка'!F91), ISBLANK('Оценка'!G91)), "", (AVERAGE( ( ('Оценка'!F91 + 4*AVERAGE('Оценка'!F91:G91) + 'Оценка'!G91)/6 - 2*(('Оценка'!G91 - 'Оценка'!F91)/6) )/5 , ( ('Оценка'!F91 + 4*AVERAGE('Оценка'!F91:G91) + 'Оценка'!G91)/6 + 2*(('Оценка'!G91 - 'Оценка'!F91)/6) )/5 ) * ( ( ('PM (Расчеты)'!$C$22/8 + 'PM (Расчеты)'!$C$23/40) + 'PM (Расчеты)'!$C$21/100 + 'PM (Расчеты)'!$C$25/100 + 'PM (Расчеты)'!$C$26/100 ) + 1 ))*5) -> 8
A92: 5 | B92: Frontend | C92: Управление пользователями | D92: Список, фильтры, детали профиля, KYC, действия | H92: =IF(OR(ISBLANK('Оценка'!F92), ISBLANK('Оценка'!G92)), "", (AVERAGE( ( ('Оценка'!F92 + 4*AVERAGE('Оценка'!F92:G92) + 'Оценка'!G92)/6 - 2*(('Оценка'!G92 - 'Оценка'!F92)/6) )/5 , ( ('Оценка'!F92 + 4*AVERAGE('Оценка'!F92:G92) + 'Оценка'!G92)/6 + 2*(('Оценка'!G92 - 'Оценка'!F92)/6) )/5 ) * ( ( ('PM (Расчеты)'!$C$22/8 + 'PM (Расчеты)'!$C$23/40) + 'PM (Расчеты)'!$C$21/100 + 'PM (Расчеты)'!$C$25/100 + 'PM (Расчеты)'!$C$26/100 ) + 1 ))*5)
A93: 5 | B93: Frontend | C93: Управление ордерами и сделками | D93: Просмотр всех ордеров и сделок | H93: =IF(OR(ISBLANK('Оценка'!F93), ISBLANK('Оценка'!G93)), "", (AVERAGE( ( ('Оценка'!F93 + 4*AVERAGE('Оценка'!F93:G93) + 'Оценка'!G93)/6 - 2*(('Оценка'!G93 - 'Оценка'!F93)/6) )/5 , ( ('Оценка'!F93 + 4*AVERAGE('Оценка'!F93:G93) + 'Оценка'!G93)/6 + 2*(('Оценка'!G93 - 'Оценка'!F93)/6) )/5 ) * ( ( ('PM (Расчеты)'!$C$22/8 + 'PM (Расчеты)'!$C$23/40) + 'PM (Расчеты)'!$C$21/100 + 'PM (Расчеты)'!$C$25/100 + 'PM (Расчеты)'!$C$26/100 ) + 1 ))*5)
A94: 5 | B94: Frontend | C94: Управление диспутами | D94: Список, детали, доказательства, форма решения | H94: =IF(OR(ISBLANK('Оценка'!F94), ISBLANK('Оценка'!G94)), "", (AVERAGE( ( ('Оценка'!F94 + 4*AVERAGE('Оценка'!F94:G94) + 'Оценка'!G94)/6 - 2*(('Оценка'!G94 - 'Оценка'!F94)/6) )/5 , ( ('Оценка'!F94 + 4*AVERAGE('Оценка'!F94:G94) + 'Оценка'!G94)/6 + 2*(('Оценка'!G94 - 'Оценка'!F94)/6) )/5 ) * ( ( ('PM (Расчеты)'!$C$22/8 + 'PM (Расчеты)'!$C$23/40) + 'PM (Расчеты)'!$C$21/100 + 'PM (Расчеты)'!$C$25/100 + 'PM (Расчеты)'!$C$26/100 ) + 1 ))*5)
A96: 5 | C96: Frontend: Интеграция с API | H96: =IF(OR(ISBLANK('Оценка'!F96), ISBLANK('Оценка'!G96)), "", (AVERAGE( ( ('Оценка'!F96 + 4*AVERAGE('Оценка'!F96:G96) + 'Оценка'!G96)/6 - 2*(('Оценка'!G96 - 'Оценка'!F96)/6) )/5 , ( ('Оценка'!F96 + 4*AVERAGE('Оценка'!F96:G96) + 'Оценка'!G96)/6 + 2*(('Оценка'!G96 - 'Оценка'!F96)/6) )/5 ) * ( ( ('PM (Расчеты)'!$C$22/8 + 'PM (Расчеты)'!$C$23/40) + 'PM (Расчеты)'!$C$21/100 + 'PM (Расчеты)'!$C$25/100 + 'PM (Расчеты)'!$C$26/100 ) + 1 ))*5)
A97: 5 | B97: Frontend | C97: Интеграция WebSocket | D97: Стакан, уведомления, обработка ошибок | F97: 1 | G97: 2 | H97: =IF(OR(ISBLANK('Оценка'!F97), ISBLANK('Оценка'!G97)), "", (AVERAGE( ( ('Оценка'!F97 + 4*AVERAGE('Оценка'!F97:G97) + 'Оценка'!G97)/6 - 2*(('Оценка'!G97 - 'Оценка'!F97)/6) )/5 , ( ('Оценка'!F97 + 4*AVERAGE('Оценка'!F97:G97) + 'Оценка'!G97)/6 + 2*(('Оценка'!G97 - 'Оценка'!F97)/6) )/5 ) * ( ( ('PM (Расчеты)'!$C$22/8 + 'PM (Расчеты)'!$C$23/40) + 'PM (Расчеты)'!$C$21/100 + 'PM (Расчеты)'!$C$25/100 + 'PM (Расчеты)'!$C$26/100 ) + 1 ))*5) -> 2.4
H98: =IF(OR(ISBLANK('Оценка'!F98), ISBLANK('Оценка'!G98)), "", (AVERAGE( ( ('Оценка'!F98 + 4*AVERAGE('Оценка'!F98:G98) + 'Оценка'!G98)/6 - 2*(('Оценка'!G98 - 'Оценка'!F98)/6) )/5 , ( ('Оценка'!F98 + 4*AVERAGE('Оценка'!F98:G98) + 'Оценка'!G98)/6 + 2*(('Оценка'!G98 - 'Оценка'!F98)/6) )/5 ) * ( ( ('PM (Расчеты)'!$C$22/8 + 'PM (Расчеты)'!$C$23/40) + 'PM (Расчеты)'!$C$21/100 + 'PM (Расчеты)'!$C$25/100 + 'PM (Расчеты)'!$C$26/100 ) + 1 ))*5)
C99: Интеграции | H99: =IF(OR(ISBLANK('Оценка'!F99), ISBLANK('Оценка'!G99)), "", (AVERAGE( ( ('Оценка'!F99 + 4*AVERAGE('Оценка'!F99:G99) + 'Оценка'!G99)/6 - 2*(('Оценка'!G99 - 'Оценка'!F99)/6) )/5 , ( ('Оценка'!F99 + 4*AVERAGE('Оценка'!F99:G99) + 'Оценка'!G99)/6 + 2*(('Оценка'!G99 - 'Оценка'!F99)/6) )/5 ) * ( ( ('PM (Расчеты)'!$C$22/8 + 'PM (Расчеты)'!$C$23/40) + 'PM (Расчеты)'!$C$21/100 + 'PM (Расчеты)'!$C$25/100 + 'PM (Расчеты)'!$C$26/100 ) + 1 ))*5)
A100: 5 | B100: Frontend | C100: KYC Интеграция | D100: Изучение документации КУС | F100: 1 | G100: 1 | H100: =IF(OR(ISBLANK('Оценка'!F100), ISBLANK('Оценка'!G100)), "", (AVERAGE( ( ('Оценка'!F100 + 4*AVERAGE('Оценка'!F100:G100) + 'Оценка'!G100)/6 - 2*(('Оценка'!G100 - 'Оценка'!F100)/6) )/5 , ( ('Оценка'!F100 + 4*AVERAGE('Оценка'!F100:G100) + 'Оценка'!G100)/6 + 2*(('Оценка'!G100 - 'Оценка'!F100)/6) )/5 ) * ( ( ('PM (Расчеты)'!$C$22/8 + 'PM (Расчеты)'!$C$23/40) + 'PM (Расчеты)'!$C$21/100 + 'PM (Расчеты)'!$C$25/100 + 'PM (Расчеты)'!$C$26/100 ) + 1 ))*5) -> 1.6
A101: 5 | B101: Frontend | C101: Чат Интеграция | D101: Изучение документации чата | F101: 1 | G101: 1 | H101: =IF(OR(ISBLANK('Оценка'!F101), ISBLANK('Оценка'!G101)), "", (AVERAGE( ( ('Оценка'!F101 + 4*AVERAGE('Оценка'!F101:G101) + 'Оценка'!G101)/6 - 2*(('Оценка'!G101 - 'Оценка'!F101)/6) )/5 , ( ('Оценка'!F101 + 4*AVERAGE('Оценка'!F101:G101) + 'Оценка'!G101)/6 + 2*(('Оценка'!G101 - 'Оценка'!F101)/6) )/5 ) * ( ( ('PM (Расчеты)'!$C$22/8 + 'PM (Расчеты)'!$C$23/40) + 'PM (Расчеты)'!$C$21/100 + 'PM (Расчеты)'!$C$25/100 + 'PM (Расчеты)'!$C$26/100 ) + 1 ))*5) -> 1.6
A102: 5 | D102: Адаптив | H102: =IF(OR(ISBLANK('Оценка'!F102), ISBLANK('Оценка'!G102)), "", (AVERAGE( ( ('Оценка'!F102 + 4*AVERAGE('Оценка'!F102:G102) + 'Оценка'!G102)/6 - 2*(('Оценка'!G102 - 'Оценка'!F102)/6) )/5 , ( ('Оценка'!F102 + 4*AVERAGE('Оценка'!F102:G102) + 'Оценка'!G102)/6 + 2*(('Оценка'!G102 - 'Оценка'!F102)/6) )/5 ) * ( ( ('PM (Расчеты)'!$C$22/8 + 'PM (Расчеты)'!$C$23/40) + 'PM (Расчеты)'!$C$21/100 + 'PM (Расчеты)'!$C$25/100 + 'PM (Расчеты)'!$C$26/100 ) + 1 ))*5)
A103: 5 | B103: Frontend | C103: Доработка интерфейсов под мобильные устройства | F103: 3 | G103: 4 | H103: =IF(OR(ISBLANK('Оценка'!F103), ISBLANK('Оценка'!G103)), "", (AVERAGE( ( ('Оценка'!F103 + 4*AVERAGE('Оценка'!F103:G103) + 'Оценка'!G103)/6 - 2*(('Оценка'!G103 - 'Оценка'!F103)/6) )/5 , ( ('Оценка'!F103 + 4*AVERAGE('Оценка'!F103:G103) + 'Оценка'!G103)/6 + 2*(('Оценка'!G103 - 'Оценка'!F103)/6) )/5 ) * ( ( ('PM (Расчеты)'!$C$22/8 + 'PM (Расчеты)'!$C$23/40) + 'PM (Расчеты)'!$C$21/100 + 'PM (Расчеты)'!$C$25/100 + 'PM (Расчеты)'!$C$26/100 ) + 1 ))*5) -> 5.6
A104: 3 | B104: Backend | C104: Unit-тестирование Backend | D104: Jest, покрытие сервисов (User, Trading, Payment, Dispute, Rewards) > 70% | F104: 2 | G104: 3 | H104: =IF(OR(ISBLANK('Оценка'!F104), ISBLANK('Оценка'!G104)), "", (AVERAGE( ( ('Оценка'!F104 + 4*AVERAGE('Оценка'!F104:G104) + 'Оценка'!G104)/6 - 2*(('Оценка'!G104 - 'Оценка'!F104)/6) )/5 , ( ('Оценка'!F104 + 4*AVERAGE('Оценка'!F104:G104) + 'Оценка'!G104)/6 + 2*(('Оценка'!G104 - 'Оценка'!F104)/6) )/5 ) * ( ( ('PM (Расчеты)'!$C$22/8 + 'PM (Расчеты)'!$C$23/40) + 'PM (Расчеты)'!$C$21/100 + 'PM (Расчеты)'!$C$25/100 + 'PM (Расчеты)'!$C$26/100 ) + 1 ))*5) -> 4
...

Sheet PM (Расчеты)
A1: ⭠ Инструкция к заполнению (нажми "+") | D1: - ячейки, которые необходимо заполнить
A2: 1. В столбце А, начиная с строки 5, вносятся ФИО или тип работ, соответсвующий выбранному типу работ в вкладке "Оценка". 2. В столбце Н, начиная с строки 5, вносятся ставки на руки специалистов на проетке. 3. В столбце С, начиная с строки 15, выбираются коэффиценты необходимые на проекте. 4. Восле занесения всех данных и окончательной оценки, в ячейке С8, сумарно сколько рабочих недель планируетс реализовывать проект (в недели 5 дней по 8 часов в дне).
B4: Проектная команда/тип работ: | C4: Виды работ | D4: Часовая ставка: | E4: Ставка на клиенте | G4: Проектная команда/тип работ: | H4: Виды работ | I4: Продолжительность работ в неделях | J4: Себестоимость
B5: Manual QA | C5: Manual QA | D5: 0 | E5: ='Sales (Итоги оценки)'!K6 | G5: Тестировщик | H5: Тестировщик | I5: =SUM(I7:I18)*C24/100 -> 0 | J5: =I5*5*8*D5 -> 0
B6: Project manager | C6: Project manager | D6: 15 | E6: ='Sales (Итоги оценки)'!K7 -> 30 | G6: Менеджер | H6: Менеджер | I6: =MAX(I7:I18)*(C27/100) -> 3.816 | J6: =I6*5*8*D6 -> 2289.6
B7: DevOps | C7: 1 | D7: 25 | E7: ='Sales (Итоги оценки)'!K8 -> 50 | G7: =B7 -> DevOps | H7: 1 | I7: =AVERAGE((('Оценка'!B5 + 4*AVERAGE('Оценка'!B5:C5) + 'Оценка'!C5)/6 - 2*(('Оценка'!C5 - 'Оценка'!B5)/6))/5 , (('Оценка'!B5 + 4*AVERAGE('Оценка'!B5:C5) + 'Оценка'!C5)/6 + 2*(('Оценка'!C5 - 'Оценка'!B5)/6))/5)*(((($C$22/8+$C$23/40)+$C$21/100+$C$25/100+$C$26/100)+1 )) -> 4.4 | J7: =I7*5*8*D7 -> 4400
B8: Smart contract | C8: 2 | D8: 30 | E8: ='Sales (Итоги оценки)'!K9 -> 50 | G8: =B8 -> Smart contract | H8: 2 | I8: =AVERAGE((('Оценка'!B6 + 4*AVERAGE('Оценка'!B6:C6) + 'Оценка'!C6)/6 - 2*(('Оценка'!C6 - 'Оценка'!B6)/6))/5 , (('Оценка'!B6 + 4*AVERAGE('Оценка'!B6:C6) + 'Оценка'!C6)/6 + 2*(('Оценка'!C6 - 'Оценка'!B6)/6))/5)*(((($C$22/8+$C$23/40)+$C$21/100+$C$25/100+$C$26/100)+1 )) -> 2.96 | J8: =I8*5*8*D8 -> 3552
B9: Backend | C9: 3 | D9: 31 | E9: ='Sales (Итоги оценки)'!K10 -> 51.666667 | G9: =B9 -> Backend | H9: 3 | I9: =AVERAGE((('Оценка'!B7 + 4*AVERAGE('Оценка'!B7:C7) + 'Оценка'!C7)/6 - 2*(('Оценка'!C7 - 'Оценка'!B7)/6))/5 , (('Оценка'!B7 + 4*AVERAGE('Оценка'!B7:C7) + 'Оценка'!C7)/6 + 2*(('Оценка'!C7 - 'Оценка'!B7)/6))/5)*(((($C$22/8+$C$23/40)+$C$21/100+$C$25/100+$C$26/100)+1 )) -> 10.16 | J9: =I9*5*8*D9 -> 12598.4
B10: Backend | C10: 4 | D10: 21 | E10: ='Sales (Итоги оценки)'!K11 -> 42 | G10: =B10 -> Backend | H10: 4 | I10: =AVERAGE((('Оценка'!B8 + 4*AVERAGE('Оценка'!B8:C8) + 'Оценка'!C8)/6 - 2*(('Оценка'!C8 - 'Оценка'!B8)/6))/5 , (('Оценка'!B8 + 4*AVERAGE('Оценка'!B8:C8) + 'Оценка'!C8)/6 + 2*(('Оценка'!C8 - 'Оценка'!B8)/6))/5)*(((($C$22/8+$C$23/40)+$C$21/100+$C$25/100+$C$26/100)+1 )) -> 10.88 | J10: =I10*5*8*D10 -> 9139.2
B11: Frontend | C11: 5 | D11: 20 | E11: ='Sales (Итоги оценки)'!K12 -> 40 | G11: =B11 -> Frontend | H11: 5 | I11: =AVERAGE((('Оценка'!B9 + 4*AVERAGE('Оценка'!B9:C9) + 'Оценка'!C9)/6 - 2*(('Оценка'!C9 - 'Оценка'!B9)/6))/5 , (('Оценка'!B9 + 4*AVERAGE('Оценка'!B9:C9) + 'Оценка'!C9)/6 + 2*(('Оценка'!C9 - 'Оценка'!B9)/6))/5)*(((($C$22/8+$C$23/40)+$C$21/100+$C$25/100+$C$26/100)+1 )) -> 12.72 | J11: =I11*5*8*D11 -> 10176
B12: QA | C12: 6 | D12: 15 | E12: ='Sales (Итоги оценки)'!K13 -> 30 | G12: =B12 -> QA | H12: 6 | I12: =AVERAGE((('Оценка'!B10 + 4*AVERAGE('Оценка'!B10:C10) + 'Оценка'!C10)/6 - 2*(('Оценка'!C10 - 'Оценка'!B10)/6))/5 , (('Оценка'!B10 + 4*AVERAGE('Оценка'!B10:C10) + 'Оценка'!C10)/6 + 2*(('Оценка'!C10 - 'Оценка'!B10)/6))/5)*(((($C$22/8+$C$23/40)+$C$21/100+$C$25/100+$C$26/100)+1 )) -> 4.8 | J12: =I12*5*8*D12 -> 2880
B13: UX/UI дизайнер | C13: 7 | D13: 20 | E13: ='Sales (Итоги оценки)'!K14 -> 40 | G13: =B13 -> UX/UI дизайнер | H13: 7 | I13: =AVERAGE((('Оценка'!F5 + 4*AVERAGE('Оценка'!F5:G5) + 'Оценка'!G5)/6 - 2*(('Оценка'!G5 - 'Оценка'!F5)/6))/5 , (('Оценка'!F5 + 4*AVERAGE('Оценка'!F5:G5) + 'Оценка'!G5)/6 + 2*(('Оценка'!G5 - 'Оценка'!F5)/6))/5)*(((($C$22/8+$C$23/40)+$C$21/100+$C$25/100+$C$26/100)+1 )) -> 4.8 | J13: =I13*5*8*D13 -> 3840
G14: =B14 | H14: 8 | I14: =AVERAGE((('Оценка'!F6 + 4*AVERAGE('Оценка'!F6:G6) + 'Оценка'!G6)/6 - 2*(('Оценка'!G6 - 'Оценка'!F6)/6))/5 , (('Оценка'!F6 + 4*AVERAGE('Оценка'!F6:G6) + 'Оценка'!G6)/6 + 2*(('Оценка'!G6 - 'Оценка'!F6)/6))/5)*(((($C$22/8+$C$23/40)+$C$21/100+$C$25/100+$C$26/100)+1 )) -> 0 | J14: =I14*5*8*D14 -> 0
G15: =B15 | H15: 9 | I15: =AVERAGE((('Оценка'!F7 + 4*AVERAGE('Оценка'!F7:G7) + 'Оценка'!G7)/6 - 2*(('Оценка'!G7 - 'Оценка'!F7)/6))/5 , (('Оценка'!F7 + 4*AVERAGE('Оценка'!F7:G7) + 'Оценка'!G7)/6 + 2*(('Оценка'!G7 - 'Оценка'!F7)/6))/5)*(((($C$22/8+$C$23/40)+$C$21/100+$C$25/100+$C$26/100)+1 )) -> 0 | J15: =I15*5*8*D15 -> 0
G16: =B16 | H16: 10 | I16: =AVERAGE((('Оценка'!F8 + 4*AVERAGE('Оценка'!F8:G8) + 'Оценка'!G8)/6 - 2*(('Оценка'!G8 - 'Оценка'!F8)/6))/5 , (('Оценка'!F8 + 4*AVERAGE('Оценка'!F8:G8) + 'Оценка'!G8)/6 + 2*(('Оценка'!G8 - 'Оценка'!F8)/6))/5)*(((($C$22/8+$C$23/40)+$C$21/100+$C$25/100+$C$26/100)+1 )) -> 0 | J16: =I16*5*8*D16 -> 0
G17: =B17 | H17: 11 | I17: =AVERAGE((('Оценка'!F9 + 4*AVERAGE('Оценка'!F9:G9) + 'Оценка'!G9)/6 - 2*(('Оценка'!G9 - 'Оценка'!F9)/6))/5 , (('Оценка'!F9 + 4*AVERAGE('Оценка'!F9:G9) + 'Оценка'!G9)/6 + 2*(('Оценка'!G9 - 'Оценка'!F9)/6))/5)*(((($C$22/8+$C$23/40)+$C$21/100+$C$25/100+$C$26/100)+1 )) -> 0 | J17: =I17*5*8*D17 -> 0
G18: =B18 | H18: 12 | I18: =AVERAGE((('Оценка'!F10 + 4*AVERAGE('Оценка'!F10:G10) + 'Оценка'!G10)/6 - 2*(('Оценка'!G10 - 'Оценка'!F10)/6))/5 , (('Оценка'!F10 + 4*AVERAGE('Оценка'!F10:G10) + 'Оценка'!G10)/6 + 2*(('Оценка'!G10 - 'Оценка'!F10)/6))/5)*(((($C$22/8+$C$23/40)+$C$21/100+$C$25/100+$C$26/100)+1 )) -> 0 | J18: =I18*5*8*D18 -> 0
C20: Коэффициенты | D20: Недель | G20: Себестоимость
B21: Проверка и отладка задач (%) | C21: 20 | D21: =(SUM(I7:I18)/((((C22/8+C23/40)+C21/100+C25/100+C26/100)+1 ))*$C$21/100) -> 6.34 | G21: Себестоимость проекта: | H21: =(D5*I5+D6*I6+D7*I7+D8*I8+D9*I9+D10*I10+D11*I11+D12*I12+D13*I13+D14*I14+D15*I15+D16*I16+D17*I17+D18*I18)*5*8 -> 48875.2
B22: Код ревью (Количество часов на разработчика в день). В норме 1 час. | C22: 1 | D22: =(SUM(I7:I18)/((((C22/8+C23/40)+C21/100+C25/100+C26/100)+1 ))*C22/8) -> 3.9625
B23: Коммуникации (3 часа в неделю на каждого) | C23: 3 | D23: =(SUM(I7:I18)/((((C22/8+C23/40)+C21/100+C25/100+C26/100)+1 ))*C23/40) -> 2.3775
B24: Тестировщик | C24: 0 | D24: =SUM(I7:I18)/((((C22/8+C23/40)+C21/100+C25/100+C26/100)+1 ))*C24/100 -> 0
B25: Буфер на риски | C25: 20 | D25: =SUM(I6:I18)/((((C22/8+C23/40)+C21/100+C25/100+C26/100)+1 ))*C25/100 -> 6.817
B26: DevOps | C26: 0 | D26: =SUM(I7:I18)/((((C22/8+C23/40)+C21/100+C25/100+C26/100)+1 ))*C26/100 -> 0
B27: Менеджер | C27: 30 | D27: =MAX(I7:I18)*C27/100 -> 3.816

Sheet Для Битрикса 
A1: Название | B1: Описание | C1: Это важная задача | D1: Разрешить ответственному менять сроки задачи | E1: Пропустить выходные и праздничные дни | F1: Проконтролировать задачу после завершения | G1: Проект | H1: Задано время на завершение задачи | I1: Время на выполнение задачи в секундах | J1: Теги | K1: Начать задачу с | L1: Завершить задачу
A2: ='Оценка'!C13 -> Создание и настройка репозиториев | B2: ='Оценка'!D12 | C2: =IF(A2<>"", 0, "") -> 0 | D2: =IF(A2<>"", 0, "") -> 0 | E2: =IF(A2<>"", 1, "") -> 1 | F2: =IF(A2<>"", 1, "") -> 1 | G2: =IF(A2<>"", 'Sales (Итоги оценки)'!$C$4, "") -> P2P платформа | H2: =IF(A2<>"", 1, "") -> 1 | I2: =IF(OR(ISBLANK('Оценка'!F12), ISBLANK('Оценка'!G12)), "", (AVERAGE( ( ('Оценка'!F12 + 4*AVERAGE('Оценка'!F12:G12) + 'Оценка'!G12)/6 - 2*(('Оценка'!G12 - 'Оценка'!F12)/6) )/5 , ( ('Оценка'!F12 + 4*AVERAGE('Оценка'!F12:G12) + 'Оценка'!G12)/6 + 2*(('Оценка'!G12 - 'Оценка'!F12)/6) )/5 ) * ( ( ('PM (Расчеты)'!$C$22/8 + 'PM (Расчеты)'!$C$23/40) + 'PM (Расчеты)'!$C$21/100 + 'PM (Расчеты)'!$C$25/100 + 'PM (Расчеты)'!$C$26/100 ) + 1 ))) * 8 * 60 * 60 -> 0 | J2: ='Оценка'!B12 | K2: =IF(A2<>"", TODAY() , "") -> 46121 | L2: =IF(A2<>"", TODAY() + (I2 /60/60) , "") -> 46121
A3: =#REF! -> #REF! | B3: ='Оценка'!D13 -> Backend, Frontend, Contracts — структура, README, права доступа | C3: =IF(A3<>"", 0, "") -> #REF! | D3: =IF(A3<>"", 0, "") -> #REF! | E3: =IF(A3<>"", 1, "") -> #REF! | F3: =IF(A3<>"", 1, "") -> #REF! | G3: =IF(A3<>"", 'Sales (Итоги оценки)'!$C$4, "") -> #REF! | H3: =IF(A3<>"", 1, "") -> #REF! | I3: =IF(OR(ISBLANK('Оценка'!F13), ISBLANK('Оценка'!G13)), "", (AVERAGE( ( ('Оценка'!F13 + 4*AVERAGE('Оценка'!F13:G13) + 'Оценка'!G13)/6 - 2*(('Оценка'!G13 - 'Оценка'!F13)/6) )/5 , ( ('Оценка'!F13 + 4*AVERAGE('Оценка'!F13:G13) + 'Оценка'!G13)/6 + 2*(('Оценка'!G13 - 'Оценка'!F13)/6) )/5 ) * ( ( ('PM (Расчеты)'!$C$22/8 + 'PM (Расчеты)'!$C$23/40) + 'PM (Расчеты)'!$C$21/100 + 'PM (Расчеты)'!$C$25/100 + 'PM (Расчеты)'!$C$26/100 ) + 1 ))) * 8 * 60 * 60 -> 6912 | J3: ='Оценка'!B13 -> DevOps | K3: =IF(A3<>"", TODAY() , "") -> #REF! | L3: =IF(A3<>"", TODAY() + (I3 /60/60) , "") -> #REF!
A4: ='Оценка'!C14 -> Настройка CI/CD pipelines | B4: ='Оценка'!D14 -> Сборка, линтинг, тесты, деплой для всех репозиториев | C4: =IF(A4<>"", 0, "") -> 0 | D4: =IF(A4<>"", 0, "") -> 0 | E4: =IF(A4<>"", 1, "") -> 1 | F4: =IF(A4<>"", 1, "") -> 1 | G4: =IF(A4<>"", 'Sales (Итоги оценки)'!$C$4, "") -> P2P платформа | H4: =IF(A4<>"", 1, "") -> 1 | I4: =IF(OR(ISBLANK('Оценка'!F14), ISBLANK('Оценка'!G14)), "", (AVERAGE( ( ('Оценка'!F14 + 4*AVERAGE('Оценка'!F14:G14) + 'Оценка'!G14)/6 - 2*(('Оценка'!G14 - 'Оценка'!F14)/6) )/5 , ( ('Оценка'!F14 + 4*AVERAGE('Оценка'!F14:G14) + 'Оценка'!G14)/6 + 2*(('Оценка'!G14 - 'Оценка'!F14)/6) )/5 ) * ( ( ('PM (Расчеты)'!$C$22/8 + 'PM (Расчеты)'!$C$23/40) + 'PM (Расчеты)'!$C$21/100 + 'PM (Расчеты)'!$C$25/100 + 'PM (Расчеты)'!$C$26/100 ) + 1 ))) * 8 * 60 * 60 -> 13824 | J4: ='Оценка'!B14 -> DevOps | K4: =IF(A4<>"", TODAY() , "") -> 46121 | L4: =IF(A4<>"", TODAY() + (I4 /60/60) , "") -> 46124.84
A5: ='Оценка'!C15 -> Настройка PostgreSQL | B5: ='Оценка'!D15 -> Установка, конфигурация, резервное копирование | C5: =IF(A5<>"", 0, "") -> 0 | D5: =IF(A5<>"", 0, "") -> 0 | E5: =IF(A5<>"", 1, "") -> 1 | F5: =IF(A5<>"", 1, "") -> 1 | G5: =IF(A5<>"", 'Sales (Итоги оценки)'!$C$4, "") -> P2P платформа | H5: =IF(A5<>"", 1, "") -> 1 | I5: =IF(OR(ISBLANK('Оценка'!F15), ISBLANK('Оценка'!G15)), "", (AVERAGE( ( ('Оценка'!F15 + 4*AVERAGE('Оценка'!F15:G15) + 'Оценка'!G15)/6 - 2*(('Оценка'!G15 - 'Оценка'!F15)/6) )/5 , ( ('Оценка'!F15 + 4*AVERAGE('Оценка'!F15:G15) + 'Оценка'!G15)/6 + 2*(('Оценка'!G15 - 'Оценка'!F15)/6) )/5 ) * ( ( ('PM (Расчеты)'!$C$22/8 + 'PM (Расчеты)'!$C$23/40) + 'PM (Расчеты)'!$C$21/100 + 'PM (Расчеты)'!$C$25/100 + 'PM (Расчеты)'!$C$26/100 ) + 1 ))) * 8 * 60 * 60 -> 13824 | J5: ='Оценка'!B15 -> DevOps | K5: =IF(A5<>"", TODAY() , "") -> 46121 | L5: =IF(A5<>"", TODAY() + (I5 /60/60) , "") -> 46124.84
A6: ='Оценка'!C16 -> Настройка Redis | B6: ='Оценка'!D16 -> Кэш, очереди, сессии | C6: =IF(A6<>"", 0, "") -> 0 | D6: =IF(A6<>"", 0, "") -> 0 | E6: =IF(A6<>"", 1, "") -> 1 | F6: =IF(A6<>"", 1, "") -> 1 | G6: =IF(A6<>"", 'Sales (Итоги оценки)'!$C$4, "") -> P2P платформа | H6: =IF(A6<>"", 1, "") -> 1 | I6: =IF(OR(ISBLANK('Оценка'!F16), ISBLANK('Оценка'!G16)), "", (AVERAGE( ( ('Оценка'!F16 + 4*AVERAGE('Оценка'!F16:G16) + 'Оценка'!G16)/6 - 2*(('Оценка'!G16 - 'Оценка'!F16)/6) )/5 , ( ('Оценка'!F16 + 4*AVERAGE('Оценка'!F16:G16) + 'Оценка'!G16)/6 + 2*(('Оценка'!G16 - 'Оценка'!F16)/6) )/5 ) * ( ( ('PM (Расчеты)'!$C$22/8 + 'PM (Расчеты)'!$C$23/40) + 'PM (Расчеты)'!$C$21/100 + 'PM (Расчеты)'!$C$25/100 + 'PM (Расчеты)'!$C$26/100 ) + 1 ))) * 8 * 60 * 60 -> 13824 | J6: ='Оценка'!B16 -> DevOps | K6: =IF(A6<>"", TODAY() , "") -> 46121 | L6: =IF(A6<>"", TODAY() + (I6 /60/60) , "") -> 46124.84
A7: ='Оценка'!C17 -> Настройка HashiCorp Vault | B7: ='Оценка'!D17 -> Хранение секретов, ключей шифрования | C7: =IF(A7<>"", 0, "") -> 0 | D7: =IF(A7<>"", 0, "") -> 0 | E7: =IF(A7<>"", 1, "") -> 1 | F7: =IF(A7<>"", 1, "") -> 1 | G7: =IF(A7<>"", 'Sales (Итоги оценки)'!$C$4, "") -> P2P платформа | H7: =IF(A7<>"", 1, "") -> 1 | I7: =IF(OR(ISBLANK('Оценка'!F17), ISBLANK('Оценка'!G17)), "", (AVERAGE( ( ('Оценка'!F17 + 4*AVERAGE('Оценка'!F17:G17) + 'Оценка'!G17)/6 - 2*(('Оценка'!G17 - 'Оценка'!F17)/6) )/5 , ( ('Оценка'!F17 + 4*AVERAGE('Оценка'!F17:G17) + 'Оценка'!G17)/6 + 2*(('Оценка'!G17 - 'Оценка'!F17)/6) )/5 ) * ( ( ('PM (Расчеты)'!$C$22/8 + 'PM (Расчеты)'!$C$23/40) + 'PM (Расчеты)'!$C$21/100 + 'PM (Расчеты)'!$C$25/100 + 'PM (Расчеты)'!$C$26/100 ) + 1 ))) * 8 * 60 * 60 -> 13824 | J7: ='Оценка'!B17 -> DevOps | K7: =IF(A7<>"", TODAY() , "") -> 46121 | L7: =IF(A7<>"", TODAY() + (I7 /60/60) , "") -> 46124.84
A8: ='Оценка'!C18 -> Настройка Nginx и доменов | B8: ='Оценка'!D18 -> Reverse proxy, SSL, rate limiting, DNS | C8: =IF(A8<>"", 0, "") -> 0 | D8: =IF(A8<>"", 0, "") -> 0 | E8: =IF(A8<>"", 1, "") -> 1 | F8: =IF(A8<>"", 1, "") -> 1 | G8: =IF(A8<>"", 'Sales (Итоги оценки)'!$C$4, "") -> P2P платформа | H8: =IF(A8<>"", 1, "") -> 1 | I8: =IF(OR(ISBLANK('Оценка'!F18), ISBLANK('Оценка'!G18)), "", (AVERAGE( ( ('Оценка'!F18 + 4*AVERAGE('Оценка'!F18:G18) + 'Оценка'!G18)/6 - 2*(('Оценка'!G18 - 'Оценка'!F18)/6) )/5 , ( ('Оценка'!F18 + 4*AVERAGE('Оценка'!F18:G18) + 'Оценка'!G18)/6 + 2*(('Оценка'!G18 - 'Оценка'!F18)/6) )/5 ) * ( ( ('PM (Расчеты)'!$C$22/8 + 'PM (Расчеты)'!$C$23/40) + 'PM (Расчеты)'!$C$21/100 + 'PM (Расчеты)'!$C$25/100 + 'PM (Расчеты)'!$C$26/100 ) + 1 ))) * 8 * 60 * 60 -> 23040 | J8: ='Оценка'!B18 -> DevOps | K8: =IF(A8<>"", TODAY() , "") -> 46121 | L8: =IF(A8<>"", TODAY() + (I8 /60/60) , "") -> 46127.4
A9: ='Оценка'!C19 -> Настройка мониторинга и алертинга | B9: ='Оценка'!D19 -> Prometheus, Grafana, PagerDuty/Slack интеграция | C9: =IF(A9<>"", 0, "") -> 0 | D9: =IF(A9<>"", 0, "") -> 0 | E9: =IF(A9<>"", 1, "") -> 1 | F9: =IF(A9<>"", 1, "") -> 1 | G9: =IF(A9<>"", 'Sales (Итоги оценки)'!$C$4, "") -> P2P платформа | H9: =IF(A9<>"", 1, "") -> 1 | I9: =IF(OR(ISBLANK('Оценка'!F19), ISBLANK('Оценка'!G19)), "", (AVERAGE( ( ('Оценка'!F19 + 4*AVERAGE('Оценка'!F19:G19) + 'Оценка'!G19)/6 - 2*(('Оценка'!G19 - 'Оценка'!F19)/6) )/5 , ( ('Оценка'!F19 + 4*AVERAGE('Оценка'!F19:G19) + 'Оценка'!G19)/6 + 2*(('Оценка'!G19 - 'Оценка'!F19)/6) )/5 ) * ( ( ('PM (Расчеты)'!$C$22/8 + 'PM (Расчеты)'!$C$23/40) + 'PM (Расчеты)'!$C$21/100 + 'PM (Расчеты)'!$C$25/100 + 'PM (Расчеты)'!$C$26/100 ) + 1 ))) * 8 * 60 * 60 -> 23040 | J9: ='Оценка'!B19 -> DevOps | K9: =IF(A9<>"", TODAY() , "") -> 46121 | L9: =IF(A9<>"", TODAY() + (I9 /60/60) , "") -> 46127.4
A10: ='Оценка'!C20 -> Настройка централизованного логирования | B10: ='Оценка'!D20 | C10: =IF(A10<>"", 0, "") -> 0 | D10: =IF(A10<>"", 0, "") -> 0 | E10: =IF(A10<>"", 1, "") -> 1 | F10: =IF(A10<>"", 1, "") -> 1 | G10: =IF(A10<>"", 'Sales (Итоги оценки)'!$C$4, "") -> P2P платформа | H10: =IF(A10<>"", 1, "") -> 1 | I10: =IF(OR(ISBLANK('Оценка'!F20), ISBLANK('Оценка'!G20)), "", (AVERAGE( ( ('Оценка'!F20 + 4*AVERAGE('Оценка'!F20:G20) + 'Оценка'!G20)/6 - 2*(('Оценка'!G20 - 'Оценка'!F20)/6) )/5 , ( ('Оценка'!F20 + 4*AVERAGE('Оценка'!F20:G20) + 'Оценка'!G20)/6 + 2*(('Оценка'!G20 - 'Оценка'!F20)/6) )/5 ) * ( ( ('PM (Расчеты)'!$C$22/8 + 'PM (Расчеты)'!$C$23/40) + 'PM (Расчеты)'!$C$21/100 + 'PM (Расчеты)'!$C$25/100 + 'PM (Расчеты)'!$C$26/100 ) + 1 ))) * 8 * 60 * 60 -> 18432 | J10: ='Оценка'!B20 -> DevOps | K10: =IF(A10<>"", TODAY() , "") -> 46121 | L10: =IF(A10<>"", TODAY() + (I10 /60/60) , "") -> 46126.12
A11: ='Оценка'!C25 -> Деплой в testnet (Sepolia) | B11: ='Оценка'!D25 -> Factory + Implementation, верификация в Etherscan | C11: =IF(A11<>"", 0, "") -> 0 | D11: =IF(A11<>"", 0, "") -> 0 | E11: =IF(A11<>"", 1, "") -> 1 | F11: =IF(A11<>"", 1, "") -> 1 | G11: =IF(A11<>"", 'Sales (Итоги оценки)'!$C$4, "") -> P2P платформа | H11: =IF(A11<>"", 1, "") -> 1 | I11: =IF(OR(ISBLANK('Оценка'!F21), ISBLANK('Оценка'!G21)), "", (AVERAGE( ( ('Оценка'!F21 + 4*AVERAGE('Оценка'!F21:G21) + 'Оценка'!G21)/6 - 2*(('Оценка'!G21 - 'Оценка'!F21)/6) )/5 , ( ('Оценка'!F21 + 4*AVERAGE('Оценка'!F21:G21) + 'Оценка'!G21)/6 + 2*(('Оценка'!G21 - 'Оценка'!F21)/6) )/5 ) * ( ( ('PM (Расчеты)'!$C$22/8 + 'PM (Расчеты)'!$C$23/40) + 'PM (Расчеты)'!$C$21/100 + 'PM (Расчеты)'!$C$25/100 + 'PM (Расчеты)'!$C$26/100 ) + 1 ))) * 8 * 60 * 60 -> 0 | J11: ='Оценка'!B25 -> Smart contract | K11: =IF(A11<>"", TODAY() , "") -> 46121 | L11: =IF(A11<>"", TODAY() + (I11 /60/60) , "") -> 46121
A12: ='Оценка'!C26 -> Деплой в mainnet | B12: ='Оценка'!D26 -> Factory + Implementation, настройка мультисиг/Fireblocks | C12: =IF(A12<>"", 0, "") -> 0 | D12: =IF(A12<>"", 0, "") -> 0 | E12: =IF(A12<>"", 1, "") -> 1 | F12: =IF(A12<>"", 1, "") -> 1 | G12: =IF(A12<>"", 'Sales (Итоги оценки)'!$C$4, "") -> P2P платформа | H12: =IF(A12<>"", 1, "") -> 1 | I12: =IF(OR(ISBLANK('Оценка'!F22), ISBLANK('Оценка'!G22)), "", (AVERAGE( ( ('Оценка'!F22 + 4*AVERAGE('Оценка'!F22:G22) + 'Оценка'!G22)/6 - 2*(('Оценка'!G22 - 'Оценка'!F22)/6) )/5 , ( ('Оценка'!F22 + 4*AVERAGE('Оценка'!F22:G22) + 'Оценка'!G22)/6 + 2*(('Оценка'!G22 - 'Оценка'!F22)/6) )/5 ) * ( ( ('PM (Расчеты)'!$C$22/8 + 'PM (Расчеты)'!$C$23/40) + 'PM (Расчеты)'!$C$21/100 + 'PM (Расчеты)'!$C$25/100 + 'PM (Расчеты)'!$C$26/100 ) + 1 ))) * 8 * 60 * 60 -> 11520 | J12: ='Оценка'!B26 -> Smart contract | K12: =IF(A12<>"", TODAY() , "") -> 46121 | L12: =IF(A12<>"", TODAY() + (I12 /60/60) , "") -> 46124.2
A13: ='Оценка'!C27 -> Аудит безопасности | B13: ='Оценка'!D27 -> Внешний аудит, исправление найденных проблем | C13: =IF(A13<>"", 0, "") -> 0 | D13: =IF(A13<>"", 0, "") -> 0 | E13: =IF(A13<>"", 1, "") -> 1 | F13: =IF(A13<>"", 1, "") -> 1 | G13: =IF(A13<>"", 'Sales (Итоги оценки)'!$C$4, "") -> P2P платформа | H13: =IF(A13<>"", 1, "") -> 1 | I13: =IF(OR(ISBLANK('Оценка'!F23), ISBLANK('Оценка'!G23)), "", (AVERAGE( ( ('Оценка'!F23 + 4*AVERAGE('Оценка'!F23:G23) + 'Оценка'!G23)/6 - 2*(('Оценка'!G23 - 'Оценка'!F23)/6) )/5 , ( ('Оценка'!F23 + 4*AVERAGE('Оценка'!F23:G23) + 'Оценка'!G23)/6 + 2*(('Оценка'!G23 - 'Оценка'!F23)/6) )/5 ) * ( ( ('PM (Расчеты)'!$C$22/8 + 'PM (Расчеты)'!$C$23/40) + 'PM (Расчеты)'!$C$21/100 + 'PM (Расчеты)'!$C$25/100 + 'PM (Расчеты)'!$C$26/100 ) + 1 ))) * 8 * 60 * 60 -> 23040 | J13: ='Оценка'!B27 -> Smart contract | K13: =IF(A13<>"", TODAY() , "") -> 46121 | L13: =IF(A13<>"", TODAY() + (I13 /60/60) , "") -> 46127.4
A14: ='Оценка'!C28 -> Backend (Monolith): Инициализация NestJS проекта | B14: ='Оценка'!D28 | C14: =IF(A14<>"", 0, "") -> 0 | D14: =IF(A14<>"", 0, "") -> 0 | E14: =IF(A14<>"", 1, "") -> 1 | F14: =IF(A14<>"", 1, "") -> 1 | G14: =IF(A14<>"", 'Sales (Итоги оценки)'!$C$4, "") -> P2P платформа | H14: =IF(A14<>"", 1, "") -> 1 | I14: =IF(OR(ISBLANK('Оценка'!F24), ISBLANK('Оценка'!G24)), "", (AVERAGE( ( ('Оценка'!F24 + 4*AVERAGE('Оценка'!F24:G24) + 'Оценка'!G24)/6 - 2*(('Оценка'!G24 - 'Оценка'!F24)/6) )/5 , ( ('Оценка'!F24 + 4*AVERAGE('Оценка'!F24:G24) + 'Оценка'!G24)/6 + 2*(('Оценка'!G24 - 'Оценка'!F24)/6) )/5 ) * ( ( ('PM (Расчеты)'!$C$22/8 + 'PM (Расчеты)'!$C$23/40) + 'PM (Расчеты)'!$C$21/100 + 'PM (Расчеты)'!$C$25/100 + 'PM (Расчеты)'!$C$26/100 ) + 1 ))) * 8 * 60 * 60 -> 18432 | J14: ='Оценка'!B28 | K14: =IF(A14<>"", TODAY() , "") -> 46121 | L14: =IF(A14<>"", TODAY() + (I14 /60/60) , "") -> 46126.12
A15: ='Оценка'!C29 -> Настройка инфраструктуры | B15: ='Оценка'!D29 -> TypeORM (PostgreSQL), Redis, Bull Queue, валидация | C15: =IF(A15<>"", 0, "") -> 0 | D15: =IF(A15<>"", 0, "") -> 0 | E15: =IF(A15<>"", 1, "") -> 1 | F15: =IF(A15<>"", 1, "") -> 1 | G15: =IF(A15<>"", 'Sales (Итоги оценки)'!$C$4, "") -> P2P платформа | H15: =IF(A15<>"", 1, "") -> 1 | I15: =IF(OR(ISBLANK('Оценка'!F25), ISBLANK('Оценка'!G25)), "", (AVERAGE( ( ('Оценка'!F25 + 4*AVERAGE('Оценка'!F25:G25) + 'Оценка'!G25)/6 - 2*(('Оценка'!G25 - 'Оценка'!F25)/6) )/5 , ( ('Оценка'!F25 + 4*AVERAGE('Оценка'!F25:G25) + 'Оценка'!G25)/6 + 2*(('Оценка'!G25 - 'Оценка'!F25)/6) )/5 ) * ( ( ('PM (Расчеты)'!$C$22/8 + 'PM (Расчеты)'!$C$23/40) + 'PM (Расчеты)'!$C$21/100 + 'PM (Расчеты)'!$C$25/100 + 'PM (Расчеты)'!$C$26/100 ) + 1 ))) * 8 * 60 * 60 -> 4608 | J15: ='Оценка'!B29 -> Backend | K15: =IF(A15<>"", TODAY() , "") -> 46121 | L15: =IF(A15<>"", TODAY() + (I15 /60/60) , "") -> 46122.28
A16: ='Оценка'!C30 -> Разработка Shared Layer | B16: ='Оценка'!D30 -> Database Service, Cache Service, Queue Service, Auth Service | C16: =IF(A16<>"", 0, "") -> 0 | D16: =IF(A16<>"", 0, "") -> 0 | E16: =IF(A16<>"", 1, "") -> 1 | F16: =IF(A16<>"", 1, "") -> 1 | G16: =IF(A16<>"", 'Sales (Итоги оценки)'!$C$4, "") -> P2P платформа | H16: =IF(A16<>"", 1, "") -> 1 | I16: =IF(OR(ISBLANK('Оценка'!F26), ISBLANK('Оценка'!G26)), "", (AVERAGE( ( ('Оценка'!F26 + 4*AVERAGE('Оценка'!F26:G26) + 'Оценка'!G26)/6 - 2*(('Оценка'!G26 - 'Оценка'!F26)/6) )/5 , ( ('Оценка'!F26 + 4*AVERAGE('Оценка'!F26:G26) + 'Оценка'!G26)/6 + 2*(('Оценка'!G26 - 'Оценка'!F26)/6) )/5 ) * ( ( ('PM (Расчеты)'!$C$22/8 + 'PM (Расчеты)'!$C$23/40) + 'PM (Расчеты)'!$C$21/100 + 'PM (Расчеты)'!$C$25/100 + 'PM (Расчеты)'!$C$26/100 ) + 1 ))) * 8 * 60 * 60 -> 18432 | J16: ='Оценка'!B30 -> Backend | K16: =IF(A16<>"", TODAY() , "") -> 46121 | L16: =IF(A16<>"", TODAY() + (I16 /60/60) , "") -> 46126.12
A17: ='Оценка'!C31 -> Разработка Blockchain Service | B17: ='Оценка'!D31 -> Ethers.js интеграция, RPC, индексатор событий | C17: =IF(A17<>"", 0, "") -> 0 | D17: =IF(A17<>"", 0, "") -> 0 | E17: =IF(A17<>"", 1, "") -> 1 | F17: =IF(A17<>"", 1, "") -> 1 | G17: =IF(A17<>"", 'Sales (Итоги оценки)'!$C$4, "") -> P2P платформа | H17: =IF(A17<>"", 1, "") -> 1 | I17: =IF(OR(ISBLANK('Оценка'!F27), ISBLANK('Оценка'!G27)), "", (AVERAGE( ( ('Оценка'!F27 + 4*AVERAGE('Оценка'!F27:G27) + 'Оценка'!G27)/6 - 2*(('Оценка'!G27 - 'Оценка'!F27)/6) )/5 , ( ('Оценка'!F27 + 4*AVERAGE('Оценка'!F27:G27) + 'Оценка'!G27)/6 + 2*(('Оценка'!G27 - 'Оценка'!F27)/6) )/5 ) * ( ( ('PM (Расчеты)'!$C$22/8 + 'PM (Расчеты)'!$C$23/40) + 'PM (Расчеты)'!$C$21/100 + 'PM (Расчеты)'!$C$25/100 + 'PM (Расчеты)'!$C$26/100 ) + 1 ))) * 8 * 60 * 60 -> 9216 | J17: ='Оценка'!B31 -> Backend | K17: =IF(A17<>"", TODAY() , "") -> 46121 | L17: =IF(A17<>"", TODAY() + (I17 /60/60) , "") -> 46123.56
A18: ='Оценка'!C32 -> Разработка Encryption Service | B18: ='Оценка'!D32 -> AES-256 для шифрования реквизитов | C18: =IF(A18<>"", 0, "") -> 0 | D18: =IF(A18<>"", 0, "") -> 0 | E18: =IF(A18<>"", 1, "") -> 1 | F18: =IF(A18<>"", 1, "") -> 1 | G18: =IF(A18<>"", 'Sales (Итоги оценки)'!$C$4, "") -> P2P платформа | H18: =IF(A18<>"", 1, "") -> 1 | I18: =IF(OR(ISBLANK('Оценка'!F28), ISBLANK('Оценка'!G28)), "", (AVERAGE( ( ('Оценка'!F28 + 4*AVERAGE('Оценка'!F28:G28) + 'Оценка'!G28)/6 - 2*(('Оценка'!G28 - 'Оценка'!F28)/6) )/5 , ( ('Оценка'!F28 + 4*AVERAGE('Оценка'!F28:G28) + 'Оценка'!G28)/6 + 2*(('Оценка'!G28 - 'Оценка'!F28)/6) )/5 ) * ( ( ('PM (Расчеты)'!$C$22/8 + 'PM (Расчеты)'!$C$23/40) + 'PM (Расчеты)'!$C$21/100 + 'PM (Расчеты)'!$C$25/100 + 'PM (Расчеты)'!$C$26/100 ) + 1 ))) * 8 * 60 * 60 -> 0 | J18: ='Оценка'!B32 -> Backend | K18: =IF(A18<>"", TODAY() , "") -> 46121 | L18: =IF(A18<>"", TODAY() + (I18 /60/60) , "") -> 46121
A19: ='Оценка'!C33 -> Backend (Monolith): User Module | B19: ='Оценка'!D33 | C19: =IF(A19<>"", 0, "") -> 0 | D19: =IF(A19<>"", 0, "") -> 0 | E19: =IF(A19<>"", 1, "") -> 1 | F19: =IF(A19<>"", 1, "") -> 1 | G19: =IF(A19<>"", 'Sales (Итоги оценки)'!$C$4, "") -> P2P платформа | H19: =IF(A19<>"", 1, "") -> 1 | I19: =IF(OR(ISBLANK('Оценка'!F29), ISBLANK('Оценка'!G29)), "", (AVERAGE( ( ('Оценка'!F29 + 4*AVERAGE('Оценка'!F29:G29) + 'Оценка'!G29)/6 - 2*(('Оценка'!G29 - 'Оценка'!F29)/6) )/5 , ( ('Оценка'!F29 + 4*AVERAGE('Оценка'!F29:G29) + 'Оценка'!G29)/6 + 2*(('Оценка'!G29 - 'Оценка'!F29)/6) )/5 ) * ( ( ('PM (Расчеты)'!$C$22/8 + 'PM (Расчеты)'!$C$23/40) + 'PM (Расчеты)'!$C$21/100 + 'PM (Расчеты)'!$C$25/100 + 'PM (Расчеты)'!$C$26/100 ) + 1 ))) * 8 * 60 * 60 -> 23040 | J19: ='Оценка'!B33 | K19: =IF(A19<>"", TODAY() , "") -> 46121 | L19: =IF(A19<>"", TODAY() + (I19 /60/60) , "") -> 46127.4
A20: ='Оценка'!C34 -> Создание сущностей | B20: ='Оценка'!D34 -> User (с полями реферальной программы: referrer_id, referrer_wallet, referral_code), Wallet, KycStatus, UserLevel — таблицы, связи, индексы | C20: =IF(A20<>"", 0, "") -> 0 | D20: =IF(A20<>"", 0, "") -> 0 | E20: =IF(A20<>"", 1, "") -> 1 | F20: =IF(A20<>"", 1, "") -> 1 | G20: =IF(A20<>"", 'Sales (Итоги оценки)'!$C$4, "") -> P2P платформа | H20: =IF(A20<>"", 1, "") -> 1 | I20: =IF(OR(ISBLANK('Оценка'!F30), ISBLANK('Оценка'!G30)), "", (AVERAGE( ( ('Оценка'!F30 + 4*AVERAGE('Оценка'!F30:G30) + 'Оценка'!G30)/6 - 2*(('Оценка'!G30 - 'Оценка'!F30)/6) )/5 , ( ('Оценка'!F30 + 4*AVERAGE('Оценка'!F30:G30) + 'Оценка'!G30)/6 + 2*(('Оценка'!G30 - 'Оценка'!F30)/6) )/5 ) * ( ( ('PM (Расчеты)'!$C$22/8 + 'PM (Расчеты)'!$C$23/40) + 'PM (Расчеты)'!$C$21/100 + 'PM (Расчеты)'!$C$25/100 + 'PM (Расчеты)'!$C$26/100 ) + 1 ))) * 8 * 60 * 60 -> 23040 | J20: ='Оценка'!B34 -> Backend | K20: =IF(A20<>"", TODAY() , "") -> 46121 | L20: =IF(A20<>"", TODAY() + (I20 /60/60) , "") -> 46127.4
A21: ='Оценка'!C35 -> Разработка API | B21: ='Оценка'!D35 -> Регистрация, авторизация (Web3 + JWT), профиль, привязка кошелька | C21: =IF(A21<>"", 0, "") -> 0 | D21: =IF(A21<>"", 0, "") -> 0 | E21: =IF(A21<>"", 1, "") -> 1 | F21: =IF(A21<>"", 1, "") -> 1 | G21: =IF(A21<>"", 'Sales (Итоги оценки)'!$C$4, "") -> P2P платформа | H21: =IF(A21<>"", 1, "") -> 1 | I21: =IF(OR(ISBLANK('Оценка'!F31), ISBLANK('Оценка'!G31)), "", (AVERAGE( ( ('Оценка'!F31 + 4*AVERAGE('Оценка'!F31:G31) + 'Оценка'!G31)/6 - 2*(('Оценка'!G31 - 'Оценка'!F31)/6) )/5 , ( ('Оценка'!F31 + 4*AVERAGE('Оценка'!F31:G31) + 'Оценка'!G31)/6 + 2*(('Оценка'!G31 - 'Оценка'!F31)/6) )/5 ) * ( ( ('PM (Расчеты)'!$C$22/8 + 'PM (Расчеты)'!$C$23/40) + 'PM (Расчеты)'!$C$21/100 + 'PM (Расчеты)'!$C$25/100 + 'PM (Расчеты)'!$C$26/100 ) + 1 ))) * 8 * 60 * 60 -> 23040 | J21: ='Оценка'!B35 -> Backend | K21: =IF(A21<>"", TODAY() , "") -> 46121 | L21: =IF(A21<>"", TODAY() + (I21 /60/60) , "") -> 46127.4
A22: ='Оценка'!C36 -> Реализация уровней доступа | B22: ='Оценка'!D36 -> Проверка прав, лимиты | C22: =IF(A22<>"", 0, "") -> 0 | D22: =IF(A22<>"", 0, "") -> 0 | E22: =IF(A22<>"", 1, "") -> 1 | F22: =IF(A22<>"", 1, "") -> 1 | G22: =IF(A22<>"", 'Sales (Итоги оценки)'!$C$4, "") -> P2P платформа | H22: =IF(A22<>"", 1, "") -> 1 | I22: =IF(OR(ISBLANK('Оценка'!F32), ISBLANK('Оценка'!G32)), "", (AVERAGE( ( ('Оценка'!F32 + 4*AVERAGE('Оценка'!F32:G32) + 'Оценка'!G32)/6 - 2*(('Оценка'!G32 - 'Оценка'!F32)/6) )/5 , ( ('Оценка'!F32 + 4*AVERAGE('Оценка'!F32:G32) + 'Оценка'!G32)/6 + 2*(('Оценка'!G32 - 'Оценка'!F32)/6) )/5 ) * ( ( ('PM (Расчеты)'!$C$22/8 + 'PM (Расчеты)'!$C$23/40) + 'PM (Расчеты)'!$C$21/100 + 'PM (Расчеты)'!$C$25/100 + 'PM (Расчеты)'!$C$26/100 ) + 1 ))) * 8 * 60 * 60 -> 13824 | J22: ='Оценка'!B36 -> Backend | K22: =IF(A22<>"", TODAY() , "") -> 46121 | L22: =IF(A22<>"", TODAY() + (I22 /60/60) , "") -> 46124.84
... A40: ='Оценка'!C54 -> Подключение стороннего сервиса аналитики | B40: ='Оценка'!D54 -> Redash или др | C40: =IF(A40<>"", 0, "") -> 0 | D40: =IF(A40<>"", 0, "") -> 0 | E40: =IF(A40<>"", 1, "") -> 1 | F40: =IF(A40<>"", 1, "") -> 1 | G40: =IF(A40<>"", 'Sales (Итоги оценки)'!$C$4, "") -> P2P платформа | H40: =IF(A40<>"", 1, "") -> 1 | I40: =IF(OR(ISBLANK('Оценка'!F50), ISBLANK('Оценка'!G50)), "", (AVERAGE( ( ('Оценка'!F50 + 4*AVERAGE('Оценка'!F50:G50) + 'Оценка'!G50)/6 - 2*(('Оценка'!G50 - 'Оценка'!F50)/6) )/5 , ( ('Оценка'!F50 + 4*AVERAGE('Оценка'!F50:G50) + 'Оценка'!G50)/6 + 2*(('Оценка'!G50 - 'Оценка'!F50)/6) )/5 ) * ( ( ('PM (Расчеты)'!$C$22/8 + 'PM (Расчеты)'!$C$23/40) + 'PM (Расчеты)'!$C$21/100 + 'PM (Расчеты)'!$C$25/100 + 'PM (Расчеты)'!$C$26/100 ) + 1 ))) * 8 * 60 * 60 -> 0 | J40: ='Оценка'!B54 -> Backend | K40: =IF(A40<>"", TODAY() , "") -> 46121 | L40: =IF(A40<>"", TODAY() + (I40 /60/60) , "") -> 46121
A41: =#REF! -> #REF! | B41: =#REF! -> #REF! | C41: =IF(A41<>"", 0, "") -> #REF! | D41: =IF(A41<>"", 0, "") -> #REF! | E41: =IF(A41<>"", 1, "") -> #REF! | F41: =IF(A41<>"", 1, "") -> #REF! | G41: =IF(A41<>"", 'Sales (Итоги оценки)'!$C$4, "") -> #REF! | H41: =IF(A41<>"", 1, "") -> #REF! | I41: =IF(OR(ISBLANK('Оценка'!F51), ISBLANK('Оценка'!G51)), "", (AVERAGE( ( ('Оценка'!F51 + 4*AVERAGE('Оценка'!F51:G51) + 'Оценка'!G51)/6 - 2*(('Оценка'!G51 - 'Оценка'!F51)/6) )/5 , ( ('Оценка'!F51 + 4*AVERAGE('Оценка'!F51:G51) + 'Оценка'!G51)/6 + 2*(('Оценка'!G51 - 'Оценка'!F51)/6) )/5 ) * ( ( ('PM (Расчеты)'!$C$22/8 + 'PM (Расчеты)'!$C$23/40) + 'PM (Расчеты)'!$C$21/100 + 'PM (Расчеты)'!$C$25/100 + 'PM (Расчеты)'!$C$26/100 ) + 1 ))) * 8 * 60 * 60 -> 9216 | J41: =#REF! -> #REF! | K41: =IF(A41<>"", TODAY() , "") -> #REF! | L41: =IF(A41<>"", TODAY() + (I41 /60/60) , "") -> #REF!
A42: =#REF! -> #REF! | B42: =#REF! -> #REF! | C42: =IF(A42<>"", 0, "") -> #REF! | D42: =IF(A42<>"", 0, "") -> #REF! | E42: =IF(A42<>"", 1, "") -> #REF! | F42: =IF(A42<>"", 1, "") -> #REF! | G42: =IF(A42<>"", 'Sales (Итоги оценки)'!$C$4, "") -> #REF! | H42: =IF(A42<>"", 1, "") -> #REF! | I42: =IF(OR(ISBLANK('Оценка'!F52), ISBLANK('Оценка'!G52)), "", (AVERAGE( ( ('Оценка'!F52 + 4*AVERAGE('Оценка'!F52:G52) + 'Оценка'!G52)/6 - 2*(('Оценка'!G52 - 'Оценка'!F52)/6) )/5 , ( ('Оценка'!F52 + 4*AVERAGE('Оценка'!F52:G52) + 'Оценка'!G52)/6 + 2*(('Оценка'!G52 - 'Оценка'!F52)/6) )/5 ) * ( ( ('PM (Расчеты)'!$C$22/8 + 'PM (Расчеты)'!$C$23/40) + 'PM (Расчеты)'!$C$21/100 + 'PM (Расчеты)'!$C$25/100 + 'PM (Расчеты)'!$C$26/100 ) + 1 ))) * 8 * 60 * 60 -> 13824 | J42: =#REF! -> #REF! | K42: =IF(A42<>"", TODAY() , "") -> #REF! | L42: =IF(A42<>"", TODAY() + (I42 /60/60) , "") -> #REF!
A43: ='Оценка'!C55 -> Backend (Monolith): Referral Module | B43: ='Оценка'!D55 | C43: =IF(A43<>"", 0, "") -> 0 | D43: =IF(A43<>"", 0, "") -> 0 | E43: =IF(A43<>"", 1, "") -> 1 | F43: =IF(A43<>"", 1, "") -> 1 | G43: =IF(A43<>"", 'Sales (Итоги оценки)'!$C$4, "") -> P2P платформа | H43: =IF(A43<>"", 1, "") -> 1 | I43: =IF(OR(ISBLANK('Оценка'!F53), ISBLANK('Оценка'!G53)), "", (AVERAGE( ( ('Оценка'!F53 + 4*AVERAGE('Оценка'!F53:G53) + 'Оценка'!G53)/6 - 2*(('Оценка'!G53 - 'Оценка'!F53)/6) )/5 , ( ('Оценка'!F53 + 4*AVERAGE('Оценка'!F53:G53) + 'Оценка'!G53)/6 + 2*(('Оценка'!G53 - 'Оценка'!F53)/6) )/5 ) * ( ( ('PM (Расчеты)'!$C$22/8 + 'PM (Расчеты)'!$C$23/40) + 'PM (Расчеты)'!$C$21/100 + 'PM (Расчеты)'!$C$25/100 + 'PM (Расчеты)'!$C$26/100 ) + 1 ))) * 8 * 60 * 60 -> 0 | J43: ='Оценка'!B55 | K43: =IF(A43<>"", TODAY() , "") -> 46121 | L43: =IF(A43<>"", TODAY() + (I43 /60/60) , "") -> 46121
A44: ='Оценка'!C56 -> API генерации реферальной ссылки | B44: ='Оценка'!D56 -> Уникальный код, URL | C44: =IF(A44<>"", 0, "") -> 0 | D44: =IF(A44<>"", 0, "") -> 0 | E44: =IF(A44<>"", 1, "") -> 1 | F44: =IF(A44<>"", 1, "") -> 1 | G44: =IF(A44<>"", 'Sales (Итоги оценки)'!$C$4, "") -> P2P платформа | H44: =IF(A44<>"", 1, "") -> 1 | I44: =IF(OR(ISBLANK('Оценка'!F54), ISBLANK('Оценка'!G54)), "", (AVERAGE( ( ('Оценка'!F54 + 4*AVERAGE('Оценка'!F54:G54) + 'Оценка'!G54)/6 - 2*(('Оценка'!G54 - 'Оценка'!F54)/6) )/5 , ( ('Оценка'!F54 + 4*AVERAGE('Оценка'!F54:G54) + 'Оценка'!G54)/6 + 2*(('Оценка'!G54 - 'Оценка'!F54)/6) )/5 ) * ( ( ('PM (Расчеты)'!$C$22/8 + 'PM (Расчеты)'!$C$23/40) + 'PM (Расчеты)'!$C$21/100 + 'PM (Расчеты)'!$C$25/100 + 'PM (Расчеты)'!$C$26/100 ) + 1 ))) * 8 * 60 * 60 -> 6912 | J44: ='Оценка'!B56 -> Backend | K44: =IF(A44<>"", TODAY() , "") -> 46121 | L44: =IF(A44<>"", TODAY() + (I44 /60/60) , "") -> 46122.92
A45: ='Оценка'!C57 -> API установки кошелька комиссий | B45: ='Оценка'!D57 -> Валидация адреса | C45: =IF(A45<>"", 0, "") -> 0 | D45: =IF(A45<>"", 0, "") -> 0 | E45: =IF(A45<>"", 1, "") -> 1 | F45: =IF(A45<>"", 1, "") -> 1 | G45: =IF(A45<>"", 'Sales (Итоги оценки)'!$C$4, "") -> P2P платформа | H45: =IF(A45<>"", 1, "") -> 1 | I45: =IF(OR(ISBLANK(#REF!), ISBLANK(#REF!)), "", (AVERAGE( ( (#REF! + 4*AVERAGE(#REF!) + #REF!)/6 - 2*((#REF! - #REF!)/6) )/5 , ( (#REF! + 4*AVERAGE(#REF!) + #REF!)/6 + 2*((#REF! - #REF!)/6) )/5 ) * ( ( ('PM (Расчеты)'!$C$22/8 + 'PM (Расчеты)'!$C$23/40) + 'PM (Расчеты)'!$C$21/100 + 'PM (Расчеты)'!$C$25/100 + 'PM (Расчеты)'!$C$26/100 ) + 1 ))) * 8 * 60 * 60 -> #REF! | J45: ='Оценка'!B57 -> Backend | K45: =IF(A45<>"", TODAY() , "") -> 46121 | L45: =IF(A45<>"", TODAY() + (I45 /60/60) , "") -> #REF!
A46: ='Оценка'!C58 -> Привязка при регистрации | B46: ='Оценка'!D58 -> Парсинг ?ref=, сохранение referrer_id/wallet | C46: =IF(A46<>"", 0, "") -> 0 | D46: =IF(A46<>"", 0, "") -> 0 | E46: =IF(A46<>"", 1, "") -> 1 | F46: =IF(A46<>"", 1, "") -> 1 | G46: =IF(A46<>"", 'Sales (Итоги оценки)'!$C$4, "") -> P2P платформа | H46: =IF(A46<>"", 1, "") -> 1 | I46: =IF(OR(ISBLANK(#REF!), ISBLANK(#REF!)), "", (AVERAGE( ( (#REF! + 4*AVERAGE(#REF!) + #REF!)/6 - 2*((#REF! - #REF!)/6) )/5 , ( (#REF! + 4*AVERAGE(#REF!) + #REF!)/6 + 2*((#REF! - #REF!)/6) )/5 ) * ( ( ('PM (Расчеты)'!$C$22/8 + 'PM (Расчеты)'!$C$23/40) + 'PM (Расчеты)'!$C$21/100 + 'PM (Расчеты)'!$C$25/100 + 'PM (Расчеты)'!$C$26/100 ) + 1 ))) * 8 * 60 * 60 -> #REF! | J46: ='Оценка'!B58 -> Backend | K46: =IF(A46<>"", TODAY() , "") -> 46121 | L46: =IF(A46<>"", TODAY() + (I46 /60/60) , "") -> #REF!
A47: ='Оценка'!C59 -> Интеграция со сделками | B47: ='Оценка'!D59 -> Получение referrer_wallet при создании сделки, передача в контракт | C47: =IF(A47<>"", 0, "") -> 0 | D47: =IF(A47<>"", 0, "") -> 0 | E47: =IF(A47<>"", 1, "") -> 1 | F47: =IF(A47<>"", 1, "") -> 1 | G47: =IF(A47<>"", 'Sales (Итоги оценки)'!$C$4, "") -> P2P платформа | H47: =IF(A47<>"", 1, "") -> 1 | I47: =IF(OR(ISBLANK('Оценка'!F55), ISBLANK('Оценка'!G55)), "", (AVERAGE( ( ('Оценка'!F55 + 4*AVERAGE('Оценка'!F55:G55) + 'Оценка'!G55)/6 - 2*(('Оценка'!G55 - 'Оценка'!F55)/6) )/5 , ( ('Оценка'!F55 + 4*AVERAGE('Оценка'!F55:G55) + 'Оценка'!G55)/6 + 2*(('Оценка'!G55 - 'Оценка'!F55)/6) )/5 ) * ( ( ('PM (Расчеты)'!$C$22/8 + 'PM (Расчеты)'!$C$23/40) + 'PM (Расчеты)'!$C$21/100 + 'PM (Расчеты)'!$C$25/100 + 'PM (Расчеты)'!$C$26/100 ) + 1 ))) * 8 * 60 * 60 -> 0 | J47: ='Оценка'!B59 -> Backend | K47: =IF(A47<>"", TODAY() , "") -> 46121 | L47: =IF(A47<>"", TODAY() + (I47 /60/60) , "") -> 46121
A48: ='Оценка'!C60 -> Создание сущности ReferralReward | B48: ='Оценка'!D60 -> Хранение истории выплат | C48: =IF(A48<>"", 0, "") -> 0 | D48: =IF(A48<>"", 0, "") -> 0 | E48: =IF(A48<>"", 1, "") -> 1 | F48: =IF(A48<>"", 1, "") -> 1 | G48: =IF(A48<>"", 'Sales (Итоги оценки)'!$C$4, "") -> P2P платформа | H48: =IF(A48<>"", 1, "") -> 1 | I48: =IF(OR(ISBLANK('Оценка'!F56), ISBLANK('Оценка'!G56)), "", (AVERAGE( ( ('Оценка'!F56 + 4*AVERAGE('Оценка'!F56:G56) + 'Оценка'!G56)/6 - 2*(('Оценка'!G56 - 'Оценка'!F56)/6) )/5 , ( ('Оценка'!F56 + 4*AVERAGE('Оценка'!F56:G56) + 'Оценка'!G56)/6 + 2*(('Оценка'!G56 - 'Оценка'!F56)/6) )/5 ) * ( ( ('PM (Расчеты)'!$C$22/8 + 'PM (Расчеты)'!$C$23/40) + 'PM (Расчеты)'!$C$21/100 + 'PM (Расчеты)'!$C$25/100 + 'PM (Расчеты)'!$C$26/100 ) + 1 ))) * 8 * 60 * 60 -> 6912 | J48: ='Оценка'!B60 -> Backend | K48: =IF(A48<>"", TODAY() , "") -> 46121 | L48: =IF(A48<>"", TODAY() + (I48 /60/60) , "") -> 46122.92
A49: ='Оценка'!C61 -> API реферальной статистики | B49: ='Оценка'!D61 -> Кол-во рефералов, сделок, сумма выплат, список | C49: =IF(A49<>"", 0, "") -> 0 | D49: =IF(A49<>"", 0, "") -> 0 | E49: =IF(A49<>"", 1, "") -> 1 | F49: =IF(A49<>"", 1, "") -> 1 | G49: =IF(A49<>"", 'Sales (Итоги оценки)'!$C$4, "") -> P2P платформа | H49: =IF(A49<>"", 1, "") -> 1 | I49: =IF(OR(ISBLANK('Оценка'!F57), ISBLANK('Оценка'!G57)), "", (AVERAGE( ( ('Оценка'!F57 + 4*AVERAGE('Оценка'!F57:G57) + 'Оценка'!G57)/6 - 2*(('Оценка'!G57 - 'Оценка'!F57)/6) )/5 , ( ('Оценка'!F57 + 4*AVERAGE('Оценка'!F57:G57) + 'Оценка'!G57)/6 + 2*(('Оценка'!G57 - 'Оценка'!F57)/6) )/5 ) * ( ( ('PM (Расчеты)'!$C$22/8 + 'PM (Расчеты)'!$C$23/40) + 'PM (Расчеты)'!$C$21/100 + 'PM (Расчеты)'!$C$25/100 + 'PM (Расчеты)'!$C$26/100 ) + 1 ))) * 8 * 60 * 60 -> 6912 | J49: ='Оценка'!B61 -> Backend | K49: =IF(A49<>"", TODAY() , "") -> 46121 | L49: =IF(A49<>"", TODAY() + (I49 /60/60) , "") -> 46122.92
A50: ='Оценка'!C62 -> Обработка событий выплат | B50: ='Оценка'!D62 -> Обновление статистики при выплате из контракта | C50: =IF(A50<>"", 0, "") -> 0 | D50: =IF(A50<>"", 0, "") -> 0 | E50: =IF(A50<>"", 1, "") -> 1 | F50: =IF(A50<>"", 1, "") -> 1 | G50: =IF(A50<>"", 'Sales (Итоги оценки)'!$C$4, "") -> P2P платформа | H50: =IF(A50<>"", 1, "") -> 1 | I50: =IF(OR(ISBLANK('Оценка'!F58), ISBLANK('Оценка'!G58)), "", (AVERAGE( ( ('Оценка'!F58 + 4*AVERAGE('Оценка'!F58:G58) + 'Оценка'!G58)/6 - 2*(('Оценка'!G58 - 'Оценка'!F58)/6) )/5 , ( ('Оценка'!F58 + 4*AVERAGE('Оценка'!F58:G58) + 'Оценка'!G58)/6 + 2*(('Оценка'!G58 - 'Оценка'!F58)/6) )/5 ) * ( ( ('PM (Расчеты)'!$C$22/8 + 'PM (Расчеты)'!$C$23/40) + 'PM (Расчеты)'!$C$21/100 + 'PM (Расчеты)'!$C$25/100 + 'PM (Расчеты)'!$C$26/100 ) + 1 ))) * 8 * 60 * 60 -> 4608 | J50: ='Оценка'!B62 -> Backend | K50: =IF(A50<>"", TODAY() , "") -> 46121 | L50: =IF(A50<>"", TODAY() + (I50 /60/60) , "") -> 46122.28
A51: ='Оценка'!C63 | B51: ='Оценка'!D63 | C51: =IF(A51<>"", 0, "") | D51: =IF(A51<>"", 0, "") | E51: =IF(A51<>"", 1, "") | F51: =IF(A51<>"", 1, "") | G51: =IF(A51<>"", 'Sales (Итоги оценки)'!$C$4, "") | H51: =IF(A51<>"", 1, "") | I51: =IF(OR(ISBLANK('Оценка'!F59), ISBLANK('Оценка'!G59)), "", (AVERAGE( ( ('Оценка'!F59 + 4*AVERAGE('Оценка'!F59:G59) + 'Оценка'!G59)/6 - 2*(('Оценка'!G59 - 'Оценка'!F59)/6) )/5 , ( ('Оценка'!F59 + 4*AVERAGE('Оценка'!F59:G59) + 'Оценка'!G59)/6 + 2*(('Оценка'!G59 - 'Оценка'!F59)/6) )/5 ) * ( ( ('PM (Расчеты)'!$C$22/8 + 'PM (Расчеты)'!$C$23/40) + 'PM (Расчеты)'!$C$21/100 + 'PM (Расчеты)'!$C$25/100 + 'PM (Расчеты)'!$C$26/100 ) + 1 ))) * 8 * 60 * 60 -> 13824 | J51: ='Оценка'!B63 | K51: =IF(A51<>"", TODAY() , "") | L51: =IF(A51<>"", TODAY() + (I51 /60/60) , "")
A52: ='Оценка'!C64 | B52: ='Оценка'!D64 | C52: =IF(A52<>"", 0, "") | D52: =IF(A52<>"", 0, "") | E52: =IF(A52<>"", 1, "") | F52: =IF(A52<>"", 1, "") | G52: =IF(A52<>"", 'Sales (Итоги оценки)'!$C$4, "") | H52: =IF(A52<>"", 1, "") | I52: =IF(OR(ISBLANK('Оценка'!F60), ISBLANK('Оценка'!G60)), "", (AVERAGE( ( ('Оценка'!F60 + 4*AVERAGE('Оценка'!F60:G60) + 'Оценка'!G60)/6 - 2*(('Оценка'!G60 - 'Оценка'!F60)/6) )/5 , ( ('Оценка'!F60 + 4*AVERAGE('Оценка'!F60:G60) + 'Оценка'!G60)/6 + 2*(('Оценка'!G60 - 'Оценка'!F60)/6) )/5 ) * ( ( ('PM (Расчеты)'!$C$22/8 + 'PM (Расчеты)'!$C$23/40) + 'PM (Расчеты)'!$C$21/100 + 'PM (Расчеты)'!$C$25/100 + 'PM (Расчеты)'!$C$26/100 ) + 1 ))) * 8 * 60 * 60 -> 6912 | J52: ='Оценка'!B64 | K52: =IF(A52<>"", TODAY() , "") | L52: =IF(A52<>"", TODAY() + (I52 /60/60) , "")
A53: ='Оценка'!C65 -> Backend (Monolith): Миграции БД и документация | B53: ='Оценка'!D65 | C53: =IF(A53<>"", 0, "") -> 0 | D53: =IF(A53<>"", 0, "") -> 0 | E53: =IF(A53<>"", 1, "") -> 1 | F53: =IF(A53<>"", 1, "") -> 1 | G53: =IF(A53<>"", 'Sales (Итоги оценки)'!$C$4, "") -> P2P платформа | H53: =IF(A53<>"", 1, "") -> 1 | I53: =IF(OR(ISBLANK('Оценка'!F61), ISBLANK('Оценка'!G61)), "", (AVERAGE( ( ('Оценка'!F61 + 4*AVERAGE('Оценка'!F61:G61) + 'Оценка'!G61)/6 - 2*(('Оценка'!G61 - 'Оценка'!F61)/6) )/5 , ( ('Оценка'!F61 + 4*AVERAGE('Оценка'!F61:G61) + 'Оценка'!G61)/6 + 2*(('Оценка'!G61 - 'Оценка'!F61)/6) )/5 ) * ( ( ('PM (Расчеты)'!$C$22/8 + 'PM (Расчеты)'!$C$23/40) + 'PM (Расчеты)'!$C$21/100 + 'PM (Расчеты)'!$C$25/100 + 'PM (Расчеты)'!$C$26/100 ) + 1 ))) * 8 * 60 * 60 -> 13824 | J53: ='Оценка'!B65 | K53: =IF(A53<>"", TODAY() , "") -> 46121 | L53: =IF(A53<>"", TODAY() + (I53 /60/60) , "") -> 46124.84
A54: ='Оценка'!C66 -> Создание миграций | B54: ='Оценка'!D66 -> Все таблицы с учетом реферальной программы: users (с полями referrer_id, referrer_wallet, referral_code), wallets, orders, deals, disputes, rating, referral_rewards и др. | C54: =IF(A54<>"", 0, "") -> 0 | D54: =IF(A54<>"", 0, "") -> 0 | E54: =IF(A54<>"", 1, "") -> 1 | F54: =IF(A54<>"", 1, "") -> 1 | G54: =IF(A54<>"", 'Sales (Итоги оценки)'!$C$4, "") -> P2P платформа | H54: =IF(A54<>"", 1, "") -> 1 | I54: =IF(OR(ISBLANK('Оценка'!F62), ISBLANK('Оценка'!G62)), "", (AVERAGE( ( ('Оценка'!F62 + 4*AVERAGE('Оценка'!F62:G62) + 'Оценка'!G62)/6 - 2*(('Оценка'!G62 - 'Оценка'!F62)/6) )/5 , ( ('Оценка'!F62 + 4*AVERAGE('Оценка'!F62:G62) + 'Оценка'!G62)/6 + 2*(('Оценка'!G62 - 'Оценка'!F62)/6) )/5 ) * ( ( ('PM (Расчеты)'!$C$22/8 + 'PM (Расчеты)'!$C$23/40) + 'PM (Расчеты)'!$C$21/100 + 'PM (Расчеты)'!$C$25/100 + 'PM (Расчеты)'!$C$26/100 ) + 1 ))) * 8 * 60 * 60 -> 9216 | J54: ='Оценка'!B66 -> Backend | K54: =IF(A54<>"", TODAY() , "") -> 46121 | L54: =IF(A54<>"", TODAY() + (I54 /60/60) , "") -> 46123.56
A55: ='Оценка'!C67 -> Настройка Swagger/OpenAPI | B55: ='Оценка'!D67 -> Автогенерация документации для всех endpoints | C55: =IF(A55<>"", 0, "") -> 0 | D55: =IF(A55<>"", 0, "") -> 0 | E55: =IF(A55<>"", 1, "") -> 1 | F55: =IF(A55<>"", 1, "") -> 1 | G55: =IF(A55<>"", 'Sales (Итоги оценки)'!$C$4, "") -> P2P платформа | H55: =IF(A55<>"", 1, "") -> 1 | I55: =IF(OR(ISBLANK('Оценка'!F63), ISBLANK('Оценка'!G63)), "", (AVERAGE( ( ('Оценка'!F63 + 4*AVERAGE('Оценка'!F63:G63) + 'Оценка'!G63)/6 - 2*(('Оценка'!G63 - 'Оценка'!F63)/6) )/5 , ( ('Оценка'!F63 + 4*AVERAGE('Оценка'!F63:G63) + 'Оценка'!G63)/6 + 2*(('Оценка'!G63 - 'Оценка'!F63)/6) )/5 ) * ( ( ('PM (Расчеты)'!$C$22/8 + 'PM (Расчеты)'!$C$23/40) + 'PM (Расчеты)'!$C$21/100 + 'PM (Расчеты)'!$C$25/100 + 'PM (Расчеты)'!$C$26/100 ) + 1 ))) * 8 * 60 * 60 -> 0 | J55: ='Оценка'!B67 -> Backend | K55: =IF(A55<>"", TODAY() , "") -> 46121 | L55: =IF(A55<>"", TODAY() + (I55 /60/60) , "") -> 46121
A56: ='Оценка'!C68 | B56: ='Оценка'!D68 | C56: =IF(A56<>"", 0, "") | D56: =IF(A56<>"", 0, "") | E56: =IF(A56<>"", 1, "") | F56: =IF(A56<>"", 1, "") | G56: =IF(A56<>"", 'Sales (Итоги оценки)'!$C$4, "") | H56: =IF(A56<>"", 1, "") | I56: =IF(OR(ISBLANK('Оценка'!F64), ISBLANK('Оценка'!G64)), "", (AVERAGE( ( ('Оценка'!F64 + 4*AVERAGE('Оценка'!F64:G64) + 'Оценка'!G64)/6 - 2*(('Оценка'!G64 - 'Оценка'!F64)/6) )/5 , ( ('Оценка'!F64 + 4*AVERAGE('Оценка'!F64:G64) + 'Оценка'!G64)/6 + 2*(('Оценка'!G64 - 'Оценка'!F64)/6) )/5 ) * ( ( ('PM (Расчеты)'!$C$22/8 + 'PM (Расчеты)'!$C$23/40) + 'PM (Расчеты)'!$C$21/100 + 'PM (Расчеты)'!$C$25/100 + 'PM (Расчеты)'!$C$26/100 ) + 1 ))) * 8 * 60 * 60 -> 0 | J56: ='Оценка'!B68 | K56: =IF(A56<>"", TODAY() , "") | L56: =IF(A56<>"", TODAY() + (I56 /60/60) , "")
A57: ='Оценка'!C69 -> Интеграции | B57: ='Оценка'!D69 | C57: =IF(A57<>"", 0, "") -> 0 | D57: =IF(A57<>"", 0, "") -> 0 | E57: =IF(A57<>"", 1, "") -> 1 | F57: =IF(A57<>"", 1, "") -> 1 | G57: =IF(A57<>"", 'Sales (Итоги оценки)'!$C$4, "") -> P2P платформа | H57: =IF(A57<>"", 1, "") -> 1 | I57: =IF(OR(ISBLANK('Оценка'!F65), ISBLANK('Оценка'!G65)), "", (AVERAGE( ( ('Оценка'!F65 + 4*AVERAGE('Оценка'!F65:G65) + 'Оценка'!G65)/6 - 2*(('Оценка'!G65 - 'Оценка'!F65)/6) )/5 , ( ('Оценка'!F65 + 4*AVERAGE('Оценка'!F65:G65) + 'Оценка'!G65)/6 + 2*(('Оценка'!G65 - 'Оценка'!F65)/6) )/5 ) * ( ( ('PM (Расчеты)'!$C$22/8 + 'PM (Расчеты)'!$C$23/40) + 'PM (Расчеты)'!$C$21/100 + 'PM (Расчеты)'!$C$25/100 + 'PM (Расчеты)'!$C$26/100 ) + 1 ))) * 8 * 60 * 60 -> 0 | J57: ='Оценка'!B69 | K57: =IF(A57<>"", TODAY() , "") -> 46121 | L57: =IF(A57<>"", TODAY() + (I57 /60/60) , "") -> 46121
A58: ='Оценка'!C70 -> KYC Интеграция | B58: ='Оценка'!D70 -> Регистрация в провайдере (SumSub/Onfido), вебхуки, SDK на frontend, обработка статусов | C58: =IF(A58<>"", 0, "") -> 0 | D58: =IF(A58<>"", 0, "") -> 0 | E58: =IF(A58<>"", 1, "") -> 1 | F58: =IF(A58<>"", 1, "") -> 1 | G58: =IF(A58<>"", 'Sales (Итоги оценки)'!$C$4, "") -> P2P платформа | H58: =IF(A58<>"", 1, "") -> 1 | I58: =IF(OR(ISBLANK('Оценка'!F66), ISBLANK('Оценка'!G66)), "", (AVERAGE( ( ('Оценка'!F66 + 4*AVERAGE('Оценка'!F66:G66) + 'Оценка'!G66)/6 - 2*(('Оценка'!G66 - 'Оценка'!F66)/6) )/5 , ( ('Оценка'!F66 + 4*AVERAGE('Оценка'!F66:G66) + 'Оценка'!G66)/6 + 2*(('Оценка'!G66 - 'Оценка'!F66)/6) )/5 ) * ( ( ('PM (Расчеты)'!$C$22/8 + 'PM (Расчеты)'!$C$23/40) + 'PM (Расчеты)'!$C$21/100 + 'PM (Расчеты)'!$C$25/100 + 'PM (Расчеты)'!$C$26/100 ) + 1 ))) * 8 * 60 * 60 -> 23040 | J58: ='Оценка'!B70 -> Backend | K58: =IF(A58<>"", TODAY() , "") -> 46121 | L58: =IF(A58<>"", TODAY() + (I58 /60/60) , "") -> 46127.4
... A84: ='Оценка'!C96 -> Frontend: Интеграция с API | B84: ='Оценка'!D96 | C84: =IF(A84<>"", 0, "") -> 0 | D84: =IF(A84<>"", 0, "") -> 0 | E84: =IF(A84<>"", 1, "") -> 1 | F84: =IF(A84<>"", 1, "") -> 1 | G84: =IF(A84<>"", 'Sales (Итоги оценки)'!$C$4, "") -> P2P платформа | H84: =IF(A84<>"", 1, "") -> 1 | I84: =IF(OR(ISBLANK('Оценка'!F92), ISBLANK('Оценка'!G92)), "", (AVERAGE( ( ('Оценка'!F92 + 4*AVERAGE('Оценка'!F92:G92) + 'Оценка'!G92)/6 - 2*(('Оценка'!G92 - 'Оценка'!F92)/6) )/5 , ( ('Оценка'!F92 + 4*AVERAGE('Оценка'!F92:G92) + 'Оценка'!G92)/6 + 2*(('Оценка'!G92 - 'Оценка'!F92)/6) )/5 ) * ( ( ('PM (Расчеты)'!$C$22/8 + 'PM (Расчеты)'!$C$23/40) + 'PM (Расчеты)'!$C$21/100 + 'PM (Расчеты)'!$C$25/100 + 'PM (Расчеты)'!$C$26/100 ) + 1 ))) * 8 * 60 * 60 -> 0 | J84: ='Оценка'!B96 | K84: =IF(A84<>"", TODAY() , "") -> 46121 | L84: =IF(A84<>"", TODAY() + (I84 /60/60) , "") -> 46121
A85: =#REF! -> #REF! | B85: =#REF! -> #REF! | C85: =IF(A85<>"", 0, "") -> #REF! | D85: =IF(A85<>"", 0, "") -> #REF! | E85: =IF(A85<>"", 1, "") -> #REF! | F85: =IF(A85<>"", 1, "") -> #REF! | G85: =IF(A85<>"", 'Sales (Итоги оценки)'!$C$4, "") -> #REF! | H85: =IF(A85<>"", 1, "") -> #REF! | I85: =IF(OR(ISBLANK('Оценка'!F93), ISBLANK('Оценка'!G93)), "", (AVERAGE( ( ('Оценка'!F93 + 4*AVERAGE('Оценка'!F93:G93) + 'Оценка'!G93)/6 - 2*(('Оценка'!G93 - 'Оценка'!F93)/6) )/5 , ( ('Оценка'!F93 + 4*AVERAGE('Оценка'!F93:G93) + 'Оценка'!G93)/6 + 2*(('Оценка'!G93 - 'Оценка'!F93)/6) )/5 ) * ( ( ('PM (Расчеты)'!$C$22/8 + 'PM (Расчеты)'!$C$23/40) + 'PM (Расчеты)'!$C$21/100 + 'PM (Расчеты)'!$C$25/100 + 'PM (Расчеты)'!$C$26/100 ) + 1 ))) * 8 * 60 * 60 -> 0 | J85: =#REF! -> #REF! | K85: =IF(A85<>"", TODAY() , "") -> #REF! | L85: =IF(A85<>"", TODAY() + (I85 /60/60) , "") -> #REF!
A86: =#REF! -> #REF! | B86: =#REF! -> #REF! | C86: =IF(A86<>"", 0, "") -> #REF! | D86: =IF(A86<>"", 0, "") -> #REF! | E86: =IF(A86<>"", 1, "") -> #REF! | F86: =IF(A86<>"", 1, "") -> #REF! | G86: =IF(A86<>"", 'Sales (Итоги оценки)'!$C$4, "") -> #REF! | H86: =IF(A86<>"", 1, "") -> #REF! | I86: =IF(OR(ISBLANK('Оценка'!F94), ISBLANK('Оценка'!G94)), "", (AVERAGE( ( ('Оценка'!F94 + 4*AVERAGE('Оценка'!F94:G94) + 'Оценка'!G94)/6 - 2*(('Оценка'!G94 - 'Оценка'!F94)/6) )/5 , ( ('Оценка'!F94 + 4*AVERAGE('Оценка'!F94:G94) + 'Оценка'!G94)/6 + 2*(('Оценка'!G94 - 'Оценка'!F94)/6) )/5 ) * ( ( ('PM (Расчеты)'!$C$22/8 + 'PM (Расчеты)'!$C$23/40) + 'PM (Расчеты)'!$C$21/100 + 'PM (Расчеты)'!$C$25/100 + 'PM (Расчеты)'!$C$26/100 ) + 1 ))) * 8 * 60 * 60 -> 0 | J86: =#REF! -> #REF! | K86: =IF(A86<>"", TODAY() , "") -> #REF! | L86: =IF(A86<>"", TODAY() + (I86 /60/60) , "") -> #REF!
A87: =#REF! -> #REF! | B87: =#REF! -> #REF! | C87: =IF(A87<>"", 0, "") -> #REF! | D87: =IF(A87<>"", 0, "") -> #REF! | E87: =IF(A87<>"", 1, "") -> #REF! | F87: =IF(A87<>"", 1, "") -> #REF! | G87: =IF(A87<>"", 'Sales (Итоги оценки)'!$C$4, "") -> #REF! | H87: =IF(A87<>"", 1, "") -> #REF! | I87: =IF(OR(ISBLANK('Оценка'!F95), ISBLANK('Оценка'!G95)), "", (AVERAGE( ( ('Оценка'!F95 + 4*AVERAGE('Оценка'!F95:G95) + 'Оценка'!G95)/6 - 2*(('Оценка'!G95 - 'Оценка'!F95)/6) )/5 , ( ('Оценка'!F95 + 4*AVERAGE('Оценка'!F95:G95) + 'Оценка'!G95)/6 + 2*(('Оценка'!G95 - 'Оценка'!F95)/6) )/5 ) * ( ( ('PM (Расчеты)'!$C$22/8 + 'PM (Расчеты)'!$C$23/40) + 'PM (Расчеты)'!$C$21/100 + 'PM (Расчеты)'!$C$25/100 + 'PM (Расчеты)'!$C$26/100 ) + 1 ))) * 8 * 60 * 60 -> 0 | J87: =#REF! -> #REF! | K87: =IF(A87<>"", TODAY() , "") -> #REF! | L87: =IF(A87<>"", TODAY() + (I87 /60/60) , "") -> #REF!
A88: =#REF! -> #REF! | B88: =#REF! -> #REF! | C88: =IF(A88<>"", 0, "") -> #REF! | D88: =IF(A88<>"", 0, "") -> #REF! | E88: =IF(A88<>"", 1, "") -> #REF! | F88: =IF(A88<>"", 1, "") -> #REF! | G88: =IF(A88<>"", 'Sales (Итоги оценки)'!$C$4, "") -> #REF! | H88: =IF(A88<>"", 1, "") -> #REF! | I88: =IF(OR(ISBLANK('Оценка'!F96), ISBLANK('Оценка'!G96)), "", (AVERAGE( ( ('Оценка'!F96 + 4*AVERAGE('Оценка'!F96:G96) + 'Оценка'!G96)/6 - 2*(('Оценка'!G96 - 'Оценка'!F96)/6) )/5 , ( ('Оценка'!F96 + 4*AVERAGE('Оценка'!F96:G96) + 'Оценка'!G96)/6 + 2*(('Оценка'!G96 - 'Оценка'!F96)/6) )/5 ) * ( ( ('PM (Расчеты)'!$C$22/8 + 'PM (Расчеты)'!$C$23/40) + 'PM (Расчеты)'!$C$21/100 + 'PM (Расчеты)'!$C$25/100 + 'PM (Расчеты)'!$C$26/100 ) + 1 ))) * 8 * 60 * 60 -> 0 | J88: =#REF! -> #REF! | K88: =IF(A88<>"", TODAY() , "") -> #REF! | L88: =IF(A88<>"", TODAY() + (I88 /60/60) , "") -> #REF!
A89: =#REF! -> #REF! | B89: =#REF! -> #REF! | C89: =IF(A89<>"", 0, "") -> #REF! | D89: =IF(A89<>"", 0, "") -> #REF! | E89: =IF(A89<>"", 1, "") -> #REF! | F89: =IF(A89<>"", 1, "") -> #REF! | G89: =IF(A89<>"", 'Sales (Итоги оценки)'!$C$4, "") -> #REF! | H89: =IF(A89<>"", 1, "") -> #REF! | I89: =IF(OR(ISBLANK(#REF!), ISBLANK(#REF!)), "", (AVERAGE( ( (#REF! + 4*AVERAGE(#REF!) + #REF!)/6 - 2*((#REF! - #REF!)/6) )/5 , ( (#REF! + 4*AVERAGE(#REF!) + #REF!)/6 + 2*((#REF! - #REF!)/6) )/5 ) * ( ( ('PM (Расчеты)'!$C$22/8 + 'PM (Расчеты)'!$C$23/40) + 'PM (Расчеты)'!$C$21/100 + 'PM (Расчеты)'!$C$25/100 + 'PM (Расчеты)'!$C$26/100 ) + 1 ))) * 8 * 60 * 60 -> #REF! | J89: =#REF! -> #REF! | K89: =IF(A89<>"", TODAY() , "") -> #REF! | L89: =IF(A89<>"", TODAY() + (I89 /60/60) , "") -> #REF!
A90: =#REF! -> #REF! | B90: =#REF! -> #REF! | C90: =IF(A90<>"", 0, "") -> #REF! | D90: =IF(A90<>"", 0, "") -> #REF! | E90: =IF(A90<>"", 1, "") -> #REF! | F90: =IF(A90<>"", 1, "") -> #REF! | G90: =IF(A90<>"", 'Sales (Итоги оценки)'!$C$4, "") -> #REF! | H90: =IF(A90<>"", 1, "") -> #REF! | I90: =IF(OR(ISBLANK(#REF!), ISBLANK(#REF!)), "", (AVERAGE( ( (#REF! + 4*AVERAGE(#REF!) + #REF!)/6 - 2*((#REF! - #REF!)/6) )/5 , ( (#REF! + 4*AVERAGE(#REF!) + #REF!)/6 + 2*((#REF! - #REF!)/6) )/5 ) * ( ( ('PM (Расчеты)'!$C$22/8 + 'PM (Расчеты)'!$C$23/40) + 'PM (Расчеты)'!$C$21/100 + 'PM (Расчеты)'!$C$25/100 + 'PM (Расчеты)'!$C$26/100 ) + 1 ))) * 8 * 60 * 60 -> #REF! | J90: =#REF! -> #REF! | K90: =IF(A90<>"", TODAY() , "") -> #REF! | L90: =IF(A90<>"", TODAY() + (I90 /60/60) , "") -> #REF!
A91: =#REF! -> #REF! | B91: =#REF! -> #REF! | C91: =IF(A91<>"", 0, "") -> #REF! | D91: =IF(A91<>"", 0, "") -> #REF! | E91: =IF(A91<>"", 1, "") -> #REF! | F91: =IF(A91<>"", 1, "") -> #REF! | G91: =IF(A91<>"", 'Sales (Итоги оценки)'!$C$4, "") -> #REF! | H91: =IF(A91<>"", 1, "") -> #REF! | I91: =IF(OR(ISBLANK(#REF!), ISBLANK(#REF!)), "", (AVERAGE( ( (#REF! + 4*AVERAGE(#REF!) + #REF!)/6 - 2*((#REF! - #REF!)/6) )/5 , ( (#REF! + 4*AVERAGE(#REF!) + #REF!)/6 + 2*((#REF! - #REF!)/6) )/5 ) * ( ( ('PM (Расчеты)'!$C$22/8 + 'PM (Расчеты)'!$C$23/40) + 'PM (Расчеты)'!$C$21/100 + 'PM (Расчеты)'!$C$25/100 + 'PM (Расчеты)'!$C$26/100 ) + 1 ))) * 8 * 60 * 60 -> #REF! | J91: =#REF! -> #REF! | K91: =IF(A91<>"", TODAY() , "") -> #REF! | L91: =IF(A91<>"", TODAY() + (I91 /60/60) , "") -> #REF!
A92: ='Оценка'!C97 -> Интеграция WebSocket | B92: ='Оценка'!D97 -> Стакан, уведомления, обработка ошибок | C92: =IF(A92<>"", 0, "") -> 0 | D92: =IF(A92<>"", 0, "") -> 0 | E92: =IF(A92<>"", 1, "") -> 1 | F92: =IF(A92<>"", 1, "") -> 1 | G92: =IF(A92<>"", 'Sales (Итоги оценки)'!$C$4, "") -> P2P платформа | H92: =IF(A92<>"", 1, "") -> 1 | I92: =IF(OR(ISBLANK(#REF!), ISBLANK(#REF!)), "", (AVERAGE( ( (#REF! + 4*AVERAGE(#REF!) + #REF!)/6 - 2*((#REF! - #REF!)/6) )/5 , ( (#REF! + 4*AVERAGE(#REF!) + #REF!)/6 + 2*((#REF! - #REF!)/6) )/5 ) * ( ( ('PM (Расчеты)'!$C$22/8 + 'PM (Расчеты)'!$C$23/40) + 'PM (Расчеты)'!$C$21/100 + 'PM (Расчеты)'!$C$25/100 + 'PM (Расчеты)'!$C$26/100 ) + 1 ))) * 8 * 60 * 60 -> #REF! | J92: ='Оценка'!B97 -> Frontend | K92: =IF(A92<>"", TODAY() , "") -> 46121 | L92: =IF(A92<>"", TODAY() + (I92 /60/60) , "") -> #REF!
A93: ='Оценка'!C98 | B93: ='Оценка'!D98 | C93: =IF(A93<>"", 0, "") | D93: =IF(A93<>"", 0, "") | E93: =IF(A93<>"", 1, "") | F93: =IF(A93<>"", 1, "") | G93: =IF(A93<>"", 'Sales (Итоги оценки)'!$C$4, "") | H93: =IF(A93<>"", 1, "") | I93: =IF(OR(ISBLANK(#REF!), ISBLANK(#REF!)), "", (AVERAGE( ( (#REF! + 4*AVERAGE(#REF!) + #REF!)/6 - 2*((#REF! - #REF!)/6) )/5 , ( (#REF! + 4*AVERAGE(#REF!) + #REF!)/6 + 2*((#REF! - #REF!)/6) )/5 ) * ( ( ('PM (Расчеты)'!$C$22/8 + 'PM (Расчеты)'!$C$23/40) + 'PM (Расчеты)'!$C$21/100 + 'PM (Расчеты)'!$C$25/100 + 'PM (Расчеты)'!$C$26/100 ) + 1 ))) * 8 * 60 * 60 -> #REF! | J93: ='Оценка'!B98 | K93: =IF(A93<>"", TODAY() , "") | L93: =IF(A93<>"", TODAY() + (I93 /60/60) , "")
A94: ='Оценка'!C99 -> Интеграции | B94: ='Оценка'!D99 | C94: =IF(A94<>"", 0, "") -> 0 | D94: =IF(A94<>"", 0, "") -> 0 | E94: =IF(A94<>"", 1, "") -> 1 | F94: =IF(A94<>"", 1, "") -> 1 | G94: =IF(A94<>"", 'Sales (Итоги оценки)'!$C$4, "") -> P2P платформа | H94: =IF(A94<>"", 1, "") -> 1 | I94: =IF(OR(ISBLANK(#REF!), ISBLANK(#REF!)), "", (AVERAGE( ( (#REF! + 4*AVERAGE(#REF!) + #REF!)/6 - 2*((#REF! - #REF!)/6) )/5 , ( (#REF! + 4*AVERAGE(#REF!) + #REF!)/6 + 2*((#REF! - #REF!)/6) )/5 ) * ( ( ('PM (Расчеты)'!$C$22/8 + 'PM (Расчеты)'!$C$23/40) + 'PM (Расчеты)'!$C$21/100 + 'PM (Расчеты)'!$C$25/100 + 'PM (Расчеты)'!$C$26/100 ) + 1 ))) * 8 * 60 * 60 -> #REF! | J94: ='Оценка'!B99 | K94: =IF(A94<>"", TODAY() , "") -> 46121 | L94: =IF(A94<>"", TODAY() + (I94 /60/60) , "") -> #REF!
A95: ='Оценка'!C100 -> KYC Интеграция | B95: ='Оценка'!D100 -> Изучение документации КУС | C95: =IF(A95<>"", 0, "") -> 0 | D95: =IF(A95<>"", 0, "") -> 0 | E95: =IF(A95<>"", 1, "") -> 1 | F95: =IF(A95<>"", 1, "") -> 1 | G95: =IF(A95<>"", 'Sales (Итоги оценки)'!$C$4, "") -> P2P платформа | H95: =IF(A95<>"", 1, "") -> 1 | I95: =IF(OR(ISBLANK(#REF!), ISBLANK(#REF!)), "", (AVERAGE( ( (#REF! + 4*AVERAGE(#REF!) + #REF!)/6 - 2*((#REF! - #REF!)/6) )/5 , ( (#REF! + 4*AVERAGE(#REF!) + #REF!)/6 + 2*((#REF! - #REF!)/6) )/5 ) * ( ( ('PM (Расчеты)'!$C$22/8 + 'PM (Расчеты)'!$C$23/40) + 'PM (Расчеты)'!$C$21/100 + 'PM (Расчеты)'!$C$25/100 + 'PM (Расчеты)'!$C$26/100 ) + 1 ))) * 8 * 60 * 60 -> #REF! | J95: ='Оценка'!B100 -> Frontend | K95: =IF(A95<>"", TODAY() , "") -> 46121 | L95: =IF(A95<>"", TODAY() + (I95 /60/60) , "") -> #REF!
A96: ='Оценка'!C101 -> Чат Интеграция | B96: ='Оценка'!D101 -> Изучение документации чата | C96: =IF(A96<>"", 0, "") -> 0 | D96: =IF(A96<>"", 0, "") -> 0 | E96: =IF(A96<>"", 1, "") -> 1 | F96: =IF(A96<>"", 1, "") -> 1 | G96: =IF(A96<>"", 'Sales (Итоги оценки)'!$C$4, "") -> P2P платформа | H96: =IF(A96<>"", 1, "") -> 1 | I96: =IF(OR(ISBLANK('Оценка'!F97), ISBLANK('Оценка'!G97)), "", (AVERAGE( ( ('Оценка'!F97 + 4*AVERAGE('Оценка'!F97:G97) + 'Оценка'!G97)/6 - 2*(('Оценка'!G97 - 'Оценка'!F97)/6) )/5 , ( ('Оценка'!F97 + 4*AVERAGE('Оценка'!F97:G97) + 'Оценка'!G97)/6 + 2*(('Оценка'!G97 - 'Оценка'!F97)/6) )/5 ) * ( ( ('PM (Расчеты)'!$C$22/8 + 'PM (Расчеты)'!$C$23/40) + 'PM (Расчеты)'!$C$21/100 + 'PM (Расчеты)'!$C$25/100 + 'PM (Расчеты)'!$C$26/100 ) + 1 ))) * 8 * 60 * 60 -> 13824 | J96: ='Оценка'!B101 -> Frontend | K96: =IF(A96<>"", TODAY() , "") -> 46121 | L96: =IF(A96<>"", TODAY() + (I96 /60/60) , "") -> 46124.84
A97: ='Оценка'!C102 | B97: ='Оценка'!D102 -> Адаптив | C97: =IF(A97<>"", 0, "") | D97: =IF(A97<>"", 0, "") | E97: =IF(A97<>"", 1, "") | F97: =IF(A97<>"", 1, "") | G97: =IF(A97<>"", 'Sales (Итоги оценки)'!$C$4, "") | H97: =IF(A97<>"", 1, "") | I97: =IF(OR(ISBLANK('Оценка'!F98), ISBLANK('Оценка'!G98)), "", (AVERAGE( ( ('Оценка'!F98 + 4*AVERAGE('Оценка'!F98:G98) + 'Оценка'!G98)/6 - 2*(('Оценка'!G98 - 'Оценка'!F98)/6) )/5 , ( ('Оценка'!F98 + 4*AVERAGE('Оценка'!F98:G98) + 'Оценка'!G98)/6 + 2*(('Оценка'!G98 - 'Оценка'!F98)/6) )/5 ) * ( ( ('PM (Расчеты)'!$C$22/8 + 'PM (Расчеты)'!$C$23/40) + 'PM (Расчеты)'!$C$21/100 + 'PM (Расчеты)'!$C$25/100 + 'PM (Расчеты)'!$C$26/100 ) + 1 ))) * 8 * 60 * 60 -> 0 | J97: ='Оценка'!B102 | K97: =IF(A97<>"", TODAY() , "") | L97: =IF(A97<>"", TODAY() + (I97 /60/60) , "")
A98: ='Оценка'!C103 -> Доработка интерфейсов под мобильные устройства | B98: ='Оценка'!D103 | C98: =IF(A98<>"", 0, "") -> 0 | D98: =IF(A98<>"", 0, "") -> 0 | E98: =IF(A98<>"", 1, "") -> 1 | F98: =IF(A98<>"", 1, "") -> 1 | G98: =IF(A98<>"", 'Sales (Итоги оценки)'!$C$4, "") -> P2P платформа | H98: =IF(A98<>"", 1, "") -> 1 | I98: =IF(OR(ISBLANK('Оценка'!F99), ISBLANK('Оценка'!G99)), "", (AVERAGE( ( ('Оценка'!F99 + 4*AVERAGE('Оценка'!F99:G99) + 'Оценка'!G99)/6 - 2*(('Оценка'!G99 - 'Оценка'!F99)/6) )/5 , ( ('Оценка'!F99 + 4*AVERAGE('Оценка'!F99:G99) + 'Оценка'!G99)/6 + 2*(('Оценка'!G99 - 'Оценка'!F99)/6) )/5 ) * ( ( ('PM (Расчеты)'!$C$22/8 + 'PM (Расчеты)'!$C$23/40) + 'PM (Расчеты)'!$C$21/100 + 'PM (Расчеты)'!$C$25/100 + 'PM (Расчеты)'!$C$26/100 ) + 1 ))) * 8 * 60 * 60 -> 0 | J98: ='Оценка'!B103 -> Frontend | K98: =IF(A98<>"", TODAY() , "") -> 46121 | L98: =IF(A98<>"", TODAY() + (I98 /60/60) , "") -> 46121
A99: ='Оценка'!C104 -> Unit-тестирование Backend | B99: ='Оценка'!D104 -> Jest, покрытие сервисов (User, Trading, Payment, Dispute, Rewards) > 70% | C99: =IF(A99<>"", 0, "") -> 0 | D99: =IF(A99<>"", 0, "") -> 0 | E99: =IF(A99<>"", 1, "") -> 1 | F99: =IF(A99<>"", 1, "") -> 1 | G99: =IF(A99<>"", 'Sales (Итоги оценки)'!$C$4, "") -> P2P платформа | H99: =IF(A99<>"", 1, "") -> 1 | I99: =IF(OR(ISBLANK('Оценка'!F100), ISBLANK('Оценка'!G100)), "", (AVERAGE( ( ('Оценка'!F100 + 4*AVERAGE('Оценка'!F100:G100) + 'Оценка'!G100)/6 - 2*(('Оценка'!G100 - 'Оценка'!F100)/6) )/5 , ( ('Оценка'!F100 + 4*AVERAGE('Оценка'!F100:G100) + 'Оценка'!G100)/6 + 2*(('Оценка'!G100 - 'Оценка'!F100)/6) )/5 ) * ( ( ('PM (Расчеты)'!$C$22/8 + 'PM (Расчеты)'!$C$23/40) + 'PM (Расчеты)'!$C$21/100 + 'PM (Расчеты)'!$C$25/100 + 'PM (Расчеты)'!$C$26/100 ) + 1 ))) * 8 * 60 * 60 -> 9216 | J99: ='Оценка'!B104 -> Backend | K99: =IF(A99<>"", TODAY() , "") -> 46121 | L99: =IF(A99<>"", TODAY() + (I99 /60/60) , "") -> 46123.56
A100: =#REF! -> #REF! | B100: =#REF! -> #REF! | C100: =IF(A100<>"", 0, "") -> #REF! | D100: =IF(A100<>"", 0, "") -> #REF! | E100: =IF(A100<>"", 1, "") -> #REF! | F100: =IF(A100<>"", 1, "") -> #REF! | G100: =IF(A100<>"", 'Sales (Итоги оценки)'!$C$4, "") -> #REF! | H100: =IF(A100<>"", 1, "") -> #REF! | I100: =IF(OR(ISBLANK('Оценка'!F101), ISBLANK('Оценка'!G101)), "", (AVERAGE( ( ('Оценка'!F101 + 4*AVERAGE('Оценка'!F101:G101) + 'Оценка'!G101)/6 - 2*(('Оценка'!G101 - 'Оценка'!F101)/6) )/5 , ( ('Оценка'!F101 + 4*AVERAGE('Оценка'!F101:G101) + 'Оценка'!G101)/6 + 2*(('Оценка'!G101 - 'Оценка'!F101)/6) )/5 ) * ( ( ('PM (Расчеты)'!$C$22/8 + 'PM (Расчеты)'!$C$23/40) + 'PM (Расчеты)'!$C$21/100 + 'PM (Расчеты)'!$C$25/100 + 'PM (Расчеты)'!$C$26/100 ) + 1 ))) * 8 * 60 * 60 -> 9216 | J100: =#REF! -> #REF! | K100: =IF(A100<>"", TODAY() , "") -> #REF! | L100: =IF(A100<>"", TODAY() + (I100 /60/60) , "") -> #REF!
A101: ='Оценка'!C105 -> Интеграционное тестирование | B101: ='Оценка'!D105 -> E2E: регистрация, создание ордера, сделка happy path, отмена, диспут, Pit на testnet | C101: =IF(A101<>"", 0, "") -> 0 | D101: =IF(A101<>"", 0, "") -> 0 | E101: =IF(A101<>"", 1, "") -> 1 | F101: =IF(A101<>"", 1, "") -> 1 | G101: =IF(A101<>"", 'Sales (Итоги оценки)'!$C$4, "") -> P2P платформа | H101: =IF(A101<>"", 1, "") -> 1 | I101: =IF(OR(ISBLANK('Оценка'!F102), ISBLANK('Оценка'!G102)), "", (AVERAGE( ( ('Оценка'!F102 + 4*AVERAGE('Оценка'!F102:G102) + 'Оценка'!G102)/6 - 2*(('Оценка'!G102 - 'Оценка'!F102)/6) )/5 , ( ('Оценка'!F102 + 4*AVERAGE('Оценка'!F102:G102) + 'Оценка'!G102)/6 + 2*(('Оценка'!G102 - 'Оценка'!F102)/6) )/5 ) * ( ( ('PM (Расчеты)'!$C$22/8 + 'PM (Расчеты)'!$C$23/40) + 'PM (Расчеты)'!$C$21/100 + 'PM (Расчеты)'!$C$25/100 + 'PM (Расчеты)'!$C$26/100 ) + 1 ))) * 8 * 60 * 60 -> 0 | J101: ='Оценка'!B105 -> QA | K101: =IF(A101<>"", TODAY() , "") -> 46121 | L101: =IF(A101<>"", TODAY() + (I101 /60/60) , "") -> 46121
A102: =#REF! -> #REF! | B102: =#REF! -> #REF! | C102: =IF(A102<>"", 0, "") -> #REF! | D102: =IF(A102<>"", 0, "") -> #REF! | E102: =IF(A102<>"", 1, "") -> #REF! | F102: =IF(A102<>"", 1, "") -> #REF! | G102: =IF(A102<>"", 'Sales (Итоги оценки)'!$C$4, "") -> #REF! | H102: =IF(A102<>"", 1, "") -> #REF! | I102: =IF(OR(ISBLANK('Оценка'!F103), ISBLANK('Оценка'!G103)), "", (AVERAGE( ( ('Оценка'!F103 + 4*AVERAGE('Оценка'!F103:G103) + 'Оценка'!G103)/6 - 2*(('Оценка'!G103 - 'Оценка'!F103)/6) )/5 , ( ('Оценка'!F103 + 4*AVERAGE('Оценка'!F103:G103) + 'Оценка'!G103)/6 + 2*(('Оценка'!G103 - 'Оценка'!F103)/6) )/5 ) * ( ( ('PM (Расчеты)'!$C$22/8 + 'PM (Расчеты)'!$C$23/40) + 'PM (Расчеты)'!$C$21/100 + 'PM (Расчеты)'!$C$25/100 + 'PM (Расчеты)'!$C$26/100 ) + 1 ))) * 8 * 60 * 60 -> 32256 | J102: =#REF! -> #REF! | K102: =IF(A102<>"", TODAY() , "") -> #REF! | L102: =IF(A102<>"", TODAY() + (I102 /60/60) , "") -> #REF!
A103: ='Оценка'!C106 -> Тестирование безопасности | B103: ='Оценка'!D106 -> Авторизация, валидация, rate limiting, CORS, шифрование, пентест (опционально) | C103: =IF(A103<>"", 0, "") -> 0 | D103: =IF(A103<>"", 0, "") -> 0 | E103: =IF(A103<>"", 1, "") -> 1 | F103: =IF(A103<>"", 1, "") -> 1 | G103: =IF(A103<>"", 'Sales (Итоги оценки)'!$C$4, "") -> P2P платформа | H103: =IF(A103<>"", 1, "") -> 1 | I103: =IF(OR(ISBLANK('Оценка'!F104), ISBLANK('Оценка'!G104)), "", (AVERAGE( ( ('Оценка'!F104 + 4*AVERAGE('Оценка'!F104:G104) + 'Оценка'!G104)/6 - 2*(('Оценка'!G104 - 'Оценка'!F104)/6) )/5 , ( ('Оценка'!F104 + 4*AVERAGE('Оценка'!F104:G104) + 'Оценка'!G104)/6 + 2*(('Оценка'!G104 - 'Оценка'!F104)/6) )/5 ) * ( ( ('PM (Расчеты)'!$C$22/8 + 'PM (Расчеты)'!$C$23/40) + 'PM (Расчеты)'!$C$21/100 + 'PM (Расчеты)'!$C$25/100 + 'PM (Расчеты)'!$C$26/100 ) + 1 ))) * 8 * 60 * 60 -> 23040 | J103: ='Оценка'!B106 -> QA | K103: =IF(A103<>"", TODAY() , "") -> 46121 | L103: =IF(A103<>"", TODAY() + (I103 /60/60) , "") -> 46127.4
A104: ='Оценка'!C107 -> Багфикс и регрессия | B104: ='Оценка'!D107 -> Сбор, приоритизация, исправление P0/P1 | C104: =IF(A104<>"", 0, "") -> 0 | D104: =IF(A104<>"", 0, "") -> 0 | E104: =IF(A104<>"", 1, "") -> 1 | F104: =IF(A104<>"", 1, "") -> 1 | G104: =IF(A104<>"", 'Sales (Итоги оценки)'!$C$4, "") -> P2P платформа | H104: =IF(A104<>"", 1, "") -> 1 | I104: =IF(OR(ISBLANK(#REF!), ISBLANK(#REF!)), "", (AVERAGE( ( (#REF! + 4*AVERAGE(#REF!) + #REF!)/6 - 2*((#REF! - #REF!)/6) )/5 , ( (#REF! + 4*AVERAGE(#REF!) + #REF!)/6 + 2*((#REF! - #REF!)/6) )/5 ) * ( ( ('PM (Расчеты)'!$C$22/8 + 'PM (Расчеты)'!$C$23/40) + 'PM (Расчеты)'!$C$21/100 + 'PM (Расчеты)'!$C$25/100 + 'PM (Расчеты)'!$C$26/100 ) + 1 ))) * 8 * 60 * 60 -> #REF! | J104: ='Оценка'!B107 -> QA | K104: =IF(A104<>"", TODAY() , "") -> 46121 | L104: =IF(A104<>"", TODAY() + (I104 /60/60) , "") -> #REF!
A105: ='Оценка'!C108 | B105: ='Оценка'!D108 | C105: =IF(A105<>"", 0, "") | D105: =IF(A105<>"", 0, "") | E105: =IF(A105<>"", 1, "") | F105: =IF(A105<>"", 1, "") | G105: =IF(A105<>"", 'Sales (Итоги оценки)'!$C$4, "") | H105: =IF(A105<>"", 1, "") | I105: =IF(OR(ISBLANK('Оценка'!F105), ISBLANK('Оценка'!G105)), "", (AVERAGE( ( ('Оценка'!F105 + 4*AVERAGE('Оценка'!F105:G105) + 'Оценка'!G105)/6 - 2*(('Оценка'!G105 - 'Оценка'!F105)/6) )/5 , ( ('Оценка'!F105 + 4*AVERAGE('Оценка'!F105:G105) + 'Оценка'!G105)/6 + 2*(('Оценка'!G105 - 'Оценка'!F105)/6) )/5 ) * ( ( ('PM (Расчеты)'!$C$22/8 + 'PM (Расчеты)'!$C$23/40) + 'PM (Расчеты)'!$C$21/100 + 'PM (Расчеты)'!$C$25/100 + 'PM (Расчеты)'!$C$26/100 ) + 1 ))) * 8 * 60 * 60 -> 138240 | J105: ='Оценка'!B108 | K105: =IF(A105<>"", TODAY() , "") | L105: =IF(A105<>"", TODAY() + (I105 /60/60) , "")
A106: ='Оценка'!C109 -> Сопровождение разработки, доработки UX/UI | B106: ='Оценка'!D109 | C106: =IF(A106<>"", 0, "") -> 0 | D106: =IF(A106<>"", 0, "") -> 0 | E106: =IF(A106<>"", 1, "") -> 1 | F106: =IF(A106<>"", 1, "") -> 1 | G106: =IF(A106<>"", 'Sales (Итоги оценки)'!$C$4, "") -> P2P платформа | H106: =IF(A106<>"", 1, "") -> 1 | I106: =IF(OR(ISBLANK(#REF!), ISBLANK(#REF!)), "", (AVERAGE( ( (#REF! + 4*AVERAGE(#REF!) + #REF!)/6 - 2*((#REF! - #REF!)/6) )/5 , ( (#REF! + 4*AVERAGE(#REF!) + #REF!)/6 + 2*((#REF! - #REF!)/6) )/5 ) * ( ( ('PM (Расчеты)'!$C$22/8 + 'PM (Расчеты)'!$C$23/40) + 'PM (Расчеты)'!$C$21/100 + 'PM (Расчеты)'!$C$25/100 + 'PM (Расчеты)'!$C$26/100 ) + 1 ))) * 8 * 60 * 60 -> #REF! | J106: ='Оценка'!B109 -> Аналитик | K106: =IF(A106<>"", TODAY() , "") -> 46121 | L106: =IF(A106<>"", TODAY() + (I106 /60/60) , "") -> #REF!
A107: ='Оценка'!C110 | B107: ='Оценка'!D110 | C107: =IF(A107<>"", 0, "") | D107: =IF(A107<>"", 0, "") | E107: =IF(A107<>"", 1, "") | F107: =IF(A107<>"", 1, "") | G107: =IF(A107<>"", 'Sales (Итоги оценки)'!$C$4, "") | H107: =IF(A107<>"", 1, "") | I107: =IF(OR(ISBLANK('Оценка'!F106), ISBLANK('Оценка'!G106)), "", (AVERAGE( ( ('Оценка'!F106 + 4*AVERAGE('Оценка'!F106:G106) + 'Оценка'!G106)/6 - 2*(('Оценка'!G106 - 'Оценка'!F106)/6) )/5 , ( ('Оценка'!F106 + 4*AVERAGE('Оценка'!F106:G106) + 'Оценка'!G106)/6 + 2*(('Оценка'!G106 - 'Оценка'!F106)/6) )/5 ) * ( ( ('PM (Расчеты)'!$C$22/8 + 'PM (Расчеты)'!$C$23/40) + 'PM (Расчеты)'!$C$21/100 + 'PM (Расчеты)'!$C$25/100 + 'PM (Расчеты)'!$C$26/100 ) + 1 ))) * 8 * 60 * 60 -> 0 | J107: ='Оценка'!B110 | K107: =IF(A107<>"", TODAY() , "") | L107: =IF(A107<>"", TODAY() + (I107 /60/60) , "")
A108: ='Оценка'!C111 -> телеграм интеграция | B108: ='Оценка'!D111 | C108: =IF(A108<>"", 0, "") -> 0 | D108: =IF(A108<>"", 0, "") -> 0 | E108: =IF(A108<>"", 1, "") -> 1 | F108: =IF(A108<>"", 1, "") -> 1 | G108: =IF(A108<>"", 'Sales (Итоги оценки)'!$C$4, "") -> P2P платформа | H108: =IF(A108<>"", 1, "") -> 1 | I108: =IF(OR(ISBLANK('Оценка'!F107), ISBLANK('Оценка'!G107)), "", (AVERAGE( ( ('Оценка'!F107 + 4*AVERAGE('Оценка'!F107:G107) + 'Оценка'!G107)/6 - 2*(('Оценка'!G107 - 'Оценка'!F107)/6) )/5 , ( ('Оценка'!F107 + 4*AVERAGE('Оценка'!F107:G107) + 'Оценка'!G107)/6 + 2*(('Оценка'!G107 - 'Оценка'!F107)/6) )/5 ) * ( ( ('PM (Расчеты)'!$C$22/8 + 'PM (Расчеты)'!$C$23/40) + 'PM (Расчеты)'!$C$21/100 + 'PM (Расчеты)'!$C$25/100 + 'PM (Расчеты)'!$C$26/100 ) + 1 ))) * 8 * 60 * 60 -> 0 | J108: ='Оценка'!B111 | K108: =IF(A108<>"", TODAY() , "") -> 46121 | L108: =IF(A108<>"", TODAY() + (I108 /60/60) , "") -> 46121
A109: ='Оценка'!C112 -> Сообщение в телеграм канал о появлении OTC сделок | B109: ='Оценка'!D112 -> появилось новая сделка в стакане | C109: =IF(A109<>"", 0, "") -> 0 | D109: =IF(A109<>"", 0, "") -> 0 | E109: =IF(A109<>"", 1, "") -> 1 | F109: =IF(A109<>"", 1, "") -> 1 | G109: =IF(A109<>"", 'Sales (Итоги оценки)'!$C$4, "") -> P2P платформа | H109: =IF(A109<>"", 1, "") -> 1 | I109: =IF(OR(ISBLANK('Оценка'!F108), ISBLANK('Оценка'!G108)), "", (AVERAGE( ( ('Оценка'!F108 + 4*AVERAGE('Оценка'!F108:G108) + 'Оценка'!G108)/6 - 2*(('Оценка'!G108 - 'Оценка'!F108)/6) )/5 , ( ('Оценка'!F108 + 4*AVERAGE('Оценка'!F108:G108) + 'Оценка'!G108)/6 + 2*(('Оценка'!G108 - 'Оценка'!F108)/6) )/5 ) * ( ( ('PM (Расчеты)'!$C$22/8 + 'PM (Расчеты)'!$C$23/40) + 'PM (Расчеты)'!$C$21/100 + 'PM (Расчеты)'!$C$25/100 + 'PM (Расчеты)'!$C$26/100 ) + 1 ))) * 8 * 60 * 60 -> 0 | J109: ='Оценка'!B112 -> Backend | K109: =IF(A109<>"", TODAY() , "") -> 46121 | L109: =IF(A109<>"", TODAY() + (I109 /60/60) , "") -> 46121
A110: ='Оценка'!C113 -> уведомление о статусе сделки в телеграм бота | B110: ='Оценка'!D113 -> при получении сообщений, при других сменах статуса, в бота куда подключится тейкер/мейкер придут сообщения. подключение опционально. авторизация через телегу тоже | C110: =IF(A110<>"", 0, "") -> 0 | D110: =IF(A110<>"", 0, "") -> 0 | E110: =IF(A110<>"", 1, "") -> 1 | F110: =IF(A110<>"", 1, "") -> 1 | G110: =IF(A110<>"", 'Sales (Итоги оценки)'!$C$4, "") -> P2P платформа | H110: =IF(A110<>"", 1, "") -> 1 | I110: =IF(OR(ISBLANK('Оценка'!F109), ISBLANK('Оценка'!G109)), "", (AVERAGE( ( ('Оценка'!F109 + 4*AVERAGE('Оценка'!F109:G109) + 'Оценка'!G109)/6 - 2*(('Оценка'!G109 - 'Оценка'!F109)/6) )/5 , ( ('Оценка'!F109 + 4*AVERAGE('Оценка'!F109:G109) + 'Оценка'!G109)/6 + 2*(('Оценка'!G109 - 'Оценка'!F109)/6) )/5 ) * ( ( ('PM (Расчеты)'!$C$22/8 + 'PM (Расчеты)'!$C$23/40) + 'PM (Расчеты)'!$C$21/100 + 'PM (Расчеты)'!$C$25/100 + 'PM (Расчеты)'!$C$26/100 ) + 1 ))) * 8 * 60 * 60 -> 138240 | J110: ='Оценка'!B113 -> Backend | K110: =IF(A110<>"", TODAY() , "") -> 46121 | L110: =IF(A110<>"", TODAY() + (I110 /60/60) , "") -> 46159.4
A111: ='Оценка'!C114 | B111: ='Оценка'!D114 | C111: =IF(A111<>"", 0, "") | D111: =IF(A111<>"", 0, "") | E111: =IF(A111<>"", 1, "") | F111: =IF(A111<>"", 1, "") | G111: =IF(A111<>"", 'Sales (Итоги оценки)'!$C$4, "") | H111: =IF(A111<>"", 1, "") | I111: =IF(OR(ISBLANK('Оценка'!F110), ISBLANK('Оценка'!G110)), "", (AVERAGE( ( ('Оценка'!F110 + 4*AVERAGE('Оценка'!F110:G110) + 'Оценка'!G110)/6 - 2*(('Оценка'!G110 - 'Оценка'!F110)/6) )/5 , ( ('Оценка'!F110 + 4*AVERAGE('Оценка'!F110:G110) + 'Оценка'!G110)/6 + 2*(('Оценка'!G110 - 'Оценка'!F110)/6) )/5 ) * ( ( ('PM (Расчеты)'!$C$22/8 + 'PM (Расчеты)'!$C$23/40) + 'PM (Расчеты)'!$C$21/100 + 'PM (Расчеты)'!$C$25/100 + 'PM (Расчеты)'!$C$26/100 ) + 1 ))) * 8 * 60 * 60 -> 0 | J111: ='Оценка'!B114 | K111: =IF(A111<>"", TODAY() , "") | L111: =IF(A111<>"", TODAY() + (I111 /60/60) , "")
A112: ='Оценка'!C115 | B112: ='Оценка'!D115 | C112: =IF(A112<>"", 0, "") | D112: =IF(A112<>"", 0, "") | E112: =IF(A112<>"", 1, "") | F112: =IF(A112<>"", 1, "") | G112: =IF(A112<>"", 'Sales (Итоги оценки)'!$C$4, "") | H112: =IF(A112<>"", 1, "") | I112: =IF(OR(ISBLANK('Оценка'!F111), ISBLANK('Оценка'!G111)), "", (AVERAGE( ( ('Оценка'!F111 + 4*AVERAGE('Оценка'!F111:G111) + 'Оценка'!G111)/6 - 2*(('Оценка'!G111 - 'Оценка'!F111)/6) )/5 , ( ('Оценка'!F111 + 4*AVERAGE('Оценка'!F111:G111) + 'Оценка'!G111)/6 + 2*(('Оценка'!G111 - 'Оценка'!F111)/6) )/5 ) * ( ( ('PM (Расчеты)'!$C$22/8 + 'PM (Расчеты)'!$C$23/40) + 'PM (Расчеты)'!$C$21/100 + 'PM (Расчеты)'!$C$25/100 + 'PM (Расчеты)'!$C$26/100 ) + 1 ))) * 8 * 60 * 60 -> 0 | J112: ='Оценка'!B115 | K112: =IF(A112<>"", TODAY() , "") | L112: =IF(A112<>"", TODAY() + (I112 /60/60) , "")
A113: ='Оценка'!C116 | B113: ='Оценка'!D116 | C113: =IF(A113<>"", 0, "") | D113: =IF(A113<>"", 0, "") | E113: =IF(A113<>"", 1, "") | F113: =IF(A113<>"", 1, "") | G113: =IF(A113<>"", 'Sales (Итоги оценки)'!$C$4, "") | H113: =IF(A113<>"", 1, "") | I113: =IF(OR(ISBLANK('Оценка'!F112), ISBLANK('Оценка'!G112)), "", (AVERAGE( ( ('Оценка'!F112 + 4*AVERAGE('Оценка'!F112:G112) + 'Оценка'!G112)/6 - 2*(('Оценка'!G112 - 'Оценка'!F112)/6) )/5 , ( ('Оценка'!F112 + 4*AVERAGE('Оценка'!F112:G112) + 'Оценка'!G112)/6 + 2*(('Оценка'!G112 - 'Оценка'!F112)/6) )/5 ) * ( ( ('PM (Расчеты)'!$C$22/8 + 'PM (Расчеты)'!$C$23/40) + 'PM (Расчеты)'!$C$21/100 + 'PM (Расчеты)'!$C$25/100 + 'PM (Расчеты)'!$C$26/100 ) + 1 ))) * 8 * 60 * 60 -> 6912 | J113: ='Оценка'!B116 | K113: =IF(A113<>"", TODAY() , "") | L113: =IF(A113<>"", TODAY() + (I113 /60/60) , "")
A114: ='Оценка'!C117 | B114: ='Оценка'!D117 | C114: =IF(A114<>"", 0, "") | D114: =IF(A114<>"", 0, "") | E114: =IF(A114<>"", 1, "") | F114: =IF(A114<>"", 1, "") | G114: =IF(A114<>"", 'Sales (Итоги оценки)'!$C$4, "") | H114: =IF(A114<>"", 1, "") | I114: =IF(OR(ISBLANK('Оценка'!F113), ISBLANK('Оценка'!G113)), "", (AVERAGE( ( ('Оценка'!F113 + 4*AVERAGE('Оценка'!F113:G113) + 'Оценка'!G113)/6 - 2*(('Оценка'!G113 - 'Оценка'!F113)/6) )/5 , ( ('Оценка'!F113 + 4*AVERAGE('Оценка'!F113:G113) + 'Оценка'!G113)/6 + 2*(('Оценка'!G113 - 'Оценка'!F113)/6) )/5 ) * ( ( ('PM (Расчеты)'!$C$22/8 + 'PM (Расчеты)'!$C$23/40) + 'PM (Расчеты)'!$C$21/100 + 'PM (Расчеты)'!$C$25/100 + 'PM (Расчеты)'!$C$26/100 ) + 1 ))) * 8 * 60 * 60 -> 13824 | J114: ='Оценка'!B117 | K114: =IF(A114<>"", TODAY() , "") | L114: =IF(A114<>"", TODAY() + (I114 /60/60) , "")
A115: ='Оценка'!C118 | B115: ='Оценка'!D118 | C115: =IF(A115<>"", 0, "") | D115: =IF(A115<>"", 0, "") | E115: =IF(A115<>"", 1, "") | F115: =IF(A115<>"", 1, "") | G115: =IF(A115<>"", 'Sales (Итоги оценки)'!$C$4, "") | H115: =IF(A115<>"", 1, "") | I115: =IF(OR(ISBLANK('Оценка'!F114), ISBLANK('Оценка'!G114)), "", (AVERAGE( ( ('Оценка'!F114 + 4*AVERAGE('Оценка'!F114:G114) + 'Оценка'!G114)/6 - 2*(('Оценка'!G114 - 'Оценка'!F114)/6) )/5 , ( ('Оценка'!F114 + 4*AVERAGE('Оценка'!F114:G114) + 'Оценка'!G114)/6 + 2*(('Оценка'!G114 - 'Оценка'!F114)/6) )/5 ) * ( ( ('PM (Расчеты)'!$C$22/8 + 'PM (Расчеты)'!$C$23/40) + 'PM (Расчеты)'!$C$21/100 + 'PM (Расчеты)'!$C$25/100 + 'PM (Расчеты)'!$C$26/100 ) + 1 ))) * 8 * 60 * 60 -> 0 | J115: ='Оценка'!B118 | K115: =IF(A115<>"", TODAY() , "") | L115: =IF(A115<>"", TODAY() + (I115 /60/60) , "")
A116: ='Оценка'!C119 | B116: ='Оценка'!D119 | C116: =IF(A116<>"", 0, "") | D116: =IF(A116<>"", 0, "") | E116: =IF(A116<>"", 1, "") | F116: =IF(A116<>"", 1, "") | G116: =IF(A116<>"", 'Sales (Итоги оценки)'!$C$4, "") | H116: =IF(A116<>"", 1, "") | I116: =IF(OR(ISBLANK('Оценка'!F115), ISBLANK('Оценка'!G115)), "", (AVERAGE( ( ('Оценка'!F115 + 4*AVERAGE('Оценка'!F115:G115) + 'Оценка'!G115)/6 - 2*(('Оценка'!G115 - 'Оценка'!F115)/6) )/5 , ( ('Оценка'!F115 + 4*AVERAGE('Оценка'!F115:G115) + 'Оценка'!G115)/6 + 2*(('Оценка'!G115 - 'Оценка'!F115)/6) )/5 ) * ( ( ('PM (Расчеты)'!$C$22/8 + 'PM (Расчеты)'!$C$23/40) + 'PM (Расчеты)'!$C$21/100 + 'PM (Расчеты)'!$C$25/100 + 'PM (Расчеты)'!$C$26/100 ) + 1 ))) * 8 * 60 * 60 -> 0 | J116: ='Оценка'!B119 | K116: =IF(A116<>"", TODAY() , "") | L116: =IF(A116<>"", TODAY() + (I116 /60/60) , "")
A117: ='Оценка'!C120 | B117: ='Оценка'!D120 | C117: =IF(A117<>"", 0, "") | D117: =IF(A117<>"", 0, "") | E117: =IF(A117<>"", 1, "") | F117: =IF(A117<>"", 1, "") | G117: =IF(A117<>"", 'Sales (Итоги оценки)'!$C$4, "") | H117: =IF(A117<>"", 1, "") | I117: =IF(OR(ISBLANK('Оценка'!F116), ISBLANK('Оценка'!G116)), "", (AVERAGE( ( ('Оценка'!F116 + 4*AVERAGE('Оценка'!F116:G116) + 'Оценка'!G116)/6 - 2*(('Оценка'!G116 - 'Оценка'!F116)/6) )/5 , ( ('Оценка'!F116 + 4*AVERAGE('Оценка'!F116:G116) + 'Оценка'!G116)/6 + 2*(('Оценка'!G116 - 'Оценка'!F116)/6) )/5 ) * ( ( ('PM (Расчеты)'!$C$22/8 + 'PM (Расчеты)'!$C$23/40) + 'PM (Расчеты)'!$C$21/100 + 'PM (Расчеты)'!$C$25/100 + 'PM (Расчеты)'!$C$26/100 ) + 1 ))) * 8 * 60 * 60 -> 0 | J117: ='Оценка'!B120 | K117: =IF(A117<>"", TODAY() , "") | L117: =IF(A117<>"", TODAY() + (I117 /60/60) , "")
A118: ='Оценка'!C121 | B118: ='Оценка'!D121 | C118: =IF(A118<>"", 0, "") | D118: =IF(A118<>"", 0, "") | E118: =IF(A118<>"", 1, "") | F118: =IF(A118<>"", 1, "") | G118: =IF(A118<>"", 'Sales (Итоги оценки)'!$C$4, "") | H118: =IF(A118<>"", 1, "") | I118: =IF(OR(ISBLANK('Оценка'!F117), ISBLANK('Оценка'!G117)), "", (AVERAGE( ( ('Оценка'!F117 + 4*AVERAGE('Оценка'!F117:G117) + 'Оценка'!G117)/6 - 2*(('Оценка'!G117 - 'Оценка'!F117)/6) )/5 , ( ('Оценка'!F117 + 4*AVERAGE('Оценка'!F117:G117) + 'Оценка'!G117)/6 + 2*(('Оценка'!G117 - 'Оценка'!F117)/6) )/5 ) * ( ( ('PM (Расчеты)'!$C$22/8 + 'PM (Расчеты)'!$C$23/40) + 'PM (Расчеты)'!$C$21/100 + 'PM (Расчеты)'!$C$25/100 + 'PM (Расчеты)'!$C$26/100 ) + 1 ))) * 8 * 60 * 60 -> 0 | J118: ='Оценка'!B121 | K118: =IF(A118<>"", TODAY() , "") | L118: =IF(A118<>"", TODAY() + (I118 /60/60) , "")
... A330: ='Оценка'!C333 | B330: ='Оценка'!D333 | C330: =IF(A330<>"", 0, "") | D330: =IF(A330<>"", 0, "") | E330: =IF(A330<>"", 1, "") | F330: =IF(A330<>"", 1, "") | G330: =IF(A330<>"", 'Sales (Итоги оценки)'!$C$4, "") | H330: =IF(A330<>"", 1, "") | I330: =IF(OR(ISBLANK('Оценка'!F329), ISBLANK('Оценка'!G329)), "", (AVERAGE( ( ('Оценка'!F329 + 4*AVERAGE('Оценка'!F329:G329) + 'Оценка'!G329)/6 - 2*(('Оценка'!G329 - 'Оценка'!F329)/6) )/5 , ( ('Оценка'!F329 + 4*AVERAGE('Оценка'!F329:G329) + 'Оценка'!G329)/6 + 2*(('Оценка'!G329 - 'Оценка'!F329)/6) )/5 ) * ( ( ('PM (Расчеты)'!$C$22/8 + 'PM (Расчеты)'!$C$23/40) + 'PM (Расчеты)'!$C$21/100 + 'PM (Расчеты)'!$C$25/100 + 'PM (Расчеты)'!$C$26/100 ) + 1 ))) * 8 * 60 * 60 -> 0 | J330: ='Оценка'!B333 | K330: =IF(A330<>"", TODAY() , "") | L330: =IF(A330<>"", TODAY() + (I330 /60/60) , "")
A331: ='Оценка'!C334 | B331: ='Оценка'!D334 | C331: =IF(A331<>"", 0, "") | D331: =IF(A331<>"", 0, "") | E331: =IF(A331<>"", 1, "") | F331: =IF(A331<>"", 1, "") | G331: =IF(A331<>"", 'Sales (Итоги оценки)'!$C$4, "") | H331: =IF(A331<>"", 1, "") | J331: ='Оценка'!B334 | K331: =IF(A331<>"", TODAY() , "") | L331: =IF(A331<>"", TODAY() + (I331 /60/60) , "")
A332: ='Оценка'!C335 | B332: ='Оценка'!D335 | C332: =IF(A332<>"", 0, "") | D332: =IF(A332<>"", 0, "") | E332: =IF(A332<>"", 1, "") | F332: =IF(A332<>"", 1, "") | G332: =IF(A332<>"", 'Sales (Итоги оценки)'!$C$4, "") | H332: =IF(A332<>"", 1, "") | J332: ='Оценка'!B335 | K332: =IF(A332<>"", TODAY() , "") | L332: =IF(A332<>"", TODAY() + (I332 /60/60) , "")
A333: ='Оценка'!C336 | B333: ='Оценка'!D336 | C333: =IF(A333<>"", 0, "") | D333: =IF(A333<>"", 0, "") | E333: =IF(A333<>"", 1, "") | F333: =IF(A333<>"", 1, "") | G333: =IF(A333<>"", 'Sales (Итоги оценки)'!$C$4, "") | H333: =IF(A333<>"", 1, "") | J333: ='Оценка'!B336 | K333: =IF(A333<>"", TODAY() , "") | L333: =IF(A333<>"", TODAY() + (I333 /60/60) , "")
A334: ='Оценка'!C337 | B334: ='Оценка'!D337 | C334: =IF(A334<>"", 0, "") | D334: =IF(A334<>"", 0, "") | E334: =IF(A334<>"", 1, "") | F334: =IF(A334<>"", 1, "") | G334: =IF(A334<>"", 'Sales (Итоги оценки)'!$C$4, "") | H334: =IF(A334<>"", 1, "") | J334: ='Оценка'!B337 | K334: =IF(A334<>"", TODAY() , "") | L334: =IF(A334<>"", TODAY() + (I334 /60/60) , "")
A335: ='Оценка'!C338 | B335: ='Оценка'!D338 | C335: =IF(A335<>"", 0, "") | D335: =IF(A335<>"", 0, "") | E335: =IF(A335<>"", 1, "") | F335: =IF(A335<>"", 1, "") | G335: =IF(A335<>"", 'Sales (Итоги оценки)'!$C$4, "") | H335: =IF(A335<>"", 1, "") | J335: ='Оценка'!B338 | K335: =IF(A335<>"", TODAY() , "") | L335: =IF(A335<>"", TODAY() + (I335 /60/60) , "")
A336: ='Оценка'!C339 | B336: ='Оценка'!D339 | C336: =IF(A336<>"", 0, "") | D336: =IF(A336<>"", 0, "") | E336: =IF(A336<>"", 1, "") | F336: =IF(A336<>"", 1, "") | G336: =IF(A336<>"", 'Sales (Итоги оценки)'!$C$4, "") | H336: =IF(A336<>"", 1, "") | J336: ='Оценка'!B339 | K336: =IF(A336<>"", TODAY() , "") | L336: =IF(A336<>"", TODAY() + (I336 /60/60) , "")
A337: ='Оценка'!C340 | B337: ='Оценка'!D340 | C337: =IF(A337<>"", 0, "") | D337: =IF(A337<>"", 0, "") | E337: =IF(A337<>"", 1, "") | F337: =IF(A337<>"", 1, "") | G337: =IF(A337<>"", 'Sales (Итоги оценки)'!$C$4, "") | H337: =IF(A337<>"", 1, "") | J337: ='Оценка'!B340 | K337: =IF(A337<>"", TODAY() , "") | L337: =IF(A337<>"", TODAY() + (I337 /60/60) , "")
A338: ='Оценка'!C341 | B338: ='Оценка'!D341 | C338: =IF(A338<>"", 0, "") | D338: =IF(A338<>"", 0, "") | E338: =IF(A338<>"", 1, "") | F338: =IF(A338<>"", 1, "") | G338: =IF(A338<>"", 'Sales (Итоги оценки)'!$C$4, "") | H338: =IF(A338<>"", 1, "") | J338: ='Оценка'!B341 | K338: =IF(A338<>"", TODAY() , "") | L338: =IF(A338<>"", TODAY() + (I338 /60/60) , "")
A339: ='Оценка'!C342 | B339: ='Оценка'!D342 | C339: =IF(A339<>"", 0, "") | D339: =IF(A339<>"", 0, "") | E339: =IF(A339<>"", 1, "") | F339: =IF(A339<>"", 1, "") | G339: =IF(A339<>"", 'Sales (Итоги оценки)'!$C$4, "") | H339: =IF(A339<>"", 1, "") | J339: ='Оценка'!B342 | K339: =IF(A339<>"", TODAY() , "") | L339: =IF(A339<>"", TODAY() + (I339 /60/60) , "")
A340: ='Оценка'!C343 | B340: ='Оценка'!D343 | C340: =IF(A340<>"", 0, "") | D340: =IF(A340<>"", 0, "") | E340: =IF(A340<>"", 1, "") | F340: =IF(A340<>"", 1, "") | G340: =IF(A340<>"", 'Sales (Итоги оценки)'!$C$4, "") | H340: =IF(A340<>"", 1, "") | J340: ='Оценка'!B343 | K340: =IF(A340<>"", TODAY() , "") | L340: =IF(A340<>"", TODAY() + (I340 /60/60) , "")
A341: ='Оценка'!C344 | B341: ='Оценка'!D344 | C341: =IF(A341<>"", 0, "") | D341: =IF(A341<>"", 0, "") | E341: =IF(A341<>"", 1, "") | F341: =IF(A341<>"", 1, "") | G341: =IF(A341<>"", 'Sales (Итоги оценки)'!$C$4, "") | H341: =IF(A341<>"", 1, "") | J341: ='Оценка'!B344 | K341: =IF(A341<>"", TODAY() , "") | L341: =IF(A341<>"", TODAY() + (I341 /60/60) , "")
A342: ='Оценка'!C345 | B342: ='Оценка'!D345 | C342: =IF(A342<>"", 0, "") | D342: =IF(A342<>"", 0, "") | E342: =IF(A342<>"", 1, "") | F342: =IF(A342<>"", 1, "") | G342: =IF(A342<>"", 'Sales (Итоги оценки)'!$C$4, "") | H342: =IF(A342<>"", 1, "") | J342: ='Оценка'!B345 | K342: =IF(A342<>"", TODAY() , "") | L342: =IF(A342<>"", TODAY() + (I342 /60/60) , "")
... A345: ='Оценка'!C348 | B345: ='Оценка'!D348 | C345: =IF(A345<>"", 0, "") | D345: =IF(A345<>"", 0, "") | E345: =IF(A345<>"", 1, "") | F345: =IF(A345<>"", 1, "") | G345: =IF(A345<>"", 'Sales (Итоги оценки)'!$C$4, "") | H345: =IF(A345<>"", 1, "") | J345: ='Оценка'!B348 | K345: =IF(A345<>"", TODAY() , "") | L345: =IF(A345<>"", TODAY() + (I345 /60/60) , "")
A346: ='Оценка'!C349 | B346: ='Оценка'!D349 | C346: =IF(A346<>"", 0, "") | D346: =IF(A346<>"", 0, "") | E346: =IF(A346<>"", 1, "") | F346: =IF(A346<>"", 1, "") | G346: =IF(A346<>"", 'Sales (Итоги оценки)'!$C$4, "") | H346: =IF(A346<>"", 1, "") | J346: ='Оценка'!B349 | L346: =IF(A346<>"", TODAY() + (I346 /60/60) , "")
A347: ='Оценка'!C350 | B347: ='Оценка'!D350 | C347: =IF(A347<>"", 0, "") | D347: =IF(A347<>"", 0, "") | E347: =IF(A347<>"", 1, "") | F347: =IF(A347<>"", 1, "") | G347: =IF(A347<>"", 'Sales (Итоги оценки)'!$C$4, "") | H347: =IF(A347<>"", 1, "") | J347: ='Оценка'!B350 | L347: =IF(A347<>"", TODAY() + (I347 /60/60) , "")
A348: ='Оценка'!C351 | B348: ='Оценка'!D351 | C348: =IF(A348<>"", 0, "") | D348: =IF(A348<>"", 0, "") | E348: =IF(A348<>"", 1, "") | F348: =IF(A348<>"", 1, "") | G348: =IF(A348<>"", 'Sales (Итоги оценки)'!$C$4, "") | H348: =IF(A348<>"", 1, "") | J348: ='Оценка'!B351 | L348: =IF(A348<>"", TODAY() + (I348 /60/60) , "")
A349: ='Оценка'!C352 | B349: ='Оценка'!D352 | C349: =IF(A349<>"", 0, "") | D349: =IF(A349<>"", 0, "") | E349: =IF(A349<>"", 1, "") | F349: =IF(A349<>"", 1, "") | G349: =IF(A349<>"", 'Sales (Итоги оценки)'!$C$4, "") | H349: =IF(A349<>"", 1, "") | J349: ='Оценка'!B352 | L349: =IF(A349<>"", TODAY() + (I349 /60/60) , "")
A350: ='Оценка'!C353 | B350: ='Оценка'!D353 | C350: =IF(A350<>"", 0, "") | D350: =IF(A350<>"", 0, "") | E350: =IF(A350<>"", 1, "") | F350: =IF(A350<>"", 1, "") | G350: =IF(A350<>"", 'Sales (Итоги оценки)'!$C$4, "") | H350: =IF(A350<>"", 1, "") | J350: ='Оценка'!B353 | L350: =IF(A350<>"", TODAY() + (I350 /60/60) , "")
A351: ='Оценка'!C354 | B351: ='Оценка'!D354 | C351: =IF(A351<>"", 0, "") | D351: =IF(A351<>"", 0, "") | E351: =IF(A351<>"", 1, "") | F351: =IF(A351<>"", 1, "") | G351: =IF(A351<>"", 'Sales (Итоги оценки)'!$C$4, "") | H351: =IF(A351<>"", 1, "") | J351: ='Оценка'!B354 | L351: =IF(A351<>"", TODAY() + (I351 /60/60) , "")
A352: ='Оценка'!C355 | B352: ='Оценка'!D355 | C352: =IF(A352<>"", 0, "") | D352: =IF(A352<>"", 0, "") | E352: =IF(A352<>"", 1, "") | F352: =IF(A352<>"", 1, "") | G352: =IF(A352<>"", 'Sales (Итоги оценки)'!$C$4, "") | H352: =IF(A352<>"", 1, "") | J352: ='Оценка'!B355 | L352: =IF(A352<>"", TODAY() + (I352 /60/60) , "")
A353: ='Оценка'!C356 | B353: ='Оценка'!D356 | C353: =IF(A353<>"", 0, "") | D353: =IF(A353<>"", 0, "") | E353: =IF(A353<>"", 1, "") | F353: =IF(A353<>"", 1, "") | G353: =IF(A353<>"", 'Sales (Итоги оценки)'!$C$4, "") | H353: =IF(A353<>"", 1, "") | J353: ='Оценка'!B356 | L353: =IF(A353<>"", TODAY() + (I353 /60/60) , "")
A354: ='Оценка'!C357 | B354: ='Оценка'!D357 | C354: =IF(A354<>"", 0, "") | D354: =IF(A354<>"", 0, "") | E354: =IF(A354<>"", 1, "") | F354: =IF(A354<>"", 1, "") | G354: =IF(A354<>"", 'Sales (Итоги оценки)'!$C$4, "") | H354: =IF(A354<>"", 1, "") | J354: ='Оценка'!B357 | L354: =IF(A354<>"", TODAY() + (I354 /60/60) , "")
A355: ='Оценка'!C358 | B355: ='Оценка'!D358 | C355: =IF(A355<>"", 0, "") | D355: =IF(A355<>"", 0, "") | E355: =IF(A355<>"", 1, "") | F355: =IF(A355<>"", 1, "") | G355: =IF(A355<>"", 'Sales (Итоги оценки)'!$C$4, "") | H355: =IF(A355<>"", 1, "") | J355: ='Оценка'!B358 | L355: =IF(A355<>"", TODAY() + (I355 /60/60) , "")
...

Sheet Чек лист Задач
B1: Вид работ | C1: Задача | D1: Комментарий | E1: Риск | F1: Дней первичных минимум | G1: Дней первичных максимум
B2: Дизайн | C2: Получение задачи | D2: Этот этап помогает в понимании: для кого разрабатывается продукт / какие задачи он будет решать / какие могут быть ограничения / какая будет структура и объем проработки. | F2: 1 | G2: 2
B3: Дизайн | C3: Проработка сценариев пользователя | D3: (основной, второстепенные, экстренные): основные шаги, целевое действие, способ перехода к следующему шагу | F3: 2 | G3: 3
B4: Дизайн | C4: Прототипирование | D4: На основе сценария и полученных данных выстраивается примерное отображение функционала и количество экранов продукта.
B5: Дизайн | C5: Визуальное решение | D5: Поиск визуального решения на основе референсов, брендбука, ожиданий клиента и ЦА | F5: 1 | G5: 2
B6: Дизайн | D6: Составление мудборда, подбор референсов и стилистики | F6: 1 | G6: 2
B7: Дизайн | C7: Отрисовка UI кита (дизайн-система) | D7: Набор базовых элементов интерфейса, которые будут применятся дальше в дизайне и вёрстке. На основе этой системы можно масштабировать дизайн продукта | F7: 2 | G7: 3
B8: Дизайн | C8: Отрисовка экранов в соответствии с дизайн системой | D8: Зависит от количества экранов | F8: 7 | G8: 10
B9: Фронтенд | C9: Получение задачи и первичное знакомство с проектом | D9: Изучение ТЗ, макетов, функциональных требований | F9: 1 | G9: 2
B10: Фронтенд | C10: Изучение специфичных технологий для проекта | D10: Если используются технологии, с которыми разработчик ранее не работал | F10: 1 | G10: 2
B11: Фронтенд | C11: Базовая настройка проекта | D11: Настройка сборки, лейаутов, проектирование архитектуры | F11: 1 | G11: 1.5
B12: Фронтенд | C12: Настройка деплоя | D12: Сборка и деплой приложения | F12: 0.5 | G12: 1
B13: Фронтенд | C13: Работа с UI-Kit | D13: Проработка элементов для использования их по всему проекту | F13: 1.5 | G13: 2
B14: Бекенд | C14: Получение задачи и первичное знакомство с проектом | D14: Изучение ТЗ, макетов, функциональных требований | F14: 1 | G14: 2
B15: Бекенд | C15: Изучение специфичных технологий для проекта | D15: Если используются технологии, с которыми разработчик ранее не работал | F15: 1 | G15: 2
B16: Бекенд | C16: Базовая настройка проекта | F16: 1 | G16: 2
B17: Бекенд | C17: Деплой на стейджинг | F17: 1 | G17: 2
B18: Тестирование | C18: Изучение проекта | D18: Первичное знакомство с проектом | F18: 1 | G18: 1.5
B19: Тестирование | C19: Тестирование технического задания | D19: Выявление неточностей, белых пятен, недостаточного описания | F19: 1 | G19: 2
B20: Тестирование | C20: Тестирование макетов | D20: Сравнение макетов с требованиями ТЗ | F20: 1 | G20: 2
B21: Тестирование | C21: Составление тест-плана и тест-кейсов | D21: Проработка кейсов поведения пользователя, планирование тестирования | F21: 1 | G21: 2
B22: Тестирование | C22: Ручное тестирование | D22: Проверка тест-кейсов и тестирование разработанного ПО на соответствие макетам. Зависит от количества экранов | F22: 5 | G22: 10
B23: Смарт контракты | C23: тест | D23: тест | F23: 1 | G23: 1
C24: Планирование, учет рабочего времени, контроль бюджета;
C25: Проектная, финансовая и прочая отчетность;
B26: Дизайн | C26: Прояснение и обновление требований и дизайнов;
B27: Дизайн | C27: Мультиязычность;
C28: Подготовка демо данных и окружения, подготовка и проведение демо;
C29: Обновление документации после изменений в коде;
C30: Сама оценка (за нее в конце концов тоже кто-то должен заплатить);
C31: различные виды тестирования, помимо функционального;
C32: получение доступов и простои из-за их отсутствия;
